Workbook

Sheet Authorization Required

Sheet directory
A1: id_no | B1: =IFERROR(__xludf.DUMMYFUNCTION("query(Data!A:AD,""Select U, B, C, D, E, F, G, H, AB, AC, J, K, L, M, N, O, P, R, S, T, V, W, X, Y, Z, AA, AD Order by B, K"")"),"client_zip_codes") -> client_zip_codes | C1: =IFERROR(__xludf.DUMMYFUNCTION("""COMPUTED_VALUE"""),"organization") -> organization | D1: =IFERROR(__xludf.DUMMYFUNCTION("""COMPUTED_VALUE"""),"org_address1") -> org_address1 | E1: =IFERROR(__xludf.DUMMYFUNCTION("""COMPUTED_VALUE"""),"org_address2") -> org_address2 | F1: =IFERROR(__xludf.DUMMYFUNCTION("""COMPUTED_VALUE"""),"org_city") -> org_city | G1: =IFERROR(__xludf.DUMMYFUNCTION("""COMPUTED_VALUE"""),"org_state") -> org_state | H1: =IFERROR(__xludf.DUMMYFUNCTION("""COMPUTED_VALUE"""),"org_zip_code") -> org_zip_code | I1: =IFERROR(__xludf.DUMMYFUNCTION("""COMPUTED_VALUE"""),"org_telephone") -> org_telephone | J1: =IFERROR(__xludf.DUMMYFUNCTION("""COMPUTED_VALUE"""),"org_coordinates") -> org_coordinates | K1: =IFERROR(__xludf.DUMMYFUNCTION("""COMPUTED_VALUE"""),"org_hours") -> org_hours | L1: =IFERROR(__xludf.DUMMYFUNCTION("""COMPUTED_VALUE"""),"hours_notes") -> hours_notes | M1: =IFERROR(__xludf.DUMMYFUNCTION("""COMPUTED_VALUE"""),"assist_id") -> assist_id | N1: =IFERROR(__xludf.DUMMYFUNCTION("""COMPUTED_VALUE"""),"assistance") -> assistance | O1: =IFERROR(__xludf.DUMMYFUNCTION("""COMPUTED_VALUE"""),"status_id") -> status_id | P1: =IFERROR(__xludf.DUMMYFUNCTION("""COMPUTED_VALUE"""),"status") -> status | Q1: =IFERROR(__xludf.DUMMYFUNCTION("""COMPUTED_VALUE"""),"status_date") -> status_date | R1: =IFERROR(__xludf.DUMMYFUNCTION("""COMPUTED_VALUE"""),"status_text") -> status_text | S1: =IFERROR(__xludf.DUMMYFUNCTION("""COMPUTED_VALUE"""),"requirements") -> requirements | T1: =IFERROR(__xludf.DUMMYFUNCTION("""COMPUTED_VALUE"""),"is_first_bold") -> is_first_bold | U1: =IFERROR(__xludf.DUMMYFUNCTION("""COMPUTED_VALUE"""),"is_first_red") -> is_first_red | V1: =IFERROR(__xludf.DUMMYFUNCTION("""COMPUTED_VALUE"""),"webpage") -> webpage | W1: =IFERROR(__xludf.DUMMYFUNCTION("""COMPUTED_VALUE"""),"googlemaps") -> googlemaps | X1: =IFERROR(__xludf.DUMMYFUNCTION("""COMPUTED_VALUE"""),"org_email") -> org_email | Y1: =IFERROR(__xludf.DUMMYFUNCTION("""COMPUTED_VALUE"""),"org_county") -> org_county | Z1: =IFERROR(__xludf.DUMMYFUNCTION("""COMPUTED_VALUE"""),"zip_neighborhoods") -> zip_neighborhoods | AA1: =IFERROR(__xludf.DUMMYFUNCTION("""COMPUTED_VALUE"""),"org_parent") -> org_parent | AB1: =IFERROR(__xludf.DUMMYFUNCTION("""COMPUTED_VALUE"""),"org_neighborhood") -> org_neighborhood
A2: {=IF(ISBLANK(B2:B1999), "", ROW(B2:B1999)-1)} -> 1 | B2: =IFERROR(__xludf.DUMMYFUNCTION("""COMPUTED_VALUE"""),"[""77002"", ""77003"", ""77004"", ""77005"", ""77006"", ""77007"", ""77008"", ""77009"", ""77010"", ""77011"", ""77012"", ""77013"", ""77014"", ""77015"", ""77016"", ""77017"", ""77018"", ""77019"", ""77020"", ""77021"", ""77022"", ""77023"", ""77024"", "&"""77025"", ""77026"", ""77027"", ""77028"", ""77029"", ""77030"", ""77031"", ""77032"", ""77033"", ""77034"", ""77035"", ""77036"", ""77037"", ""77038"", ""77039"", ""77040"", ""77041"", ""77042"", ""77043"", ""77044"", ""77045"", ""77046"", ""77047"", """&"77048"", ""77049"", ""77050"", ""77051"", ""77053"", ""77054"", ""77055"", ""77056"", ""77057"", ""77058"", ""77059"", ""77060"", ""77061"", ""77062"", ""77063"", ""77064"", ""77065"", ""77066"", ""77067"", ""77068"", ""77069"", ""77070"", ""77071"", ""77"&"072"", ""77073"", ""77074"", ""77075"", ""77076"", ""77077"", ""77078"", ""77079"", ""77080"", ""77081"", ""77082"", ""77083"", ""77084"", ""77085"", ""77086"", ""77087"", ""77088"", ""77089"", ""77090"", ""77091"", ""77092"", ""77093"", ""77094"", ""7709"&"5"", ""77096"", ""77098"", ""77099"", ""77242"", ""77257"", ""77277"", ""77279"", ""77336"", ""77338"", ""77339"", ""77345"", ""77346"", ""77347"", ""77357"", ""77365"", ""77373"", ""77375"", ""77377"", ""77379"", ""77383"", ""77387"", ""77388"", ""77389"&""", ""77393"", ""77396"", ""77401"", ""77406"", ""77407"", ""77410"", ""77417"", ""77423"", ""77429"", ""77430"", ""77433"", ""77441"", ""77444"", ""77447"", ""77449"", ""77450"", ""77451"", ""77459"", ""77461"", ""77464"", ""77469"", ""77471"", ""77476"""&", ""77477"", ""77478"", ""77479"", ""77481"", ""77484"", ""77485"", ""77489"", ""77493"", ""77494"", ""77498"", ""77501"", ""77502"", ""77503"", ""77504"", ""77505"", ""77506"", ""77507"", ""77508"", ""77520"", ""77521"", ""77530"", ""77532"", ""77535"", "&"""77536"", ""77545"", ""77546"", ""77547"", ""77562"", ""77571"", ""77581"", ""77583"", ""77584"", ""77586"", ""77587"", ""77598""]") -> ["77002", "77003", "77004", "77005", "77006", "77007", "77008", "77009", "77010", "77011", "77012", "77013", "77014", "77015", "77016", "77017", "77018", "77019", "77020", "77021", "77022", "77023", "77024", "77025", "77026", "77027", "77028", "77029", "77030", "77031", "77032", "77033", "77034", "77035", "77036", "77037", "77038", "77039", "77040", "77041", "77042", "77043", "77044", "77045", "77046", "77047", "77048", "77049", "77050", "77051", "77053", "77054", "77055", "77056", "77057", "77058", "77059", "77060", "77061", "77062", "77063", "77064", "77065", "77066", "77067", "77068", "77069", "77070", "77071", "77072", "77073", "77074", "77075", "77076", "77077", "77078", "77079", "77080", "77081", "77082", "77083", "77084", "77085", "77086", "77087", "77088", "77089", "77090", "77091", "77092", "77093", "77094", "77095", "77096", "77098", "77099", "77242", "77257", "77277", "77279", "77336", "77338", "77339", "77345", "77346", "77347", "77357", "77365", "77373", "77375", "77377", "77379", "77383", "77387", "77388", "77389", "77393", "77396", "77401", "77406", "77407", "77410", "77417", "77423", "77429", "77430", "77433", "77441", "77444", "77447", "77449", "77450", "77451", "77459", "77461", "77464", "77469", "77471", "77476", "77477", "77478", "77479", "77481", "77484", "77485", "77489", "77493", "77494", "77498", "77501", "77502", "77503", "77504", "77505", "77506", "77507", "77508", "77520", "77521", "77530", "77532", "77535", "77536", "77545", "77546", "77547", "77562", "77571", "77581", "77583", "77584", "77586", "77587", "77598"] | C2: =IFERROR(__xludf.DUMMYFUNCTION("""COMPUTED_VALUE"""),"3 ""A"" Bereavement Foundation (3ABF)") -> 3 "A" Bereavement Foundation (3ABF) | D2: =IFERROR(__xludf.DUMMYFUNCTION("""COMPUTED_VALUE"""),"5330 Griggs Road") -> 5330 Griggs Road | E2: =IFERROR(__xludf.DUMMYFUNCTION("""COMPUTED_VALUE"""),"Suite A108") -> Suite A108 | F2: =IFERROR(__xludf.DUMMYFUNCTION("""COMPUTED_VALUE"""),"Houston") -> Houston | G2: =IFERROR(__xludf.DUMMYFUNCTION("""COMPUTED_VALUE"""),"TX") -> TX | H2: =IFERROR(__xludf.DUMMYFUNCTION("""COMPUTED_VALUE"""),"77021") -> 77021 | I2: =IFERROR(__xludf.DUMMYFUNCTION("""COMPUTED_VALUE"""),"713-649-3232") -> 713-649-3232 | J2: =IFERROR(__xludf.DUMMYFUNCTION("""COMPUTED_VALUE"""),"29.6967871212121, -95.3336860909091") -> 29.6967871212121, -95.3336860909091 | K2: =IFERROR(__xludf.DUMMYFUNCTION("""COMPUTED_VALUE"""),"{""regular"":[{""days"":[""Mo"",""Tu"",""We"",""Th"",""Fr""],""open"":""09:00"",""close"":""17:00""}]}") -> {"regular":[{"days":["Mo","Tu","We","Th","Fr"],"open":"09:00","close":"17:00"}]} | M2: =IFERROR(__xludf.DUMMYFUNCTION("""COMPUTED_VALUE"""),65.0) -> 65 | N2: =IFERROR(__xludf.DUMMYFUNCTION("""COMPUTED_VALUE"""),"Other") -> Other | O2: =IFERROR(__xludf.DUMMYFUNCTION("""COMPUTED_VALUE"""),1.0) -> 1 | P2: =IFERROR(__xludf.DUMMYFUNCTION("""COMPUTED_VALUE"""),"ACTIVE") -> ACTIVE | Q2: =IFERROR(__xludf.DUMMYFUNCTION("""COMPUTED_VALUE"""),45789.0) -> 45789 | R2: =IFERROR(__xludf.DUMMYFUNCTION("""COMPUTED_VALUE"""),"Verified online") -> Verified online | S2: =IFERROR(__xludf.DUMMYFUNCTION("""COMPUTED_VALUE"""),"Financial assistance for funeral services. Needs based. Financial verification required. Funeral consultations. Grief counseling. Aftercare services") -> Financial assistance for funeral services. Needs based. Financial verification required. Funeral consultations. Grief counseling. Aftercare services | T2: =IFERROR(__xludf.DUMMYFUNCTION("""COMPUTED_VALUE"""),FALSE) -> FALSE | U2: =IFERROR(__xludf.DUMMYFUNCTION("""COMPUTED_VALUE"""),FALSE) -> FALSE | V2: =IFERROR(__xludf.DUMMYFUNCTION("""COMPUTED_VALUE"""),"https://3abereavement.weebly.com/") -> https://3abereavement.weebly.com/ | W2: =IFERROR(__xludf.DUMMYFUNCTION("""COMPUTED_VALUE"""),"https://www.google.com/maps/place/Three+A+Bereavement/@29.6962313,-95.3378945,16z/data=!3m1!4b1!4m6!3m5!1s0x8640be3dadb801b5:0x44b0b287f8f22ef6!8m2!3d29.6962267!4d-95.3353142!16s%2Fg%2F1tlqqcg1?entry=ttu&g_ep=EgoyMDI1MDUwNy4wIKXMDSoASAFQAw%3D%3D") -> https://www.google.com/maps/place/Three+A+Bereavement/@29.6962313,-95.3378945,16z/data=!3m1!4b1!4m6!3m5!1s0x8640be3dadb801b5:0x44b0b287f8f22ef6!8m2!3d29.6962267!4d-95.3353142!16s%2Fg%2F1tlqqcg1?entry=ttu&g_ep=EgoyMDI1MDUwNy4wIKXMDSoASAFQAw%3D%3D | Y2: =IFERROR(__xludf.DUMMYFUNCTION("""COMPUTED_VALUE"""),"Houston") -> Houston | Z2: =IFERROR(__xludf.DUMMYFUNCTION("""COMPUTED_VALUE"""),"MacGregor, Riverside Terrace, South Side") -> MacGregor, Riverside Terrace, South Side | AA2: =IFERROR(__xludf.DUMMYFUNCTION("""COMPUTED_VALUE"""),"3 ""A"" Bereavement Foundation (3ABF)") -> 3 "A" Bereavement Foundation (3ABF) | AB2: =IFERROR(__xludf.DUMMYFUNCTION("""COMPUTED_VALUE"""),"South Side") -> South Side
A3: 2 | B3: =IFERROR(__xludf.DUMMYFUNCTION("""COMPUTED_VALUE"""),"[""99999""]") -> ["99999"] | C3: =IFERROR(__xludf.DUMMYFUNCTION("""COMPUTED_VALUE"""),"A Touch of God's Love Outreach") -> A Touch of God's Love Outreach | D3: =IFERROR(__xludf.DUMMYFUNCTION("""COMPUTED_VALUE"""),"10103 Fondren Road") -> 10103 Fondren Road | E3: =IFERROR(__xludf.DUMMYFUNCTION("""COMPUTED_VALUE"""),"Suit 420") -> Suit 420 | F3: =IFERROR(__xludf.DUMMYFUNCTION("""COMPUTED_VALUE"""),"Houston") -> Houston | G3: =IFERROR(__xludf.DUMMYFUNCTION("""COMPUTED_VALUE"""),"TX") -> TX | H3: =IFERROR(__xludf.DUMMYFUNCTION("""COMPUTED_VALUE"""),"77096") -> 77096 | I3: =IFERROR(__xludf.DUMMYFUNCTION("""COMPUTED_VALUE"""),"346-701-8094") -> 346-701-8094 | J3: =IFERROR(__xludf.DUMMYFUNCTION("""COMPUTED_VALUE"""),"29.669937, -95.508457") -> 29.669937, -95.508457 | M3: =IFERROR(__xludf.DUMMYFUNCTION("""COMPUTED_VALUE"""),56.0) -> 56 | N3: =IFERROR(__xludf.DUMMYFUNCTION("""COMPUTED_VALUE"""),"Veterans") -> Veterans | O3: =IFERROR(__xludf.DUMMYFUNCTION("""COMPUTED_VALUE"""),4.0) -> 4 | P3: =IFERROR(__xludf.DUMMYFUNCTION("""COMPUTED_VALUE"""),"CLOSED") -> CLOSED | Q3: =IFERROR(__xludf.DUMMYFUNCTION("""COMPUTED_VALUE"""),45670.0) -> 45670 | R3: =IFERROR(__xludf.DUMMYFUNCTION("""COMPUTED_VALUE"""),"Phone disconnected") -> Phone disconnected | S3: =IFERROR(__xludf.DUMMYFUNCTION("""COMPUTED_VALUE"""),"Financial assistance with utilities, food, Medical - Primary Care and Handyman for Veterans, Senior Citizens and Disabled") -> Financial assistance with utilities, food, Medical - Primary Care and Handyman for Veterans, Senior Citizens and Disabled | T3: =IFERROR(__xludf.DUMMYFUNCTION("""COMPUTED_VALUE"""),FALSE) -> FALSE | U3: =IFERROR(__xludf.DUMMYFUNCTION("""COMPUTED_VALUE"""),FALSE) -> FALSE | W3: =IFERROR(__xludf.DUMMYFUNCTION("""COMPUTED_VALUE"""),"https://maps.google.com/?q=A%20Touch%20of%20God's%20Love%20Outreach%2010103%20Fondren%20Suite%20420%20Houston%20TX%2077096") -> https://maps.google.com/?q=A%20Touch%20of%20God's%20Love%20Outreach%2010103%20Fondren%20Suite%20420%20Houston%20TX%2077096 | Y3: =IFERROR(__xludf.DUMMYFUNCTION("""COMPUTED_VALUE"""),"Houston") -> Houston | Z3: =IFERROR(__xludf.DUMMYFUNCTION("""COMPUTED_VALUE"""),"Brays Oaks, Meyerland, Westbury, Willow Meadows") -> Brays Oaks, Meyerland, Westbury, Willow Meadows | AA3: =IFERROR(__xludf.DUMMYFUNCTION("""COMPUTED_VALUE"""),"A Touch of God's Love Outreach") -> A Touch of God's Love Outreach | AB3: =IFERROR(__xludf.DUMMYFUNCTION("""COMPUTED_VALUE"""),"Brays Oaks") -> Brays Oaks
A4: 3 | B4: =IFERROR(__xludf.DUMMYFUNCTION("""COMPUTED_VALUE"""),"[""99999""]") -> ["99999"] | C4: =IFERROR(__xludf.DUMMYFUNCTION("""COMPUTED_VALUE"""),"AAMA George L Sanchez Charter School North") -> AAMA George L Sanchez Charter School North | D4: =IFERROR(__xludf.DUMMYFUNCTION("""COMPUTED_VALUE"""),"170 Rittenhouse Street") -> 170 Rittenhouse Street | F4: =IFERROR(__xludf.DUMMYFUNCTION("""COMPUTED_VALUE"""),"Houston") -> Houston | G4: =IFERROR(__xludf.DUMMYFUNCTION("""COMPUTED_VALUE"""),"TX") -> TX | H4: =IFERROR(__xludf.DUMMYFUNCTION("""COMPUTED_VALUE"""),"77076") -> 77076 | I4: =IFERROR(__xludf.DUMMYFUNCTION("""COMPUTED_VALUE"""),"832-622-0685") -> 832-622-0685 | J4: =IFERROR(__xludf.DUMMYFUNCTION("""COMPUTED_VALUE"""),"29.863906955714647, -95.37843356123234") -> 29.863906955714647, -95.37843356123234 | K4: =IFERROR(__xludf.DUMMYFUNCTION("""COMPUTED_VALUE"""),"{""regular"":[{""days"":[""Mo"",""Tu"",""We"",""Th"",""Fr""],""open"":null,""close"":null}]}") -> {"regular":[{"days":["Mo","Tu","We","Th","Fr"],"open":null,"close":null}]} | M4: =IFERROR(__xludf.DUMMYFUNCTION("""COMPUTED_VALUE"""),43.0) -> 43 | N4: =IFERROR(__xludf.DUMMYFUNCTION("""COMPUTED_VALUE"""),"Education - Children") -> Education - Children | O4: =IFERROR(__xludf.DUMMYFUNCTION("""COMPUTED_VALUE"""),1.0) -> 1 | P4: =IFERROR(__xludf.DUMMYFUNCTION("""COMPUTED_VALUE"""),"ACTIVE") -> ACTIVE | Q4: =IFERROR(__xludf.DUMMYFUNCTION("""COMPUTED_VALUE"""),45893.0) -> 45893 | S4: =IFERROR(__xludf.DUMMYFUNCTION("""COMPUTED_VALUE"""),"Middle thru High School. Free Tuition which includes free breakfast and lunch. Apply online") -> Middle thru High School. Free Tuition which includes free breakfast and lunch. Apply online | T4: =IFERROR(__xludf.DUMMYFUNCTION("""COMPUTED_VALUE"""),FALSE) -> FALSE | U4: =IFERROR(__xludf.DUMMYFUNCTION("""COMPUTED_VALUE"""),FALSE) -> FALSE | V4: =IFERROR(__xludf.DUMMYFUNCTION("""COMPUTED_VALUE"""),"https://www.aama.org/apps/pages/george-i-sanchez-charter-schools") -> https://www.aama.org/apps/pages/george-i-sanchez-charter-schools | W4: =IFERROR(__xludf.DUMMYFUNCTION("""COMPUTED_VALUE"""),"https://www.google.com/maps/place/Sanchez+Charter+Middle+and+High+School/@29.8635627,-95.3810943,16z/data=!3m1!4b1!4m6!3m5!1s0x8640b80004692007:0x8f00566854f63014!8m2!3d29.8635581!4d-95.3785194!16s%2Fg%2F11c600mkxz?entry=ttu&g_ep=EgoyMDI1MDgxOS4wIKXMDSoAS"&"AFQAw%3D%3D") -> https://www.google.com/maps/place/Sanchez+Charter+Middle+and+High+School/@29.8635627,-95.3810943,16z/data=!3m1!4b1!4m6!3m5!1s0x8640b80004692007:0x8f00566854f63014!8m2!3d29.8635581!4d-95.3785194!16s%2Fg%2F11c600mkxz?entry=ttu&g_ep=EgoyMDI1MDgxOS4wIKXMDSoASAFQAw%3D%3D | Y4: =IFERROR(__xludf.DUMMYFUNCTION("""COMPUTED_VALUE"""),"Houston") -> Houston | Z4: =IFERROR(__xludf.DUMMYFUNCTION("""COMPUTED_VALUE"""),"Independence Heights, Northline, Northside / Northline") -> Independence Heights, Northline, Northside / Northline | AA4: =IFERROR(__xludf.DUMMYFUNCTION("""COMPUTED_VALUE"""),"Association for Advancement of Mexican Americans (AAMA)") -> Association for Advancement of Mexican Americans (AAMA) | AB4: =IFERROR(__xludf.DUMMYFUNCTION("""COMPUTED_VALUE"""),"Northside / Northline") -> Northside / Northline
A5: 4 | B5: =IFERROR(__xludf.DUMMYFUNCTION("""COMPUTED_VALUE"""),"[""99999""]") -> ["99999"] | C5: =IFERROR(__xludf.DUMMYFUNCTION("""COMPUTED_VALUE"""),"AAMA George L Sanchez Charter School South") -> AAMA George L Sanchez Charter School South | D5: =IFERROR(__xludf.DUMMYFUNCTION("""COMPUTED_VALUE"""),"6001 Gulf Fwy") -> 6001 Gulf Fwy | F5: =IFERROR(__xludf.DUMMYFUNCTION("""COMPUTED_VALUE"""),"Houston") -> Houston | G5: =IFERROR(__xludf.DUMMYFUNCTION("""COMPUTED_VALUE"""),"TX") -> TX | H5: =IFERROR(__xludf.DUMMYFUNCTION("""COMPUTED_VALUE"""),"77023") -> 77023 | I5: =IFERROR(__xludf.DUMMYFUNCTION("""COMPUTED_VALUE"""),"832-622-0685") -> 832-622-0685 | J5: =IFERROR(__xludf.DUMMYFUNCTION("""COMPUTED_VALUE"""),"29.714369469154935, -95.3121463531626") -> 29.714369469154935, -95.3121463531626 | K5: =IFERROR(__xludf.DUMMYFUNCTION("""COMPUTED_VALUE"""),"{""regular"":[{""days"":[""Mo"",""Tu"",""We"",""Th"",""Fr""],""open"":null,""close"":null}]}") -> {"regular":[{"days":["Mo","Tu","We","Th","Fr"],"open":null,"close":null}]} | M5: =IFERROR(__xludf.DUMMYFUNCTION("""COMPUTED_VALUE"""),43.0) -> 43 | N5: =IFERROR(__xludf.DUMMYFUNCTION("""COMPUTED_VALUE"""),"Education - Children") -> Education - Children | O5: =IFERROR(__xludf.DUMMYFUNCTION("""COMPUTED_VALUE"""),1.0) -> 1 | P5: =IFERROR(__xludf.DUMMYFUNCTION("""COMPUTED_VALUE"""),"ACTIVE") -> ACTIVE | Q5: =IFERROR(__xludf.DUMMYFUNCTION("""COMPUTED_VALUE"""),45893.0) -> 45893 | S5: =IFERROR(__xludf.DUMMYFUNCTION("""COMPUTED_VALUE"""),"Elementary thru High School. Free Tuition which includes free breakfast and lunch. Apply online") -> Elementary thru High School. Free Tuition which includes free breakfast and lunch. Apply online | T5: =IFERROR(__xludf.DUMMYFUNCTION("""COMPUTED_VALUE"""),FALSE) -> FALSE | U5: =IFERROR(__xludf.DUMMYFUNCTION("""COMPUTED_VALUE"""),FALSE) -> FALSE | V5: =IFERROR(__xludf.DUMMYFUNCTION("""COMPUTED_VALUE"""),"https://www.aama.org/apps/pages/george-i-sanchez-charter-schools") -> https://www.aama.org/apps/pages/george-i-sanchez-charter-schools | W5: =IFERROR(__xludf.DUMMYFUNCTION("""COMPUTED_VALUE"""),"https://www.google.com/maps/place/AAMA/@29.7143334,-95.3127981,19z/data=!3m1!4b1!4m6!3m5!1s0x8640bfd5e8dcfca9:0x894a10d39493d560!8m2!3d29.7143322!4d-95.3121544!16s%2Fg%2F11sszckmnd?entry=ttu&g_ep=EgoyMDI1MDgxOS4wIKXMDSoASAFQAw%3D%3D") -> https://www.google.com/maps/place/AAMA/@29.7143334,-95.3127981,19z/data=!3m1!4b1!4m6!3m5!1s0x8640bfd5e8dcfca9:0x894a10d39493d560!8m2!3d29.7143322!4d-95.3121544!16s%2Fg%2F11sszckmnd?entry=ttu&g_ep=EgoyMDI1MDgxOS4wIKXMDSoASAFQAw%3D%3D | Y5: =IFERROR(__xludf.DUMMYFUNCTION("""COMPUTED_VALUE"""),"Houston") -> Houston | Z5: =IFERROR(__xludf.DUMMYFUNCTION("""COMPUTED_VALUE"""),"Eastwood, Gulfgate Riverview / Pine Valley, Idylwood, Lawndale / Wayside, Magnolia Park, South Central Houston") -> Eastwood, Gulfgate Riverview / Pine Valley, Idylwood, Lawndale / Wayside, Magnolia Park, South Central Houston | AA5: =IFERROR(__xludf.DUMMYFUNCTION("""COMPUTED_VALUE"""),"Association for Advancement of Mexican Americans (AAMA)") -> Association for Advancement of Mexican Americans (AAMA) | AB5: =IFERROR(__xludf.DUMMYFUNCTION("""COMPUTED_VALUE"""),"Lawndale / Wayside") -> Lawndale / Wayside
A6: 5 | B6: =IFERROR(__xludf.DUMMYFUNCTION("""COMPUTED_VALUE"""),"[""99999""]") -> ["99999"] | C6: =IFERROR(__xludf.DUMMYFUNCTION("""COMPUTED_VALUE"""),"Ability Found") -> Ability Found | D6: =IFERROR(__xludf.DUMMYFUNCTION("""COMPUTED_VALUE"""),"2324 S Constitution Blvd") -> 2324 S Constitution Blvd | F6: =IFERROR(__xludf.DUMMYFUNCTION("""COMPUTED_VALUE"""),"West Valley City") -> West Valley City | G6: =IFERROR(__xludf.DUMMYFUNCTION("""COMPUTED_VALUE"""),"UT") -> UT | H6: =IFERROR(__xludf.DUMMYFUNCTION("""COMPUTED_VALUE"""),"84119") -> 84119 | I6: =IFERROR(__xludf.DUMMYFUNCTION("""COMPUTED_VALUE"""),"801-505-0529") -> 801-505-0529 | J6: =IFERROR(__xludf.DUMMYFUNCTION("""COMPUTED_VALUE"""),"40.72037806604348, -111.95827946249824") -> 40.72037806604348, -111.95827946249824 | K6: =IFERROR(__xludf.DUMMYFUNCTION("""COMPUTED_VALUE"""),"{""regular"":[{""days"":[""Mo"",""Tu"",""We"",""Th"",""Fr""],""open"":null,""close"":null}]}") -> {"regular":[{"days":["Mo","Tu","We","Th","Fr"],"open":null,"close":null}]} | L6: =IFERROR(__xludf.DUMMYFUNCTION("""COMPUTED_VALUE"""),"Apply online") -> Apply online | M6: =IFERROR(__xludf.DUMMYFUNCTION("""COMPUTED_VALUE"""),31.0) -> 31 | N6: =IFERROR(__xludf.DUMMYFUNCTION("""COMPUTED_VALUE"""),"Medical - Primary Care") -> Medical - Primary Care | O6: =IFERROR(__xludf.DUMMYFUNCTION("""COMPUTED_VALUE"""),1.0) -> 1 | P6: =IFERROR(__xludf.DUMMYFUNCTION("""COMPUTED_VALUE"""),"ACTIVE") -> ACTIVE | Q6: =IFERROR(__xludf.DUMMYFUNCTION("""COMPUTED_VALUE"""),46045.0) -> 46045 | R6: =IFERROR(__xludf.DUMMYFUNCTION("""COMPUTED_VALUE"""),"Verified online") -> Verified online | S6: =IFERROR(__xludf.DUMMYFUNCTION("""COMPUTED_VALUE"""),"Provides mobility equipment at a low cost fee. Equipment is customized for the needs of the individual. They do not provide medical supplies or financial assistance. Requests should be submitted online by a physical therapist if you have one, otherwise co"&"ntact the organization directly thru their website. ") -> Provides mobility equipment at a low cost fee. Equipment is customized for the needs of the individual. They do not provide medical supplies or financial assistance. Requests should be submitted online by a physical therapist if you have one, otherwise contact the organization directly thru their website. | T6: =IFERROR(__xludf.DUMMYFUNCTION("""COMPUTED_VALUE"""),FALSE) -> FALSE | U6: =IFERROR(__xludf.DUMMYFUNCTION("""COMPUTED_VALUE"""),FALSE) -> FALSE | V6: =IFERROR(__xludf.DUMMYFUNCTION("""COMPUTED_VALUE"""),"https://abilityfound.org/pages/need-help") -> https://abilityfound.org/pages/need-help | W6: =IFERROR(__xludf.DUMMYFUNCTION("""COMPUTED_VALUE"""),"https://www.google.com/maps/place/Ability+Found+Charity/@40.7202562,-111.9631665,17z/data=!3m1!4b1!4m6!3m5!1s0x87528a2b55962c8f:0x4d686ad30de1f05d!8m2!3d40.7202563!4d-111.9582902!16s%2Fg%2F1vzv443n?entry=ttu&g_ep=EgoyMDI2MDEyMC4wIKXMDSoKLDEwMDc5MjA2OUgBUA"&"M%3D") -> https://www.google.com/maps/place/Ability+Found+Charity/@40.7202562,-111.9631665,17z/data=!3m1!4b1!4m6!3m5!1s0x87528a2b55962c8f:0x4d686ad30de1f05d!8m2!3d40.7202563!4d-111.9582902!16s%2Fg%2F1vzv443n?entry=ttu&g_ep=EgoyMDI2MDEyMC4wIKXMDSoKLDEwMDc5MjA2OUgBUAM%3D | Y6: =IFERROR(__xludf.DUMMYFUNCTION("""COMPUTED_VALUE"""),"West Valley City") -> West Valley City | Z6: =IFERROR(__xludf.DUMMYFUNCTION("""COMPUTED_VALUE"""),"West Valley City") -> West Valley City | AA6: =IFERROR(__xludf.DUMMYFUNCTION("""COMPUTED_VALUE"""),"Ability Found") -> Ability Found | AB6: =IFERROR(__xludf.DUMMYFUNCTION("""COMPUTED_VALUE"""),"West Valley City") -> West Valley City
A7: 6 | B7: =IFERROR(__xludf.DUMMYFUNCTION("""COMPUTED_VALUE"""),"[""77418"", ""77452"", ""77474""]") -> ["77418", "77452", "77474"] | C7: =IFERROR(__xludf.DUMMYFUNCTION("""COMPUTED_VALUE"""),"AccessHealth Bellville WIC Center") -> AccessHealth Bellville WIC Center | D7: =IFERROR(__xludf.DUMMYFUNCTION("""COMPUTED_VALUE"""),"800 E Wendt Street") -> 800 E Wendt Street | F7: =IFERROR(__xludf.DUMMYFUNCTION("""COMPUTED_VALUE"""),"Bellville") -> Bellville | G7: =IFERROR(__xludf.DUMMYFUNCTION("""COMPUTED_VALUE"""),"TX") -> TX | H7: =IFERROR(__xludf.DUMMYFUNCTION("""COMPUTED_VALUE"""),"77418") -> 77418 | I7: =IFERROR(__xludf.DUMMYFUNCTION("""COMPUTED_VALUE"""),"979-865-9140") -> 979-865-9140 | J7: =IFERROR(__xludf.DUMMYFUNCTION("""COMPUTED_VALUE"""),"29.9396576157338, -96.2537193375798") -> 29.9396576157338, -96.2537193375798 | K7: =IFERROR(__xludf.DUMMYFUNCTION("""COMPUTED_VALUE"""),"{""regular"":[{""days"":[""Mo"",""Tu"",""Th""],""open"":""08:00"",""close"":""17:30""}]}") -> {"regular":[{"days":["Mo","Tu","Th"],"open":"08:00","close":"17:30"}]} | M7: =IFERROR(__xludf.DUMMYFUNCTION("""COMPUTED_VALUE"""),44.0) -> 44 | N7: =IFERROR(__xludf.DUMMYFUNCTION("""COMPUTED_VALUE"""),"Mother & Child") -> Mother & Child | O7: =IFERROR(__xludf.DUMMYFUNCTION("""COMPUTED_VALUE"""),1.0) -> 1 | P7: =IFERROR(__xludf.DUMMYFUNCTION("""COMPUTED_VALUE"""),"ACTIVE") -> ACTIVE | Q7: =IFERROR(__xludf.DUMMYFUNCTION("""COMPUTED_VALUE"""),45831.0) -> 45831 | R7: =IFERROR(__xludf.DUMMYFUNCTION("""COMPUTED_VALUE"""),"Verified online") -> Verified online | S7: =IFERROR(__xludf.DUMMYFUNCTION("""COMPUTED_VALUE"""),"WIC is a special supplemental nutrition program for women, infants and children. It is a nutrition program for pregnant, breastfeeding women and families with children younger than 5 years old. To qualify you must meet income guidelines but if you receiv"&"e Medicaid, SNAP or TANF, then you already meet the income eligibility guidelines for WIC. AccessHealth is a private, not-for-profit organization and a Federally Qualified Health Center. It's primary focus is the low-income population of Fort Bend and Wa"&"ller counties but will not turn anyone away, regardless of income or circumstance. Fee based group sessions for Family Violence Intervention and Prevention and Anger Management Programs. ") -> WIC is a special supplemental nutrition program for women, infants and children. It is a nutrition program for pregnant, breastfeeding women and families with children younger than 5 years old. To qualify you must meet income guidelines but if you receive Medicaid, SNAP or TANF, then you already meet the income eligibility guidelines for WIC. AccessHealth is a private, not-for-profit organization and a Federally Qualified Health Center. It's primary focus is the low-income population of Fort Bend and Waller counties but will not turn anyone away, regardless of income or circumstance. Fee based group sessions for Family Violence Intervention and Prevention and Anger Management Programs. | T7: =IFERROR(__xludf.DUMMYFUNCTION("""COMPUTED_VALUE"""),FALSE) -> FALSE | U7: =IFERROR(__xludf.DUMMYFUNCTION("""COMPUTED_VALUE"""),FALSE) -> FALSE | V7: =IFERROR(__xludf.DUMMYFUNCTION("""COMPUTED_VALUE"""),"https://www.myaccesshealth.org/") -> https://www.myaccesshealth.org/ | W7: =IFERROR(__xludf.DUMMYFUNCTION("""COMPUTED_VALUE"""),"https://www.google.com/maps/place/Access+Health+Bellville+WIC+Clinic/@29.9400956,-96.2564832,16z/data=!3m1!4b1!4m6!3m5!1s0x86415214a20f7165:0x9a29241743df954d!8m2!3d29.940091!4d-96.2539029!16s%2Fg%2F11bzsdntr2?entry=ttu&g_ep=EgoyMDI1MDYxNy4wIKXMDSoASAFQAw"&"%3D%3D") -> https://www.google.com/maps/place/Access+Health+Bellville+WIC+Clinic/@29.9400956,-96.2564832,16z/data=!3m1!4b1!4m6!3m5!1s0x86415214a20f7165:0x9a29241743df954d!8m2!3d29.940091!4d-96.2539029!16s%2Fg%2F11bzsdntr2?entry=ttu&g_ep=EgoyMDI1MDYxNy4wIKXMDSoASAFQAw%3D%3D | Y7: =IFERROR(__xludf.DUMMYFUNCTION("""COMPUTED_VALUE"""),"Bellville") -> Bellville | Z7: =IFERROR(__xludf.DUMMYFUNCTION("""COMPUTED_VALUE"""),"Bellville") -> Bellville | AA7: =IFERROR(__xludf.DUMMYFUNCTION("""COMPUTED_VALUE"""),"AccessHealth") -> AccessHealth | AB7: =IFERROR(__xludf.DUMMYFUNCTION("""COMPUTED_VALUE"""),"Bellville") -> Bellville
A8: 7 | B8: =IFERROR(__xludf.DUMMYFUNCTION("""COMPUTED_VALUE"""),"[""77053"", ""77406"", ""77407"", ""77417"", ""77423"", ""77430"", ""77441"", ""77444"", ""77451"", ""77459"", ""77461"", ""77464"", ""77469"", ""77471"", ""77476"", ""77477"", ""77478"", ""77479"", ""77481"", ""77485"", ""77489"", ""77494"", ""77498"", "&"""77545"", ""77583"", ""77584""]") -> ["77053", "77406", "77407", "77417", "77423", "77430", "77441", "77444", "77451", "77459", "77461", "77464", "77469", "77471", "77476", "77477", "77478", "77479", "77481", "77485", "77489", "77494", "77498", "77545", "77583", "77584"] | C8: =IFERROR(__xludf.DUMMYFUNCTION("""COMPUTED_VALUE"""),"AccessHealth Brookshire Clinic") -> AccessHealth Brookshire Clinic | D8: =IFERROR(__xludf.DUMMYFUNCTION("""COMPUTED_VALUE"""),"533 FM 359 S") -> 533 FM 359 S | F8: =IFERROR(__xludf.DUMMYFUNCTION("""COMPUTED_VALUE"""),"Brookshire") -> Brookshire | G8: =IFERROR(__xludf.DUMMYFUNCTION("""COMPUTED_VALUE"""),"TX") -> TX | H8: =IFERROR(__xludf.DUMMYFUNCTION("""COMPUTED_VALUE"""),"77423") -> 77423 | I8: =IFERROR(__xludf.DUMMYFUNCTION("""COMPUTED_VALUE"""),"281-342-4530") -> 281-342-4530 | J8: =IFERROR(__xludf.DUMMYFUNCTION("""COMPUTED_VALUE"""),"29.77434, -95.950801") -> 29.77434, -95.950801 | K8: =IFERROR(__xludf.DUMMYFUNCTION("""COMPUTED_VALUE"""),"{""regular"":[{""days"":[""Mo"",""Tu"",""We""],""open"":""07:00"",""close"":""17:30""},{""days"":[""Th"",""Fr""],""open"":""08:00"",""close"":""17:00""}]}") -> {"regular":[{"days":["Mo","Tu","We"],"open":"07:00","close":"17:30"},{"days":["Th","Fr"],"open":"08:00","close":"17:00"}]} | M8: =IFERROR(__xludf.DUMMYFUNCTION("""COMPUTED_VALUE"""),31.0) -> 31 | N8: =IFERROR(__xludf.DUMMYFUNCTION("""COMPUTED_VALUE"""),"Medical - Primary Care") -> Medical - Primary Care | O8: =IFERROR(__xludf.DUMMYFUNCTION("""COMPUTED_VALUE"""),1.0) -> 1 | P8: =IFERROR(__xludf.DUMMYFUNCTION("""COMPUTED_VALUE"""),"ACTIVE") -> ACTIVE | Q8: =IFERROR(__xludf.DUMMYFUNCTION("""COMPUTED_VALUE"""),45831.0) -> 45831 | R8: =IFERROR(__xludf.DUMMYFUNCTION("""COMPUTED_VALUE"""),"Verified online") -> Verified online | S8: =IFERROR(__xludf.DUMMYFUNCTION("""COMPUTED_VALUE"""),"Family medicine, primary care, adults, women's health, pediatric, counseling and mental health, pharmacy, immunizations, Lab, OB.GYN, Hepatitis testing and treatment, substance abuse and addiction. AccessHealth is a private, not-for-profit organization an"&"d a Federally Qualified Health Center. It's primary focus is the low-income population of Fort Bend and Waller counties but will not turn anyone away, regardless of income or circumstance. Sliding scale of fee based on income.") -> Family medicine, primary care, adults, women's health, pediatric, counseling and mental health, pharmacy, immunizations, Lab, OB.GYN, Hepatitis testing and treatment, substance abuse and addiction. AccessHealth is a private, not-for-profit organization and a Federally Qualified Health Center. It's primary focus is the low-income population of Fort Bend and Waller counties but will not turn anyone away, regardless of income or circumstance. Sliding scale of fee based on income. | T8: =IFERROR(__xludf.DUMMYFUNCTION("""COMPUTED_VALUE"""),FALSE) -> FALSE | U8: =IFERROR(__xludf.DUMMYFUNCTION("""COMPUTED_VALUE"""),FALSE) -> FALSE | V8: =IFERROR(__xludf.DUMMYFUNCTION("""COMPUTED_VALUE"""),"https://www.myaccesshealth.org/") -> https://www.myaccesshealth.org/ | W8: =IFERROR(__xludf.DUMMYFUNCTION("""COMPUTED_VALUE"""),"https://www.google.com/maps/place/AccessHealth+Brookshire+Clinic/@29.774261,-95.9528807,17z/data=!3m1!4b1!4m6!3m5!1s0x86413ba32ec6aa43:0xecb591ea00b3e4b5!8m2!3d29.7742564!4d-95.9503004!16s%2Fg%2F11hc_k0k4f?entry=ttu&g_ep=EgoyMDI1MDYxNy4wIKXMDSoASAFQAw%3D%"&"3D") -> https://www.google.com/maps/place/AccessHealth+Brookshire+Clinic/@29.774261,-95.9528807,17z/data=!3m1!4b1!4m6!3m5!1s0x86413ba32ec6aa43:0xecb591ea00b3e4b5!8m2!3d29.7742564!4d-95.9503004!16s%2Fg%2F11hc_k0k4f?entry=ttu&g_ep=EgoyMDI1MDYxNy4wIKXMDSoASAFQAw%3D%3D | Y8: =IFERROR(__xludf.DUMMYFUNCTION("""COMPUTED_VALUE"""),"Brookshire") -> Brookshire | Z8: =IFERROR(__xludf.DUMMYFUNCTION("""COMPUTED_VALUE"""),"Brookshire") -> Brookshire | AA8: =IFERROR(__xludf.DUMMYFUNCTION("""COMPUTED_VALUE"""),"AccessHealth") -> AccessHealth | AB8: =IFERROR(__xludf.DUMMYFUNCTION("""COMPUTED_VALUE"""),"Brookshire") -> Brookshire
A9: 8 | B9: =IFERROR(__xludf.DUMMYFUNCTION("""COMPUTED_VALUE"""),"[""77053"", ""77406"", ""77407"", ""77417"", ""77423"", ""77430"", ""77441"", ""77444"", ""77451"", ""77459"", ""77461"", ""77464"", ""77469"", ""77471"", ""77476"", ""77477"", ""77478"", ""77479"", ""77481"", ""77485"", ""77489"", ""77494"", ""77498"", "&"""77545"", ""77583"", ""77584""]") -> ["77053", "77406", "77407", "77417", "77423", "77430", "77441", "77444", "77451", "77459", "77461", "77464", "77469", "77471", "77476", "77477", "77478", "77479", "77481", "77485", "77489", "77494", "77498", "77545", "77583", "77584"] | C9: =IFERROR(__xludf.DUMMYFUNCTION("""COMPUTED_VALUE"""),"AccessHealth Brookshire WIC Center") -> AccessHealth Brookshire WIC Center | D9: =IFERROR(__xludf.DUMMYFUNCTION("""COMPUTED_VALUE"""),"531 FM 359 S") -> 531 FM 359 S | F9: =IFERROR(__xludf.DUMMYFUNCTION("""COMPUTED_VALUE"""),"Brookshire") -> Brookshire | G9: =IFERROR(__xludf.DUMMYFUNCTION("""COMPUTED_VALUE"""),"TX") -> TX | H9: =IFERROR(__xludf.DUMMYFUNCTION("""COMPUTED_VALUE"""),"77423") -> 77423 | I9: =IFERROR(__xludf.DUMMYFUNCTION("""COMPUTED_VALUE"""),"281-822-4242") -> 281-822-4242 | J9: =IFERROR(__xludf.DUMMYFUNCTION("""COMPUTED_VALUE"""),"29.774335, -95.951041") -> 29.774335, -95.951041 | K9: =IFERROR(__xludf.DUMMYFUNCTION("""COMPUTED_VALUE"""),"{""regular"":[{""days"":[""Mo"",""We"",""Th""],""open"":""08:00"",""close"":""17:30""},{""days"":[""Tu""],""open"":""08:00"",""close"":""18:00""},{""days"":[""Fr""],""open"":""08:00"",""close"":""13:30""}]}") -> {"regular":[{"days":["Mo","We","Th"],"open":"08:00","close":"17:30"},{"days":["Tu"],"open":"08:00","close":"18:00"},{"days":["Fr"],"open":"08:00","close":"13:30"}]} | M9: =IFERROR(__xludf.DUMMYFUNCTION("""COMPUTED_VALUE"""),44.0) -> 44 | N9: =IFERROR(__xludf.DUMMYFUNCTION("""COMPUTED_VALUE"""),"Mother & Child") -> Mother & Child | O9: =IFERROR(__xludf.DUMMYFUNCTION("""COMPUTED_VALUE"""),1.0) -> 1 | P9: =IFERROR(__xludf.DUMMYFUNCTION("""COMPUTED_VALUE"""),"ACTIVE") -> ACTIVE | Q9: =IFERROR(__xludf.DUMMYFUNCTION("""COMPUTED_VALUE"""),45831.0) -> 45831 | R9: =IFERROR(__xludf.DUMMYFUNCTION("""COMPUTED_VALUE"""),"Verified online") -> Verified online | S9: =IFERROR(__xludf.DUMMYFUNCTION("""COMPUTED_VALUE"""),"WIC is a special supplemental nutrition program for women, infants and children. It is a nutrition program for pregnant, breastfeeding women and families with children younger than 5 years old. To qualify you must meet income guidelines but if you receiv"&"e Medicaid, SNAP or TANF, then you already meet the income eligibility guidelines for WIC. AccessHealth is a private, not-for-profit organization and a Federally Qualified Health Center. It's primary focus is the low-income population of Fort Bend and Wa"&"ller counties but will not turn anyone away, regardless of income or circumstance. ") -> WIC is a special supplemental nutrition program for women, infants and children. It is a nutrition program for pregnant, breastfeeding women and families with children younger than 5 years old. To qualify you must meet income guidelines but if you receive Medicaid, SNAP or TANF, then you already meet the income eligibility guidelines for WIC. AccessHealth is a private, not-for-profit organization and a Federally Qualified Health Center. It's primary focus is the low-income population of Fort Bend and Waller counties but will not turn anyone away, regardless of income or circumstance. | T9: =IFERROR(__xludf.DUMMYFUNCTION("""COMPUTED_VALUE"""),FALSE) -> FALSE | U9: =IFERROR(__xludf.DUMMYFUNCTION("""COMPUTED_VALUE"""),FALSE) -> FALSE | V9: =IFERROR(__xludf.DUMMYFUNCTION("""COMPUTED_VALUE"""),"https://www.myaccesshealth.org/") -> https://www.myaccesshealth.org/ | W9: =IFERROR(__xludf.DUMMYFUNCTION("""COMPUTED_VALUE"""),"https://www.google.com/maps/place/Access+Health+Brookshire+WIC+Clinic/@29.7743128,-95.9532197,17z/data=!3m1!4b1!4m6!3m5!1s0x86413ba32420529b:0x5798dda56f02582e!8m2!3d29.7743082!4d-95.9506394!16s%2Fg%2F11hcd_dmqz?entry=ttu&g_ep=EgoyMDI1MDYxNy4wIKXMDSoASAFQ"&"Aw%3D%3D") -> https://www.google.com/maps/place/Access+Health+Brookshire+WIC+Clinic/@29.7743128,-95.9532197,17z/data=!3m1!4b1!4m6!3m5!1s0x86413ba32420529b:0x5798dda56f02582e!8m2!3d29.7743082!4d-95.9506394!16s%2Fg%2F11hcd_dmqz?entry=ttu&g_ep=EgoyMDI1MDYxNy4wIKXMDSoASAFQAw%3D%3D | Y9: =IFERROR(__xludf.DUMMYFUNCTION("""COMPUTED_VALUE"""),"Brookshire") -> Brookshire | Z9: =IFERROR(__xludf.DUMMYFUNCTION("""COMPUTED_VALUE"""),"Brookshire") -> Brookshire | AA9: =IFERROR(__xludf.DUMMYFUNCTION("""COMPUTED_VALUE"""),"AccessHealth") -> AccessHealth | AB9: =IFERROR(__xludf.DUMMYFUNCTION("""COMPUTED_VALUE"""),"Brookshire") -> Brookshire
A10: 9 | B10: =IFERROR(__xludf.DUMMYFUNCTION("""COMPUTED_VALUE"""),"[""77053"", ""77406"", ""77407"", ""77417"", ""77423"", ""77430"", ""77441"", ""77444"", ""77451"", ""77459"", ""77461"", ""77464"", ""77469"", ""77471"", ""77476"", ""77477"", ""77478"", ""77479"", ""77481"", ""77485"", ""77489"", ""77494"", ""77498"", "&"""77545"", ""77583"", ""77584""]") -> ["77053", "77406", "77407", "77417", "77423", "77430", "77441", "77444", "77451", "77459", "77461", "77464", "77469", "77471", "77476", "77477", "77478", "77479", "77481", "77485", "77489", "77494", "77498", "77545", "77583", "77584"] | C10: =IFERROR(__xludf.DUMMYFUNCTION("""COMPUTED_VALUE"""),"AccessHealth East Fort Bend Clinic") -> AccessHealth East Fort Bend Clinic | D10: =IFERROR(__xludf.DUMMYFUNCTION("""COMPUTED_VALUE"""),"7707 Highway 6 South") -> 7707 Highway 6 South | F10: =IFERROR(__xludf.DUMMYFUNCTION("""COMPUTED_VALUE"""),"Missouri City") -> Missouri City | G10: =IFERROR(__xludf.DUMMYFUNCTION("""COMPUTED_VALUE"""),"TX") -> TX | H10: =IFERROR(__xludf.DUMMYFUNCTION("""COMPUTED_VALUE"""),"77459") -> 77459 | I10: =IFERROR(__xludf.DUMMYFUNCTION("""COMPUTED_VALUE"""),"281-342-4530") -> 281-342-4530 | J10: =IFERROR(__xludf.DUMMYFUNCTION("""COMPUTED_VALUE"""),"29.55004371572688, -95.54838500791375") -> 29.55004371572688, -95.54838500791375 | K10: =IFERROR(__xludf.DUMMYFUNCTION("""COMPUTED_VALUE"""),"{""regular"":[{""days"":[""Mo"",""Tu"",""We"",""Th""],""open"":""08:00"",""close"":""17:00""}]}") -> {"regular":[{"days":["Mo","Tu","We","Th"],"open":"08:00","close":"17:00"}]} | M10: =IFERROR(__xludf.DUMMYFUNCTION("""COMPUTED_VALUE"""),31.0) -> 31 | N10: =IFERROR(__xludf.DUMMYFUNCTION("""COMPUTED_VALUE"""),"Medical - Primary Care") -> Medical - Primary Care | O10: =IFERROR(__xludf.DUMMYFUNCTION("""COMPUTED_VALUE"""),1.0) -> 1 | P10: =IFERROR(__xludf.DUMMYFUNCTION("""COMPUTED_VALUE"""),"ACTIVE") -> ACTIVE | Q10: =IFERROR(__xludf.DUMMYFUNCTION("""COMPUTED_VALUE"""),45831.0) -> 45831 | R10: =IFERROR(__xludf.DUMMYFUNCTION("""COMPUTED_VALUE"""),"Verified online") -> Verified online | S10: =IFERROR(__xludf.DUMMYFUNCTION("""COMPUTED_VALUE"""),"Family medicine, primary care, adults, women's health, pediatric, counseling and mental health, pharmacy, immunizations, Lab, OB.GYN, Hepatitis testing and treatment, substance abuse and addiction. AccessHealth is a private, not-for-profit organization an"&"d a Federally Qualified Health Center. It's primary focus is the low-income population of Fort Bend and Waller counties but will not turn anyone away, regardless of income or circumstance. Sliding scale of fee based on income.") -> Family medicine, primary care, adults, women's health, pediatric, counseling and mental health, pharmacy, immunizations, Lab, OB.GYN, Hepatitis testing and treatment, substance abuse and addiction. AccessHealth is a private, not-for-profit organization and a Federally Qualified Health Center. It's primary focus is the low-income population of Fort Bend and Waller counties but will not turn anyone away, regardless of income or circumstance. Sliding scale of fee based on income. | T10: =IFERROR(__xludf.DUMMYFUNCTION("""COMPUTED_VALUE"""),FALSE) -> FALSE | U10: =IFERROR(__xludf.DUMMYFUNCTION("""COMPUTED_VALUE"""),FALSE) -> FALSE | V10: =IFERROR(__xludf.DUMMYFUNCTION("""COMPUTED_VALUE"""),"https://www.myaccesshealth.org/") -> https://www.myaccesshealth.org/ | W10: =IFERROR(__xludf.DUMMYFUNCTION("""COMPUTED_VALUE"""),"https://www.google.com/maps/place/AccessHealth+East+Fort+Bend/@29.5498337,-95.5509975,17z/data=!3m1!4b1!4m6!3m5!1s0x8640ef623897ab5b:0x45df221a3b363090!8m2!3d29.5498291!4d-95.5484172!16s%2Fg%2F11g3zk_tqr?entry=ttu&g_ep=EgoyMDI1MDYxNy4wIKXMDSoASAFQAw%3D%3D") -> https://www.google.com/maps/place/AccessHealth+East+Fort+Bend/@29.5498337,-95.5509975,17z/data=!3m1!4b1!4m6!3m5!1s0x8640ef623897ab5b:0x45df221a3b363090!8m2!3d29.5498291!4d-95.5484172!16s%2Fg%2F11g3zk_tqr?entry=ttu&g_ep=EgoyMDI1MDYxNy4wIKXMDSoASAFQAw%3D%3D | Y10: =IFERROR(__xludf.DUMMYFUNCTION("""COMPUTED_VALUE"""),"Missouri City") -> Missouri City | Z10: =IFERROR(__xludf.DUMMYFUNCTION("""COMPUTED_VALUE"""),"Missouri City, Plantation Park, Sienna") -> Missouri City, Plantation Park, Sienna | AA10: =IFERROR(__xludf.DUMMYFUNCTION("""COMPUTED_VALUE"""),"AccessHealth") -> AccessHealth | AB10: =IFERROR(__xludf.DUMMYFUNCTION("""COMPUTED_VALUE"""),"Missouri City") -> Missouri City
A11: 10 | B11: =IFERROR(__xludf.DUMMYFUNCTION("""COMPUTED_VALUE"""),"[""77445"", ""77446"", ""77466"", ""77492""]") -> ["77445", "77446", "77466", "77492"] | C11: =IFERROR(__xludf.DUMMYFUNCTION("""COMPUTED_VALUE"""),"AccessHealth Hempstead WIC Center") -> AccessHealth Hempstead WIC Center | D11: =IFERROR(__xludf.DUMMYFUNCTION("""COMPUTED_VALUE"""),"1737 13th Street") -> 1737 13th Street | F11: =IFERROR(__xludf.DUMMYFUNCTION("""COMPUTED_VALUE"""),"Hempstead") -> Hempstead | G11: =IFERROR(__xludf.DUMMYFUNCTION("""COMPUTED_VALUE"""),"TX") -> TX | H11: =IFERROR(__xludf.DUMMYFUNCTION("""COMPUTED_VALUE"""),"77445") -> 77445 | I11: =IFERROR(__xludf.DUMMYFUNCTION("""COMPUTED_VALUE"""),"979-557-2860") -> 979-557-2860 | J11: =IFERROR(__xludf.DUMMYFUNCTION("""COMPUTED_VALUE"""),"30.0888023601738, -96.0826334225169") -> 30.0888023601738, -96.0826334225169 | K11: =IFERROR(__xludf.DUMMYFUNCTION("""COMPUTED_VALUE"""),"{""regular"":[{""days"":[""Mo"",""Tu""],""open"":""08:00"",""close"":""18:00""},{""days"":[""We"",""Th""],""open"":""08:00"",""close"":""17:30""},{""days"":[""Fr""],""open"":""08:00"",""close"":""13:00""}]}") -> {"regular":[{"days":["Mo","Tu"],"open":"08:00","close":"18:00"},{"days":["We","Th"],"open":"08:00","close":"17:30"},{"days":["Fr"],"open":"08:00","close":"13:00"}]} | M11: =IFERROR(__xludf.DUMMYFUNCTION("""COMPUTED_VALUE"""),44.0) -> 44 | N11: =IFERROR(__xludf.DUMMYFUNCTION("""COMPUTED_VALUE"""),"Mother & Child") -> Mother & Child | O11: =IFERROR(__xludf.DUMMYFUNCTION("""COMPUTED_VALUE"""),1.0) -> 1 | P11: =IFERROR(__xludf.DUMMYFUNCTION("""COMPUTED_VALUE"""),"ACTIVE") -> ACTIVE | Q11: =IFERROR(__xludf.DUMMYFUNCTION("""COMPUTED_VALUE"""),45831.0) -> 45831 | R11: =IFERROR(__xludf.DUMMYFUNCTION("""COMPUTED_VALUE"""),"Verified online") -> Verified online | S11: =IFERROR(__xludf.DUMMYFUNCTION("""COMPUTED_VALUE"""),"WIC is a special supplemental nutrition program for women, infants and children. It is a nutrition program for pregnant, breastfeeding women and families with children younger than 5 years old. To qualify you must meet income guidelines but if you receiv"&"e Medicaid, SNAP or TANF, then you already meet the income eligibility guidelines for WIC. AccessHealth is a private, not-for-profit organization and a Federally Qualified Health Center. It's primary focus is the low-income population of Fort Bend and Wa"&"ller counties but will not turn anyone away, regardless of income or circumstance. ") -> WIC is a special supplemental nutrition program for women, infants and children. It is a nutrition program for pregnant, breastfeeding women and families with children younger than 5 years old. To qualify you must meet income guidelines but if you receive Medicaid, SNAP or TANF, then you already meet the income eligibility guidelines for WIC. AccessHealth is a private, not-for-profit organization and a Federally Qualified Health Center. It's primary focus is the low-income population of Fort Bend and Waller counties but will not turn anyone away, regardless of income or circumstance. | T11: =IFERROR(__xludf.DUMMYFUNCTION("""COMPUTED_VALUE"""),FALSE) -> FALSE | U11: =IFERROR(__xludf.DUMMYFUNCTION("""COMPUTED_VALUE"""),FALSE) -> FALSE | V11: =IFERROR(__xludf.DUMMYFUNCTION("""COMPUTED_VALUE"""),"https://www.myaccesshealth.org/") -> https://www.myaccesshealth.org/ | W11: =IFERROR(__xludf.DUMMYFUNCTION("""COMPUTED_VALUE"""),"https://www.google.com/maps/place/Access+Health+Hempstead+WIC+Clinic/@30.0885994,-96.0854671,17z/data=!3m1!4b1!4m6!3m5!1s0x8646cbf2bdd604ed:0x3871c5dc9c88752f!8m2!3d30.0885948!4d-96.0828868!16s%2Fg%2F11c80c5pwh?entry=ttu&g_ep=EgoyMDI1MDYxNy4wIKXMDSoASAFQA"&"w%3D%3D") -> https://www.google.com/maps/place/Access+Health+Hempstead+WIC+Clinic/@30.0885994,-96.0854671,17z/data=!3m1!4b1!4m6!3m5!1s0x8646cbf2bdd604ed:0x3871c5dc9c88752f!8m2!3d30.0885948!4d-96.0828868!16s%2Fg%2F11c80c5pwh?entry=ttu&g_ep=EgoyMDI1MDYxNy4wIKXMDSoASAFQAw%3D%3D | Y11: =IFERROR(__xludf.DUMMYFUNCTION("""COMPUTED_VALUE"""),"Hempstead") -> Hempstead | Z11: =IFERROR(__xludf.DUMMYFUNCTION("""COMPUTED_VALUE"""),"Hempstead, Northside") -> Hempstead, Northside | AA11: =IFERROR(__xludf.DUMMYFUNCTION("""COMPUTED_VALUE"""),"AccessHealth") -> AccessHealth | AB11: =IFERROR(__xludf.DUMMYFUNCTION("""COMPUTED_VALUE"""),"Hempstead") -> Hempstead
A12: 11 | B12: =IFERROR(__xludf.DUMMYFUNCTION("""COMPUTED_VALUE"""),"[""77053"", ""77406"", ""77407"", ""77417"", ""77423"", ""77430"", ""77441"", ""77444"", ""77451"", ""77459"", ""77461"", ""77464"", ""77469"", ""77471"", ""77476"", ""77477"", ""77478"", ""77479"", ""77481"", ""77485"", ""77489"", ""77494"", ""77498"", "&"""77545"", ""77583"", ""77584""]") -> ["77053", "77406", "77407", "77417", "77423", "77430", "77441", "77444", "77451", "77459", "77461", "77464", "77469", "77471", "77476", "77477", "77478", "77479", "77481", "77485", "77489", "77494", "77498", "77545", "77583", "77584"] | C12: =IFERROR(__xludf.DUMMYFUNCTION("""COMPUTED_VALUE"""),"AccessHealth Katy WIC Center") -> AccessHealth Katy WIC Center | D12: =IFERROR(__xludf.DUMMYFUNCTION("""COMPUTED_VALUE"""),"1260 Pin Oak Road") -> 1260 Pin Oak Road | E12: =IFERROR(__xludf.DUMMYFUNCTION("""COMPUTED_VALUE"""),"Suite 110") -> Suite 110 | F12: =IFERROR(__xludf.DUMMYFUNCTION("""COMPUTED_VALUE"""),"Katy") -> Katy | G12: =IFERROR(__xludf.DUMMYFUNCTION("""COMPUTED_VALUE"""),"TX") -> TX | H12: =IFERROR(__xludf.DUMMYFUNCTION("""COMPUTED_VALUE"""),"77494") -> 77494 | I12: =IFERROR(__xludf.DUMMYFUNCTION("""COMPUTED_VALUE"""),"281-391-4168") -> 281-391-4168 | J12: =IFERROR(__xludf.DUMMYFUNCTION("""COMPUTED_VALUE"""),"29.7721292, -95.8181261") -> 29.7721292, -95.8181261 | K12: =IFERROR(__xludf.DUMMYFUNCTION("""COMPUTED_VALUE"""),"{""regular"":[{""days"":[""Mo""],""open"":""08:00"",""close"":""19:00""},{""days"":[""Tu"",""We"",""Th""],""open"":""08:00"",""close"":""17:00""},{""days"":[""Fr""],""open"":""08:00"",""close"":""12:00""}]}") -> {"regular":[{"days":["Mo"],"open":"08:00","close":"19:00"},{"days":["Tu","We","Th"],"open":"08:00","close":"17:00"},{"days":["Fr"],"open":"08:00","close":"12:00"}]} | M12: =IFERROR(__xludf.DUMMYFUNCTION("""COMPUTED_VALUE"""),44.0) -> 44 | N12: =IFERROR(__xludf.DUMMYFUNCTION("""COMPUTED_VALUE"""),"Mother & Child") -> Mother & Child | O12: =IFERROR(__xludf.DUMMYFUNCTION("""COMPUTED_VALUE"""),1.0) -> 1 | P12: =IFERROR(__xludf.DUMMYFUNCTION("""COMPUTED_VALUE"""),"ACTIVE") -> ACTIVE | Q12: =IFERROR(__xludf.DUMMYFUNCTION("""COMPUTED_VALUE"""),45831.0) -> 45831 | R12: =IFERROR(__xludf.DUMMYFUNCTION("""COMPUTED_VALUE"""),"Verified online") -> Verified online | S12: =IFERROR(__xludf.DUMMYFUNCTION("""COMPUTED_VALUE"""),"WIC is a special supplemental nutrition program for women, infants and children. It is a nutrition program for pregnant, breastfeeding women and families with children younger than 5 years old. To qualify you must meet income guidelines but if you receiv"&"e Medicaid, SNAP or TANF, then you already meet the income eligibility guidelines for WIC. AccessHealth is a private, not-for-profit organization and a Federally Qualified Health Center. It's primary focus is the low-income population of Fort Bend and Wa"&"ller counties but will not turn anyone away, regardless of income or circumstance. ") -> WIC is a special supplemental nutrition program for women, infants and children. It is a nutrition program for pregnant, breastfeeding women and families with children younger than 5 years old. To qualify you must meet income guidelines but if you receive Medicaid, SNAP or TANF, then you already meet the income eligibility guidelines for WIC. AccessHealth is a private, not-for-profit organization and a Federally Qualified Health Center. It's primary focus is the low-income population of Fort Bend and Waller counties but will not turn anyone away, regardless of income or circumstance. | T12: =IFERROR(__xludf.DUMMYFUNCTION("""COMPUTED_VALUE"""),FALSE) -> FALSE | U12: =IFERROR(__xludf.DUMMYFUNCTION("""COMPUTED_VALUE"""),FALSE) -> FALSE | V12: =IFERROR(__xludf.DUMMYFUNCTION("""COMPUTED_VALUE"""),"https://www.myaccesshealth.org/") -> https://www.myaccesshealth.org/ | W12: =IFERROR(__xludf.DUMMYFUNCTION("""COMPUTED_VALUE"""),"https://www.google.com/maps/place/Access+Health+Katy+WIC+Clinic/@29.7715667,-95.8211363,17z/data=!3m2!4b1!5s0x8641241ea38f160d:0x1f5667d0be90dcb3!4m6!3m5!1s0x8641241ea41aa14b:0xbfb6bd3112b944c4!8m2!3d29.7715621!4d-95.818556!16s%2Fg%2F1tkb5hd8?entry=ttu&g_"&"ep=EgoyMDI1MDYxNy4wIKXMDSoASAFQAw%3D%3D") -> https://www.google.com/maps/place/Access+Health+Katy+WIC+Clinic/@29.7715667,-95.8211363,17z/data=!3m2!4b1!5s0x8641241ea38f160d:0x1f5667d0be90dcb3!4m6!3m5!1s0x8641241ea41aa14b:0xbfb6bd3112b944c4!8m2!3d29.7715621!4d-95.818556!16s%2Fg%2F1tkb5hd8?entry=ttu&g_ep=EgoyMDI1MDYxNy4wIKXMDSoASAFQAw%3D%3D | Y12: =IFERROR(__xludf.DUMMYFUNCTION("""COMPUTED_VALUE"""),"Katy") -> Katy | Z12: =IFERROR(__xludf.DUMMYFUNCTION("""COMPUTED_VALUE"""),"Cinco Ranch West, Firethorne, Katy, Seven Meadows") -> Cinco Ranch West, Firethorne, Katy, Seven Meadows | AA12: =IFERROR(__xludf.DUMMYFUNCTION("""COMPUTED_VALUE"""),"AccessHealth") -> AccessHealth | AB12: =IFERROR(__xludf.DUMMYFUNCTION("""COMPUTED_VALUE"""),"Katy") -> Katy
A13: 12 | B13: =IFERROR(__xludf.DUMMYFUNCTION("""COMPUTED_VALUE"""),"[""77053"", ""77406"", ""77407"", ""77417"", ""77423"", ""77430"", ""77441"", ""77444"", ""77451"", ""77459"", ""77461"", ""77464"", ""77469"", ""77471"", ""77476"", ""77477"", ""77478"", ""77479"", ""77481"", ""77485"", ""77489"", ""77494"", ""77498"", "&"""77545"", ""77583"", ""77584""]") -> ["77053", "77406", "77407", "77417", "77423", "77430", "77441", "77444", "77451", "77459", "77461", "77464", "77469", "77471", "77476", "77477", "77478", "77479", "77481", "77485", "77489", "77494", "77498", "77545", "77583", "77584"] | C13: =IFERROR(__xludf.DUMMYFUNCTION("""COMPUTED_VALUE"""),"AccessHealth Missouri City Clinic") -> AccessHealth Missouri City Clinic | D13: =IFERROR(__xludf.DUMMYFUNCTION("""COMPUTED_VALUE"""),"307 Texas Parkway") -> 307 Texas Parkway | E13: =IFERROR(__xludf.DUMMYFUNCTION("""COMPUTED_VALUE"""),"Suite 100") -> Suite 100 | F13: =IFERROR(__xludf.DUMMYFUNCTION("""COMPUTED_VALUE"""),"Missouri City") -> Missouri City | G13: =IFERROR(__xludf.DUMMYFUNCTION("""COMPUTED_VALUE"""),"TX") -> TX | H13: =IFERROR(__xludf.DUMMYFUNCTION("""COMPUTED_VALUE"""),"77489") -> 77489 | I13: =IFERROR(__xludf.DUMMYFUNCTION("""COMPUTED_VALUE"""),"281-342-4530") -> 281-342-4530 | J13: =IFERROR(__xludf.DUMMYFUNCTION("""COMPUTED_VALUE"""),"29.6178774285714, -95.537035") -> 29.6178774285714, -95.537035 | K13: =IFERROR(__xludf.DUMMYFUNCTION("""COMPUTED_VALUE"""),"{""regular"":[{""days"":[""Mo"",""We"",""Th"",""Fr""],""open"":""07:00"",""close"":""17:00""},{""days"":[""Tu""],""open"":""07:00"",""close"":""18:00""}]}") -> {"regular":[{"days":["Mo","We","Th","Fr"],"open":"07:00","close":"17:00"},{"days":["Tu"],"open":"07:00","close":"18:00"}]} | M13: =IFERROR(__xludf.DUMMYFUNCTION("""COMPUTED_VALUE"""),31.0) -> 31 | N13: =IFERROR(__xludf.DUMMYFUNCTION("""COMPUTED_VALUE"""),"Medical - Primary Care") -> Medical - Primary Care | O13: =IFERROR(__xludf.DUMMYFUNCTION("""COMPUTED_VALUE"""),1.0) -> 1 | P13: =IFERROR(__xludf.DUMMYFUNCTION("""COMPUTED_VALUE"""),"ACTIVE") -> ACTIVE | Q13: =IFERROR(__xludf.DUMMYFUNCTION("""COMPUTED_VALUE"""),45831.0) -> 45831 | R13: =IFERROR(__xludf.DUMMYFUNCTION("""COMPUTED_VALUE"""),"Verified online") -> Verified online | S13: =IFERROR(__xludf.DUMMYFUNCTION("""COMPUTED_VALUE"""),"Family medicine, primary care, adults, women's health, pediatric, counseling and mental health, pharmacy, immunizations, Lab, OB.GYN, Hepatitis testing and treatment, substance abuse and addiction. AccessHealth is a private, not-for-profit organization an"&"d a Federally Qualified Health Center. It's primary focus is the low-income population of Fort Bend and Waller counties but will not turn anyone away, regardless of income or circumstance. Sliding scale of fee based on income.") -> Family medicine, primary care, adults, women's health, pediatric, counseling and mental health, pharmacy, immunizations, Lab, OB.GYN, Hepatitis testing and treatment, substance abuse and addiction. AccessHealth is a private, not-for-profit organization and a Federally Qualified Health Center. It's primary focus is the low-income population of Fort Bend and Waller counties but will not turn anyone away, regardless of income or circumstance. Sliding scale of fee based on income. | T13: =IFERROR(__xludf.DUMMYFUNCTION("""COMPUTED_VALUE"""),FALSE) -> FALSE | U13: =IFERROR(__xludf.DUMMYFUNCTION("""COMPUTED_VALUE"""),FALSE) -> FALSE | V13: =IFERROR(__xludf.DUMMYFUNCTION("""COMPUTED_VALUE"""),"https://www.myaccesshealth.org/") -> https://www.myaccesshealth.org/ | W13: =IFERROR(__xludf.DUMMYFUNCTION("""COMPUTED_VALUE"""),"https://www.google.com/maps/place/AccessHealth+Missouri+City+Clinic/@29.6175145,-95.5386005,17z/data=!3m1!4b1!4m6!3m5!1s0x8640e8f2465c6023:0xf54e0d695a0a28f2!8m2!3d29.6175099!4d-95.5360202!16s%2Fg%2F1v3lqbd7?entry=ttu&g_ep=EgoyMDI1MDYxNy4wIKXMDSoASAFQAw%3"&"D%3D") -> https://www.google.com/maps/place/AccessHealth+Missouri+City+Clinic/@29.6175145,-95.5386005,17z/data=!3m1!4b1!4m6!3m5!1s0x8640e8f2465c6023:0xf54e0d695a0a28f2!8m2!3d29.6175099!4d-95.5360202!16s%2Fg%2F1v3lqbd7?entry=ttu&g_ep=EgoyMDI1MDYxNy4wIKXMDSoASAFQAw%3D%3D | Y13: =IFERROR(__xludf.DUMMYFUNCTION("""COMPUTED_VALUE"""),"Missouri City") -> Missouri City | Z13: =IFERROR(__xludf.DUMMYFUNCTION("""COMPUTED_VALUE"""),"Missouri City, Olde Missouri City Market Place, Quail Green South, Quail Valley, Sta-mo Annex") -> Missouri City, Olde Missouri City Market Place, Quail Green South, Quail Valley, Sta-mo Annex | AA13: =IFERROR(__xludf.DUMMYFUNCTION("""COMPUTED_VALUE"""),"AccessHealth") -> AccessHealth | AB13: =IFERROR(__xludf.DUMMYFUNCTION("""COMPUTED_VALUE"""),"Olde Missouri City Market Place") -> Olde Missouri City Market Place
A14: 13 | B14: =IFERROR(__xludf.DUMMYFUNCTION("""COMPUTED_VALUE"""),"[""77053"", ""77406"", ""77407"", ""77417"", ""77423"", ""77430"", ""77441"", ""77444"", ""77451"", ""77459"", ""77461"", ""77464"", ""77469"", ""77471"", ""77476"", ""77477"", ""77478"", ""77479"", ""77481"", ""77485"", ""77489"", ""77494"", ""77498"", "&"""77545"", ""77583"", ""77584""]") -> ["77053", "77406", "77407", "77417", "77423", "77430", "77441", "77444", "77451", "77459", "77461", "77464", "77469", "77471", "77476", "77477", "77478", "77479", "77481", "77485", "77489", "77494", "77498", "77545", "77583", "77584"] | C14: =IFERROR(__xludf.DUMMYFUNCTION("""COMPUTED_VALUE"""),"AccessHealth Richmond Clinic") -> AccessHealth Richmond Clinic | D14: =IFERROR(__xludf.DUMMYFUNCTION("""COMPUTED_VALUE"""),"400 Austin Street") -> 400 Austin Street | F14: =IFERROR(__xludf.DUMMYFUNCTION("""COMPUTED_VALUE"""),"Richmond") -> Richmond | G14: =IFERROR(__xludf.DUMMYFUNCTION("""COMPUTED_VALUE"""),"TX") -> TX | H14: =IFERROR(__xludf.DUMMYFUNCTION("""COMPUTED_VALUE"""),"77469") -> 77469 | I14: =IFERROR(__xludf.DUMMYFUNCTION("""COMPUTED_VALUE"""),"281-342-4530") -> 281-342-4530 | J14: =IFERROR(__xludf.DUMMYFUNCTION("""COMPUTED_VALUE"""),"29.578459, -95.759783") -> 29.578459, -95.759783 | K14: =IFERROR(__xludf.DUMMYFUNCTION("""COMPUTED_VALUE"""),"{""regular"":[{""days"":[""Mo"",""Tu"",""We"",""Th"",""Fr""],""open"":""07:00"",""close"":""17:00""},{""days"":[""Sa""],""open"":""08:00"",""close"":""12:00""}]}") -> {"regular":[{"days":["Mo","Tu","We","Th","Fr"],"open":"07:00","close":"17:00"},{"days":["Sa"],"open":"08:00","close":"12:00"}]} | M14: =IFERROR(__xludf.DUMMYFUNCTION("""COMPUTED_VALUE"""),31.0) -> 31 | N14: =IFERROR(__xludf.DUMMYFUNCTION("""COMPUTED_VALUE"""),"Medical - Primary Care") -> Medical - Primary Care | O14: =IFERROR(__xludf.DUMMYFUNCTION("""COMPUTED_VALUE"""),1.0) -> 1 | P14: =IFERROR(__xludf.DUMMYFUNCTION("""COMPUTED_VALUE"""),"ACTIVE") -> ACTIVE | Q14: =IFERROR(__xludf.DUMMYFUNCTION("""COMPUTED_VALUE"""),45831.0) -> 45831 | R14: =IFERROR(__xludf.DUMMYFUNCTION("""COMPUTED_VALUE"""),"Verified online") -> Verified online | S14: =IFERROR(__xludf.DUMMYFUNCTION("""COMPUTED_VALUE"""),"Family medicine, primary care, adults, women's health, pediatric, counseling and mental health, pharmacy, immunizations, Lab, OB.GYN, Hepatitis testing and treatment, substance abuse and addiction. AccessHealth is a private, not-for-profit organization an"&"d a Federally Qualified Health Center. It's primary focus is the low-income population of Fort Bend and Waller counties but will not turn anyone away, regardless of income or circumstance. Sliding scale of fee based on income.") -> Family medicine, primary care, adults, women's health, pediatric, counseling and mental health, pharmacy, immunizations, Lab, OB.GYN, Hepatitis testing and treatment, substance abuse and addiction. AccessHealth is a private, not-for-profit organization and a Federally Qualified Health Center. It's primary focus is the low-income population of Fort Bend and Waller counties but will not turn anyone away, regardless of income or circumstance. Sliding scale of fee based on income. | T14: =IFERROR(__xludf.DUMMYFUNCTION("""COMPUTED_VALUE"""),FALSE) -> FALSE | U14: =IFERROR(__xludf.DUMMYFUNCTION("""COMPUTED_VALUE"""),FALSE) -> FALSE | V14: =IFERROR(__xludf.DUMMYFUNCTION("""COMPUTED_VALUE"""),"https://www.myaccesshealth.org/") -> https://www.myaccesshealth.org/ | W14: =IFERROR(__xludf.DUMMYFUNCTION("""COMPUTED_VALUE"""),"https://www.google.com/maps/place/AccessHealth+Richmond+Clinic/@29.5786882,-95.7628537,17z/data=!3m1!4b1!4m6!3m5!1s0x86411e70c080105b:0x621ea27cba35c1c3!8m2!3d29.5786836!4d-95.7602734!16s%2Fg%2F1td72cvn?entry=ttu&g_ep=EgoyMDI1MDYxNy4wIKXMDSoASAFQAw%3D%3D") -> https://www.google.com/maps/place/AccessHealth+Richmond+Clinic/@29.5786882,-95.7628537,17z/data=!3m1!4b1!4m6!3m5!1s0x86411e70c080105b:0x621ea27cba35c1c3!8m2!3d29.5786836!4d-95.7602734!16s%2Fg%2F1td72cvn?entry=ttu&g_ep=EgoyMDI1MDYxNy4wIKXMDSoASAFQAw%3D%3D | Y14: =IFERROR(__xludf.DUMMYFUNCTION("""COMPUTED_VALUE"""),"Richmond") -> Richmond | Z14: =IFERROR(__xludf.DUMMYFUNCTION("""COMPUTED_VALUE"""),"Greatwood, Richmond") -> Greatwood, Richmond | AA14: =IFERROR(__xludf.DUMMYFUNCTION("""COMPUTED_VALUE"""),"AccessHealth") -> AccessHealth | AB14: =IFERROR(__xludf.DUMMYFUNCTION("""COMPUTED_VALUE"""),"Richmond") -> Richmond
A15: 14 | B15: =IFERROR(__xludf.DUMMYFUNCTION("""COMPUTED_VALUE"""),"[""77053"", ""77406"", ""77407"", ""77417"", ""77423"", ""77430"", ""77441"", ""77444"", ""77451"", ""77459"", ""77461"", ""77464"", ""77469"", ""77471"", ""77476"", ""77477"", ""77478"", ""77479"", ""77481"", ""77485"", ""77489"", ""77494"", ""77498"", "&"""77545"", ""77583"", ""77584""]") -> ["77053", "77406", "77407", "77417", "77423", "77430", "77441", "77444", "77451", "77459", "77461", "77464", "77469", "77471", "77476", "77477", "77478", "77479", "77481", "77485", "77489", "77494", "77498", "77545", "77583", "77584"] | C15: =IFERROR(__xludf.DUMMYFUNCTION("""COMPUTED_VALUE"""),"AccessHealth Rosenberg WIC Center") -> AccessHealth Rosenberg WIC Center | D15: =IFERROR(__xludf.DUMMYFUNCTION("""COMPUTED_VALUE"""),"1720 BF Terry Blvd") -> 1720 BF Terry Blvd | E15: =IFERROR(__xludf.DUMMYFUNCTION("""COMPUTED_VALUE"""),"Suite A") -> Suite A | F15: =IFERROR(__xludf.DUMMYFUNCTION("""COMPUTED_VALUE"""),"Rosenberg") -> Rosenberg | G15: =IFERROR(__xludf.DUMMYFUNCTION("""COMPUTED_VALUE"""),"TX") -> TX | H15: =IFERROR(__xludf.DUMMYFUNCTION("""COMPUTED_VALUE"""),"77471") -> 77471 | I15: =IFERROR(__xludf.DUMMYFUNCTION("""COMPUTED_VALUE"""),"281-238-2316") -> 281-238-2316 | J15: =IFERROR(__xludf.DUMMYFUNCTION("""COMPUTED_VALUE"""),"29.537481773188, -95.7748140958404") -> 29.537481773188, -95.7748140958404 | K15: =IFERROR(__xludf.DUMMYFUNCTION("""COMPUTED_VALUE"""),"{""regular"":[{""days"":[""Mo"",""We""],""open"":""08:00"",""close"":""17:00""},{""days"":[""Tu""],""open"":""08:00"",""close"":""19:00""},{""days"":[""Th""],""open"":""07:00"",""close"":""18:00""},{""days"":[""Fr""],""open"":""08:00"",""close"":""13:00"""&"}]}") -> {"regular":[{"days":["Mo","We"],"open":"08:00","close":"17:00"},{"days":["Tu"],"open":"08:00","close":"19:00"},{"days":["Th"],"open":"07:00","close":"18:00"},{"days":["Fr"],"open":"08:00","close":"13:00"}]} | M15: =IFERROR(__xludf.DUMMYFUNCTION("""COMPUTED_VALUE"""),44.0) -> 44 | N15: =IFERROR(__xludf.DUMMYFUNCTION("""COMPUTED_VALUE"""),"Mother & Child") -> Mother & Child | O15: =IFERROR(__xludf.DUMMYFUNCTION("""COMPUTED_VALUE"""),1.0) -> 1 | P15: =IFERROR(__xludf.DUMMYFUNCTION("""COMPUTED_VALUE"""),"ACTIVE") -> ACTIVE | Q15: =IFERROR(__xludf.DUMMYFUNCTION("""COMPUTED_VALUE"""),45831.0) -> 45831 | R15: =IFERROR(__xludf.DUMMYFUNCTION("""COMPUTED_VALUE"""),"Verified online") -> Verified online | S15: =IFERROR(__xludf.DUMMYFUNCTION("""COMPUTED_VALUE"""),"WIC is a special supplemental nutrition program for women, infants and children. It is a nutrition program for pregnant, breastfeeding women and families with children younger than 5 years old. To qualify you must meet income guidelines but if you receiv"&"e Medicaid, SNAP or TANF, then you already meet the income eligibility guidelines for WIC. AccessHealth is a private, not-for-profit organization and a Federally Qualified Health Center. It's primary focus is the low-income population of Fort Bend and Wa"&"ller counties but will not turn anyone away, regardless of income or circumstance. ") -> WIC is a special supplemental nutrition program for women, infants and children. It is a nutrition program for pregnant, breastfeeding women and families with children younger than 5 years old. To qualify you must meet income guidelines but if you receive Medicaid, SNAP or TANF, then you already meet the income eligibility guidelines for WIC. AccessHealth is a private, not-for-profit organization and a Federally Qualified Health Center. It's primary focus is the low-income population of Fort Bend and Waller counties but will not turn anyone away, regardless of income or circumstance. | T15: =IFERROR(__xludf.DUMMYFUNCTION("""COMPUTED_VALUE"""),FALSE) -> FALSE | U15: =IFERROR(__xludf.DUMMYFUNCTION("""COMPUTED_VALUE"""),FALSE) -> FALSE | V15: =IFERROR(__xludf.DUMMYFUNCTION("""COMPUTED_VALUE"""),"https://www.myaccesshealth.org/") -> https://www.myaccesshealth.org/ | W15: =IFERROR(__xludf.DUMMYFUNCTION("""COMPUTED_VALUE"""),"https://www.google.com/maps/place/Access+Health+Rosenberg+WIC+Clinic/@29.5538011,-95.769961,17z/data=!3m1!4b1!4m6!3m5!1s0x86411dcbe3b6a681:0x3c791560e4e234fd!8m2!3d29.5537965!4d-95.7673807!16s%2Fg%2F11bc73s7j8?entry=ttu&g_ep=EgoyMDI1MDYxNy4wIKXMDSoASAFQAw"&"%3D%3D") -> https://www.google.com/maps/place/Access+Health+Rosenberg+WIC+Clinic/@29.5538011,-95.769961,17z/data=!3m1!4b1!4m6!3m5!1s0x86411dcbe3b6a681:0x3c791560e4e234fd!8m2!3d29.5537965!4d-95.7673807!16s%2Fg%2F11bc73s7j8?entry=ttu&g_ep=EgoyMDI1MDYxNy4wIKXMDSoASAFQAw%3D%3D | Y15: =IFERROR(__xludf.DUMMYFUNCTION("""COMPUTED_VALUE"""),"Rosenberg") -> Rosenberg | Z15: =IFERROR(__xludf.DUMMYFUNCTION("""COMPUTED_VALUE"""),"Allendale Manor, Rosenberg, Timberlane Addition") -> Allendale Manor, Rosenberg, Timberlane Addition | AA15: =IFERROR(__xludf.DUMMYFUNCTION("""COMPUTED_VALUE"""),"AccessHealth") -> AccessHealth | AB15: =IFERROR(__xludf.DUMMYFUNCTION("""COMPUTED_VALUE"""),"Rosenberg") -> Rosenberg
A16: 15 | B16: =IFERROR(__xludf.DUMMYFUNCTION("""COMPUTED_VALUE"""),"[""77418"", ""77452"", ""77474""]") -> ["77418", "77452", "77474"] | C16: =IFERROR(__xludf.DUMMYFUNCTION("""COMPUTED_VALUE"""),"AccessHealth Sealy WIC Center") -> AccessHealth Sealy WIC Center | D16: =IFERROR(__xludf.DUMMYFUNCTION("""COMPUTED_VALUE"""),"526 Ward Street") -> 526 Ward Street | F16: =IFERROR(__xludf.DUMMYFUNCTION("""COMPUTED_VALUE"""),"Sealy") -> Sealy | G16: =IFERROR(__xludf.DUMMYFUNCTION("""COMPUTED_VALUE"""),"TX") -> TX | H16: =IFERROR(__xludf.DUMMYFUNCTION("""COMPUTED_VALUE"""),"77474") -> 77474 | I16: =IFERROR(__xludf.DUMMYFUNCTION("""COMPUTED_VALUE"""),"979-885-0517") -> 979-885-0517 | J16: =IFERROR(__xludf.DUMMYFUNCTION("""COMPUTED_VALUE"""),"29.7778938979592, -96.1603012857143") -> 29.7778938979592, -96.1603012857143 | K16: =IFERROR(__xludf.DUMMYFUNCTION("""COMPUTED_VALUE"""),"{""regular"":[{""days"":[""Mo""],""open"":""08:00"",""close"":""17:30""},{""days"":[""We""],""open"":""08:00"",""close"":""18:00""},{""days"":[""Fr"",""Sa""],""open"":""08:00"",""close"":""13:30""}]}") -> {"regular":[{"days":["Mo"],"open":"08:00","close":"17:30"},{"days":["We"],"open":"08:00","close":"18:00"},{"days":["Fr","Sa"],"open":"08:00","close":"13:30"}]} | M16: =IFERROR(__xludf.DUMMYFUNCTION("""COMPUTED_VALUE"""),44.0) -> 44 | N16: =IFERROR(__xludf.DUMMYFUNCTION("""COMPUTED_VALUE"""),"Mother & Child") -> Mother & Child | O16: =IFERROR(__xludf.DUMMYFUNCTION("""COMPUTED_VALUE"""),1.0) -> 1 | P16: =IFERROR(__xludf.DUMMYFUNCTION("""COMPUTED_VALUE"""),"ACTIVE") -> ACTIVE | Q16: =IFERROR(__xludf.DUMMYFUNCTION("""COMPUTED_VALUE"""),45831.0) -> 45831 | R16: =IFERROR(__xludf.DUMMYFUNCTION("""COMPUTED_VALUE"""),"Verified online") -> Verified online | S16: =IFERROR(__xludf.DUMMYFUNCTION("""COMPUTED_VALUE"""),"WIC is a special supplemental nutrition program for women, infants and children. It is a nutrition program for pregnant, breastfeeding women and families with children younger than 5 years old. To qualify you must meet income guidelines but if you receiv"&"e Medicaid, SNAP or TANF, then you already meet the income eligibility guidelines for WIC. AccessHealth is a private, not-for-profit organization and a Federally Qualified Health Center. It's primary focus is the low-income population of Fort Bend and Wa"&"ller counties but will not turn anyone away, regardless of income or circumstance. ") -> WIC is a special supplemental nutrition program for women, infants and children. It is a nutrition program for pregnant, breastfeeding women and families with children younger than 5 years old. To qualify you must meet income guidelines but if you receive Medicaid, SNAP or TANF, then you already meet the income eligibility guidelines for WIC. AccessHealth is a private, not-for-profit organization and a Federally Qualified Health Center. It's primary focus is the low-income population of Fort Bend and Waller counties but will not turn anyone away, regardless of income or circumstance. | T16: =IFERROR(__xludf.DUMMYFUNCTION("""COMPUTED_VALUE"""),FALSE) -> FALSE | U16: =IFERROR(__xludf.DUMMYFUNCTION("""COMPUTED_VALUE"""),FALSE) -> FALSE | V16: =IFERROR(__xludf.DUMMYFUNCTION("""COMPUTED_VALUE"""),"https://www.myaccesshealth.org/") -> https://www.myaccesshealth.org/ | W16: =IFERROR(__xludf.DUMMYFUNCTION("""COMPUTED_VALUE"""),"https://www.google.com/maps/place/Access+Health+Sealy+WIC+Clinic/@29.7775694,-96.1626114,17z/data=!3m1!4b1!4m6!3m5!1s0x864145c2ee89398d:0xf4a9afa58d7d4bb2!8m2!3d29.7775648!4d-96.1600311!16s%2Fg%2F11ql_575sd?entry=ttu&g_ep=EgoyMDI1MDYxNy4wIKXMDSoASAFQAw%3D"&"%3D") -> https://www.google.com/maps/place/Access+Health+Sealy+WIC+Clinic/@29.7775694,-96.1626114,17z/data=!3m1!4b1!4m6!3m5!1s0x864145c2ee89398d:0xf4a9afa58d7d4bb2!8m2!3d29.7775648!4d-96.1600311!16s%2Fg%2F11ql_575sd?entry=ttu&g_ep=EgoyMDI1MDYxNy4wIKXMDSoASAFQAw%3D%3D | Y16: =IFERROR(__xludf.DUMMYFUNCTION("""COMPUTED_VALUE"""),"Sealy") -> Sealy | Z16: =IFERROR(__xludf.DUMMYFUNCTION("""COMPUTED_VALUE"""),"Brazos Country, San Felipe, Sealy") -> Brazos Country, San Felipe, Sealy | AA16: =IFERROR(__xludf.DUMMYFUNCTION("""COMPUTED_VALUE"""),"AccessHealth") -> AccessHealth | AB16: =IFERROR(__xludf.DUMMYFUNCTION("""COMPUTED_VALUE"""),"Sealy") -> Sealy
A17: 16 | B17: =IFERROR(__xludf.DUMMYFUNCTION("""COMPUTED_VALUE"""),"[""77053"", ""77406"", ""77407"", ""77417"", ""77423"", ""77430"", ""77441"", ""77444"", ""77451"", ""77459"", ""77461"", ""77464"", ""77469"", ""77471"", ""77476"", ""77477"", ""77478"", ""77479"", ""77481"", ""77485"", ""77489"", ""77494"", ""77498"", "&"""77545"", ""77583"", ""77584""]") -> ["77053", "77406", "77407", "77417", "77423", "77430", "77441", "77444", "77451", "77459", "77461", "77464", "77469", "77471", "77476", "77477", "77478", "77479", "77481", "77485", "77489", "77494", "77498", "77545", "77583", "77584"] | C17: =IFERROR(__xludf.DUMMYFUNCTION("""COMPUTED_VALUE"""),"AccessHealth Second Mile Clinic") -> AccessHealth Second Mile Clinic | D17: =IFERROR(__xludf.DUMMYFUNCTION("""COMPUTED_VALUE"""),"1135 Hwy 90 Alt") -> 1135 Hwy 90 Alt | F17: =IFERROR(__xludf.DUMMYFUNCTION("""COMPUTED_VALUE"""),"Missouri City") -> Missouri City | G17: =IFERROR(__xludf.DUMMYFUNCTION("""COMPUTED_VALUE"""),"TX") -> TX | H17: =IFERROR(__xludf.DUMMYFUNCTION("""COMPUTED_VALUE"""),"77489") -> 77489 | I17: =IFERROR(__xludf.DUMMYFUNCTION("""COMPUTED_VALUE"""),"281-342-4530") -> 281-342-4530 | J17: =IFERROR(__xludf.DUMMYFUNCTION("""COMPUTED_VALUE"""),"29.620701912018554, -95.52988893726626") -> 29.620701912018554, -95.52988893726626 | K17: =IFERROR(__xludf.DUMMYFUNCTION("""COMPUTED_VALUE"""),"{""regular"":[{""days"":[""Mo"",""Tu"",""Th"",""Fr""],""open"":""07:00"",""close"":""17:00""},{""days"":[""We""],""open"":""07:00"",""close"":""18:00""}]}") -> {"regular":[{"days":["Mo","Tu","Th","Fr"],"open":"07:00","close":"17:00"},{"days":["We"],"open":"07:00","close":"18:00"}]} | M17: =IFERROR(__xludf.DUMMYFUNCTION("""COMPUTED_VALUE"""),31.0) -> 31 | N17: =IFERROR(__xludf.DUMMYFUNCTION("""COMPUTED_VALUE"""),"Medical - Primary Care") -> Medical - Primary Care | O17: =IFERROR(__xludf.DUMMYFUNCTION("""COMPUTED_VALUE"""),1.0) -> 1 | P17: =IFERROR(__xludf.DUMMYFUNCTION("""COMPUTED_VALUE"""),"ACTIVE") -> ACTIVE | Q17: =IFERROR(__xludf.DUMMYFUNCTION("""COMPUTED_VALUE"""),45831.0) -> 45831 | R17: =IFERROR(__xludf.DUMMYFUNCTION("""COMPUTED_VALUE"""),"Verified online") -> Verified online | S17: =IFERROR(__xludf.DUMMYFUNCTION("""COMPUTED_VALUE"""),"Family medicine, primary care, adults, women's health, pediatric, counseling and mental health, pharmacy, immunizations, Lab, OB.GYN, Hepatitis testing and treatment, substance abuse and addiction. AccessHealth is a private, not-for-profit organization an"&"d a Federally Qualified Health Center. It's primary focus is the low-income population of Fort Bend and Waller counties but will not turn anyone away, regardless of income or circumstance. Sliding scale of fee based on income.") -> Family medicine, primary care, adults, women's health, pediatric, counseling and mental health, pharmacy, immunizations, Lab, OB.GYN, Hepatitis testing and treatment, substance abuse and addiction. AccessHealth is a private, not-for-profit organization and a Federally Qualified Health Center. It's primary focus is the low-income population of Fort Bend and Waller counties but will not turn anyone away, regardless of income or circumstance. Sliding scale of fee based on income. | T17: =IFERROR(__xludf.DUMMYFUNCTION("""COMPUTED_VALUE"""),FALSE) -> FALSE | U17: =IFERROR(__xludf.DUMMYFUNCTION("""COMPUTED_VALUE"""),FALSE) -> FALSE | V17: =IFERROR(__xludf.DUMMYFUNCTION("""COMPUTED_VALUE"""),"https://www.myaccesshealth.org/") -> https://www.myaccesshealth.org/ | W17: =IFERROR(__xludf.DUMMYFUNCTION("""COMPUTED_VALUE"""),"https://www.google.com/maps/place/AccessHealth+Second+Mile+Clinic/@29.6205168,-95.5324576,17z/data=!3m1!4b1!4m6!3m5!1s0x8640e9ffb088e7c1:0x9b6babdfeeae07e7!8m2!3d29.6205122!4d-95.5298773!16s%2Fg%2F11l2x99fkq?entry=ttu&g_ep=EgoyMDI1MDYxNy4wIKXMDSoASAFQAw%3"&"D%3D") -> https://www.google.com/maps/place/AccessHealth+Second+Mile+Clinic/@29.6205168,-95.5324576,17z/data=!3m1!4b1!4m6!3m5!1s0x8640e9ffb088e7c1:0x9b6babdfeeae07e7!8m2!3d29.6205122!4d-95.5298773!16s%2Fg%2F11l2x99fkq?entry=ttu&g_ep=EgoyMDI1MDYxNy4wIKXMDSoASAFQAw%3D%3D | Y17: =IFERROR(__xludf.DUMMYFUNCTION("""COMPUTED_VALUE"""),"Missouri City") -> Missouri City | Z17: =IFERROR(__xludf.DUMMYFUNCTION("""COMPUTED_VALUE"""),"Missouri City, Olde Missouri City Market Place, Quail Green South, Quail Valley, Sta-mo Annex") -> Missouri City, Olde Missouri City Market Place, Quail Green South, Quail Valley, Sta-mo Annex | AA17: =IFERROR(__xludf.DUMMYFUNCTION("""COMPUTED_VALUE"""),"AccessHealth") -> AccessHealth | AB17: =IFERROR(__xludf.DUMMYFUNCTION("""COMPUTED_VALUE"""),"Missouri City") -> Missouri City
A18: 17 | B18: =IFERROR(__xludf.DUMMYFUNCTION("""COMPUTED_VALUE"""),"[""77053"", ""77406"", ""77407"", ""77417"", ""77423"", ""77430"", ""77441"", ""77444"", ""77451"", ""77459"", ""77461"", ""77464"", ""77469"", ""77471"", ""77476"", ""77477"", ""77478"", ""77479"", ""77481"", ""77485"", ""77489"", ""77494"", ""77498"", "&"""77545"", ""77583"", ""77584""]") -> ["77053", "77406", "77407", "77417", "77423", "77430", "77441", "77444", "77451", "77459", "77461", "77464", "77469", "77471", "77476", "77477", "77478", "77479", "77481", "77485", "77489", "77494", "77498", "77545", "77583", "77584"] | C18: =IFERROR(__xludf.DUMMYFUNCTION("""COMPUTED_VALUE"""),"AccessHealth Stafford Clinic") -> AccessHealth Stafford Clinic | D18: =IFERROR(__xludf.DUMMYFUNCTION("""COMPUTED_VALUE"""),"10435 Greenbough Drive") -> 10435 Greenbough Drive | E18: =IFERROR(__xludf.DUMMYFUNCTION("""COMPUTED_VALUE"""),"Suite 300") -> Suite 300 | F18: =IFERROR(__xludf.DUMMYFUNCTION("""COMPUTED_VALUE"""),"Stafford") -> Stafford | G18: =IFERROR(__xludf.DUMMYFUNCTION("""COMPUTED_VALUE"""),"TX") -> TX | H18: =IFERROR(__xludf.DUMMYFUNCTION("""COMPUTED_VALUE"""),"77477") -> 77477 | I18: =IFERROR(__xludf.DUMMYFUNCTION("""COMPUTED_VALUE"""),"281-342-4530") -> 281-342-4530 | J18: =IFERROR(__xludf.DUMMYFUNCTION("""COMPUTED_VALUE"""),"29.6210934081633, -95.5623412653061") -> 29.6210934081633, -95.5623412653061 | K18: =IFERROR(__xludf.DUMMYFUNCTION("""COMPUTED_VALUE"""),"{""regular"":[{""days"":[""Mo"",""Tu"",""We"",""Th"",""Fr""],""open"":""07:00"",""close"":""17:00""}]}") -> {"regular":[{"days":["Mo","Tu","We","Th","Fr"],"open":"07:00","close":"17:00"}]} | M18: =IFERROR(__xludf.DUMMYFUNCTION("""COMPUTED_VALUE"""),31.0) -> 31 | N18: =IFERROR(__xludf.DUMMYFUNCTION("""COMPUTED_VALUE"""),"Medical - Primary Care") -> Medical - Primary Care | O18: =IFERROR(__xludf.DUMMYFUNCTION("""COMPUTED_VALUE"""),1.0) -> 1 | P18: =IFERROR(__xludf.DUMMYFUNCTION("""COMPUTED_VALUE"""),"ACTIVE") -> ACTIVE | Q18: =IFERROR(__xludf.DUMMYFUNCTION("""COMPUTED_VALUE"""),45831.0) -> 45831 | R18: =IFERROR(__xludf.DUMMYFUNCTION("""COMPUTED_VALUE"""),"Verified online") -> Verified online | S18: =IFERROR(__xludf.DUMMYFUNCTION("""COMPUTED_VALUE"""),"Family medicine, primary care, adults, women's health, pediatric, dental care, counseling and mental health, pharmacy, immunizations, Lab, OB.GYN, Hepatitis testing and treatment, substance abuse and addiction. AccessHealth is a private, not-for-profit or"&"ganization and a Federally Qualified Health Center. It's primary focus is the low-income population of Fort Bend and Waller counties but will not turn anyone away, regardless of income or circumstance. Sliding scale of fee based on income.") -> Family medicine, primary care, adults, women's health, pediatric, dental care, counseling and mental health, pharmacy, immunizations, Lab, OB.GYN, Hepatitis testing and treatment, substance abuse and addiction. AccessHealth is a private, not-for-profit organization and a Federally Qualified Health Center. It's primary focus is the low-income population of Fort Bend and Waller counties but will not turn anyone away, regardless of income or circumstance. Sliding scale of fee based on income. | T18: =IFERROR(__xludf.DUMMYFUNCTION("""COMPUTED_VALUE"""),FALSE) -> FALSE | U18: =IFERROR(__xludf.DUMMYFUNCTION("""COMPUTED_VALUE"""),FALSE) -> FALSE | V18: =IFERROR(__xludf.DUMMYFUNCTION("""COMPUTED_VALUE"""),"https://www.myaccesshealth.org/") -> https://www.myaccesshealth.org/ | W18: =IFERROR(__xludf.DUMMYFUNCTION("""COMPUTED_VALUE"""),"https://www.google.com/maps/place/AccessHealth+Stafford+Clinic/@29.6205769,-95.5674255,16z/data=!3m1!4b1!4m6!3m5!1s0x8640e62a1e55c92b:0xaffc49351a84756c!8m2!3d29.6205723!4d-95.5625492!16s%2Fg%2F11hd9qz3ct?entry=ttu&g_ep=EgoyMDI1MDYxNy4wIKXMDSoASAFQAw%3D%3"&"D") -> https://www.google.com/maps/place/AccessHealth+Stafford+Clinic/@29.6205769,-95.5674255,16z/data=!3m1!4b1!4m6!3m5!1s0x8640e62a1e55c92b:0xaffc49351a84756c!8m2!3d29.6205723!4d-95.5625492!16s%2Fg%2F11hd9qz3ct?entry=ttu&g_ep=EgoyMDI1MDYxNy4wIKXMDSoASAFQAw%3D%3D | Y18: =IFERROR(__xludf.DUMMYFUNCTION("""COMPUTED_VALUE"""),"Stafford") -> Stafford | Z18: =IFERROR(__xludf.DUMMYFUNCTION("""COMPUTED_VALUE"""),"Clark Plaza One, Corporate Bus Park, Greenbriar Southwest, Stafford, The Fountains") -> Clark Plaza One, Corporate Bus Park, Greenbriar Southwest, Stafford, The Fountains | AA18: =IFERROR(__xludf.DUMMYFUNCTION("""COMPUTED_VALUE"""),"AccessHealth") -> AccessHealth | AB18: =IFERROR(__xludf.DUMMYFUNCTION("""COMPUTED_VALUE"""),"Greenbriar Southwest") -> Greenbriar Southwest
A19: 18 | B19: =IFERROR(__xludf.DUMMYFUNCTION("""COMPUTED_VALUE"""),"[""77053"", ""77406"", ""77407"", ""77417"", ""77423"", ""77430"", ""77441"", ""77444"", ""77451"", ""77459"", ""77461"", ""77464"", ""77469"", ""77471"", ""77476"", ""77477"", ""77478"", ""77479"", ""77481"", ""77485"", ""77489"", ""77494"", ""77498"", "&"""77545"", ""77583"", ""77584""]") -> ["77053", "77406", "77407", "77417", "77423", "77430", "77441", "77444", "77451", "77459", "77461", "77464", "77469", "77471", "77476", "77477", "77478", "77479", "77481", "77485", "77489", "77494", "77498", "77545", "77583", "77584"] | C19: =IFERROR(__xludf.DUMMYFUNCTION("""COMPUTED_VALUE"""),"AccessHealth Stafford Clinic") -> AccessHealth Stafford Clinic | D19: =IFERROR(__xludf.DUMMYFUNCTION("""COMPUTED_VALUE"""),"10435 Greenbough Drive") -> 10435 Greenbough Drive | E19: =IFERROR(__xludf.DUMMYFUNCTION("""COMPUTED_VALUE"""),"Suite 300") -> Suite 300 | F19: =IFERROR(__xludf.DUMMYFUNCTION("""COMPUTED_VALUE"""),"Stafford") -> Stafford | G19: =IFERROR(__xludf.DUMMYFUNCTION("""COMPUTED_VALUE"""),"TX") -> TX | H19: =IFERROR(__xludf.DUMMYFUNCTION("""COMPUTED_VALUE"""),"77477") -> 77477 | I19: =IFERROR(__xludf.DUMMYFUNCTION("""COMPUTED_VALUE"""),"281-342-4530") -> 281-342-4530 | J19: =IFERROR(__xludf.DUMMYFUNCTION("""COMPUTED_VALUE"""),"29.6210934081633, -95.5623412653061") -> 29.6210934081633, -95.5623412653061 | K19: =IFERROR(__xludf.DUMMYFUNCTION("""COMPUTED_VALUE"""),"{""regular"":[{""days"":[""Mo"",""Tu"",""We"",""Th"",""Fr""],""open"":""07:00"",""close"":""17:00""}]}") -> {"regular":[{"days":["Mo","Tu","We","Th","Fr"],"open":"07:00","close":"17:00"}]} | M19: =IFERROR(__xludf.DUMMYFUNCTION("""COMPUTED_VALUE"""),32.0) -> 32 | N19: =IFERROR(__xludf.DUMMYFUNCTION("""COMPUTED_VALUE"""),"Medical - Dental & Vision") -> Medical - Dental & Vision | O19: =IFERROR(__xludf.DUMMYFUNCTION("""COMPUTED_VALUE"""),1.0) -> 1 | P19: =IFERROR(__xludf.DUMMYFUNCTION("""COMPUTED_VALUE"""),"ACTIVE") -> ACTIVE | Q19: =IFERROR(__xludf.DUMMYFUNCTION("""COMPUTED_VALUE"""),46048.0) -> 46048 | R19: =IFERROR(__xludf.DUMMYFUNCTION("""COMPUTED_VALUE"""),"Verified online") -> Verified online | S19: =IFERROR(__xludf.DUMMYFUNCTION("""COMPUTED_VALUE"""),"Dental Includes cleanings, exams, x-rays, sealants, fillings, extractions, bridges, partials and dental emergencies AccessHealth is a private, not-for-profit organization and a Federally Qualified Health Center. It's primary focus is the low-income popul"&"ation of Fort Bend and Waller counties but will not turn anyone away, regardless of income or circumstance. Sliding scale of fee based on income.") -> Dental Includes cleanings, exams, x-rays, sealants, fillings, extractions, bridges, partials and dental emergencies AccessHealth is a private, not-for-profit organization and a Federally Qualified Health Center. It's primary focus is the low-income population of Fort Bend and Waller counties but will not turn anyone away, regardless of income or circumstance. Sliding scale of fee based on income. | T19: =IFERROR(__xludf.DUMMYFUNCTION("""COMPUTED_VALUE"""),TRUE) -> TRUE | U19: =IFERROR(__xludf.DUMMYFUNCTION("""COMPUTED_VALUE"""),FALSE) -> FALSE | V19: =IFERROR(__xludf.DUMMYFUNCTION("""COMPUTED_VALUE"""),"https://www.myaccesshealth.org/") -> https://www.myaccesshealth.org/ | W19: =IFERROR(__xludf.DUMMYFUNCTION("""COMPUTED_VALUE"""),"https://www.google.com/maps/place/AccessHealth+Stafford+Clinic/@29.6205769,-95.5674255,16z/data=!3m1!4b1!4m6!3m5!1s0x8640e62a1e55c92b:0xaffc49351a84756c!8m2!3d29.6205723!4d-95.5625492!16s%2Fg%2F11hd9qz3ct?entry=ttu&g_ep=EgoyMDI1MDYxNy4wIKXMDSoASAFQAw%3D%3"&"D") -> https://www.google.com/maps/place/AccessHealth+Stafford+Clinic/@29.6205769,-95.5674255,16z/data=!3m1!4b1!4m6!3m5!1s0x8640e62a1e55c92b:0xaffc49351a84756c!8m2!3d29.6205723!4d-95.5625492!16s%2Fg%2F11hd9qz3ct?entry=ttu&g_ep=EgoyMDI1MDYxNy4wIKXMDSoASAFQAw%3D%3D | Y19: =IFERROR(__xludf.DUMMYFUNCTION("""COMPUTED_VALUE"""),"Stafford") -> Stafford | Z19: =IFERROR(__xludf.DUMMYFUNCTION("""COMPUTED_VALUE"""),"Clark Plaza One, Corporate Bus Park, Greenbriar Southwest, Stafford, The Fountains") -> Clark Plaza One, Corporate Bus Park, Greenbriar Southwest, Stafford, The Fountains | AA19: =IFERROR(__xludf.DUMMYFUNCTION("""COMPUTED_VALUE"""),"AccessHealth") -> AccessHealth | AB19: =IFERROR(__xludf.DUMMYFUNCTION("""COMPUTED_VALUE"""),"Greenbriar Southwest") -> Greenbriar Southwest
A20: 19 | B20: =IFERROR(__xludf.DUMMYFUNCTION("""COMPUTED_VALUE"""),"[""77053"", ""77406"", ""77407"", ""77417"", ""77423"", ""77430"", ""77441"", ""77444"", ""77451"", ""77459"", ""77461"", ""77464"", ""77469"", ""77471"", ""77476"", ""77477"", ""77478"", ""77479"", ""77481"", ""77485"", ""77489"", ""77494"", ""77498"", "&"""77545"", ""77583"", ""77584""]") -> ["77053", "77406", "77407", "77417", "77423", "77430", "77441", "77444", "77451", "77459", "77461", "77464", "77469", "77471", "77476", "77477", "77478", "77479", "77481", "77485", "77489", "77494", "77498", "77545", "77583", "77584"] | C20: =IFERROR(__xludf.DUMMYFUNCTION("""COMPUTED_VALUE"""),"AccessHealth Stafford WIC Center") -> AccessHealth Stafford WIC Center | D20: =IFERROR(__xludf.DUMMYFUNCTION("""COMPUTED_VALUE"""),"10435 Greenbough Drive") -> 10435 Greenbough Drive | E20: =IFERROR(__xludf.DUMMYFUNCTION("""COMPUTED_VALUE"""),"Suite 300") -> Suite 300 | F20: =IFERROR(__xludf.DUMMYFUNCTION("""COMPUTED_VALUE"""),"Stafford") -> Stafford | G20: =IFERROR(__xludf.DUMMYFUNCTION("""COMPUTED_VALUE"""),"TX") -> TX | H20: =IFERROR(__xludf.DUMMYFUNCTION("""COMPUTED_VALUE"""),"77477") -> 77477 | I20: =IFERROR(__xludf.DUMMYFUNCTION("""COMPUTED_VALUE"""),"281-969-1835") -> 281-969-1835 | J20: =IFERROR(__xludf.DUMMYFUNCTION("""COMPUTED_VALUE"""),"29.6210934081633, -95.5623412653061") -> 29.6210934081633, -95.5623412653061 | K20: =IFERROR(__xludf.DUMMYFUNCTION("""COMPUTED_VALUE"""),"{""regular"":[{""days"":[""Mo"",""We""],""open"":""08:00"",""close"":""17:00""},{""days"":[""Tu""],""open"":""08:00"",""close"":""19:00""},{""days"":[""Th""],""open"":""07:00"",""close"":""18:00""},{""days"":[""Fr""],""open"":""08:00"",""close"":""13:00"""&"}]}") -> {"regular":[{"days":["Mo","We"],"open":"08:00","close":"17:00"},{"days":["Tu"],"open":"08:00","close":"19:00"},{"days":["Th"],"open":"07:00","close":"18:00"},{"days":["Fr"],"open":"08:00","close":"13:00"}]} | M20: =IFERROR(__xludf.DUMMYFUNCTION("""COMPUTED_VALUE"""),44.0) -> 44 | N20: =IFERROR(__xludf.DUMMYFUNCTION("""COMPUTED_VALUE"""),"Mother & Child") -> Mother & Child | O20: =IFERROR(__xludf.DUMMYFUNCTION("""COMPUTED_VALUE"""),1.0) -> 1 | P20: =IFERROR(__xludf.DUMMYFUNCTION("""COMPUTED_VALUE"""),"ACTIVE") -> ACTIVE | Q20: =IFERROR(__xludf.DUMMYFUNCTION("""COMPUTED_VALUE"""),45831.0) -> 45831 | R20: =IFERROR(__xludf.DUMMYFUNCTION("""COMPUTED_VALUE"""),"Verified online") -> Verified online | S20: =IFERROR(__xludf.DUMMYFUNCTION("""COMPUTED_VALUE"""),"WIC is a special supplemental nutrition program for women, infants and children. It is a nutrition program for pregnant, breastfeeding women and families with children younger than 5 years old. To qualify you must meet income guidelines but if you receiv"&"e Medicaid, SNAP or TANF, then you already meet the income eligibility guidelines for WIC. AccessHealth is a private, not-for-profit organization and a Federally Qualified Health Center. It's primary focus is the low-income population of Fort Bend and Wa"&"ller counties but will not turn anyone away, regardless of income or circumstance. ") -> WIC is a special supplemental nutrition program for women, infants and children. It is a nutrition program for pregnant, breastfeeding women and families with children younger than 5 years old. To qualify you must meet income guidelines but if you receive Medicaid, SNAP or TANF, then you already meet the income eligibility guidelines for WIC. AccessHealth is a private, not-for-profit organization and a Federally Qualified Health Center. It's primary focus is the low-income population of Fort Bend and Waller counties but will not turn anyone away, regardless of income or circumstance. | T20: =IFERROR(__xludf.DUMMYFUNCTION("""COMPUTED_VALUE"""),FALSE) -> FALSE | U20: =IFERROR(__xludf.DUMMYFUNCTION("""COMPUTED_VALUE"""),FALSE) -> FALSE | V20: =IFERROR(__xludf.DUMMYFUNCTION("""COMPUTED_VALUE"""),"https://www.myaccesshealth.org/") -> https://www.myaccesshealth.org/ | W20: =IFERROR(__xludf.DUMMYFUNCTION("""COMPUTED_VALUE"""),"https://www.google.com/maps/place/Access+Health+Stafford+WIC+Clinic/@29.6206841,-95.5651997,17z/data=!3m1!4b1!4m6!3m5!1s0x8640e62a1dd7f35d:0xc95ea2dcf95c8f93!8m2!3d29.6206795!4d-95.5626194!16s%2Fg%2F1v_w2r9z?entry=ttu&g_ep=EgoyMDI1MDYxNy4wIKXMDSoASAFQAw%3"&"D%3D") -> https://www.google.com/maps/place/Access+Health+Stafford+WIC+Clinic/@29.6206841,-95.5651997,17z/data=!3m1!4b1!4m6!3m5!1s0x8640e62a1dd7f35d:0xc95ea2dcf95c8f93!8m2!3d29.6206795!4d-95.5626194!16s%2Fg%2F1v_w2r9z?entry=ttu&g_ep=EgoyMDI1MDYxNy4wIKXMDSoASAFQAw%3D%3D | Y20: =IFERROR(__xludf.DUMMYFUNCTION("""COMPUTED_VALUE"""),"Stafford") -> Stafford | Z20: =IFERROR(__xludf.DUMMYFUNCTION("""COMPUTED_VALUE"""),"Clark Plaza One, Corporate Bus Park, Greenbriar Southwest, Stafford, The Fountains") -> Clark Plaza One, Corporate Bus Park, Greenbriar Southwest, Stafford, The Fountains | AA20: =IFERROR(__xludf.DUMMYFUNCTION("""COMPUTED_VALUE"""),"AccessHealth") -> AccessHealth | AB20: =IFERROR(__xludf.DUMMYFUNCTION("""COMPUTED_VALUE"""),"Greenbriar Southwest") -> Greenbriar Southwest
A21: 20 | B21: =IFERROR(__xludf.DUMMYFUNCTION("""COMPUTED_VALUE"""),"[""77488""]") -> ["77488"] | C21: =IFERROR(__xludf.DUMMYFUNCTION("""COMPUTED_VALUE"""),"AccessHealth Wharton WIC Center") -> AccessHealth Wharton WIC Center | D21: =IFERROR(__xludf.DUMMYFUNCTION("""COMPUTED_VALUE"""),"20115 N Fulton Street") -> 20115 N Fulton Street | F21: =IFERROR(__xludf.DUMMYFUNCTION("""COMPUTED_VALUE"""),"Wharton") -> Wharton | G21: =IFERROR(__xludf.DUMMYFUNCTION("""COMPUTED_VALUE"""),"TX") -> TX | H21: =IFERROR(__xludf.DUMMYFUNCTION("""COMPUTED_VALUE"""),"77488") -> 77488 | I21: =IFERROR(__xludf.DUMMYFUNCTION("""COMPUTED_VALUE"""),"979-532-8755") -> 979-532-8755 | J21: =IFERROR(__xludf.DUMMYFUNCTION("""COMPUTED_VALUE"""),"29.329366007624188, -96.09311470962987") -> 29.329366007624188, -96.09311470962987 | K21: =IFERROR(__xludf.DUMMYFUNCTION("""COMPUTED_VALUE"""),"{""regular"":[{""days"":[""Mo"",""We""],""open"":""08:00"",""close"":""17:00""},{""days"":[""Tu""],""open"":""08:00"",""close"":""19:00""},{""days"":[""Th""],""open"":""07:00"",""close"":""18:00""},{""days"":[""Fr""],""open"":""08:00"",""close"":""13:00"""&"}]}") -> {"regular":[{"days":["Mo","We"],"open":"08:00","close":"17:00"},{"days":["Tu"],"open":"08:00","close":"19:00"},{"days":["Th"],"open":"07:00","close":"18:00"},{"days":["Fr"],"open":"08:00","close":"13:00"}]} | M21: =IFERROR(__xludf.DUMMYFUNCTION("""COMPUTED_VALUE"""),44.0) -> 44 | N21: =IFERROR(__xludf.DUMMYFUNCTION("""COMPUTED_VALUE"""),"Mother & Child") -> Mother & Child | O21: =IFERROR(__xludf.DUMMYFUNCTION("""COMPUTED_VALUE"""),1.0) -> 1 | P21: =IFERROR(__xludf.DUMMYFUNCTION("""COMPUTED_VALUE"""),"ACTIVE") -> ACTIVE | Q21: =IFERROR(__xludf.DUMMYFUNCTION("""COMPUTED_VALUE"""),45831.0) -> 45831 | R21: =IFERROR(__xludf.DUMMYFUNCTION("""COMPUTED_VALUE"""),"Verified online") -> Verified online | S21: =IFERROR(__xludf.DUMMYFUNCTION("""COMPUTED_VALUE"""),"WIC is a special supplemental nutrition program for women, infants and children. It is a nutrition program for pregnant, breastfeeding women and families with children younger than 5 years old. To qualify you must meet income guidelines but if you receiv"&"e Medicaid, SNAP or TANF, then you already meet the income eligibility guidelines for WIC. AccessHealth is a private, not-for-profit organization and a Federally Qualified Health Center. It's primary focus is the low-income population of Fort Bend and Wa"&"ller counties but will not turn anyone away, regardless of income or circumstance. ") -> WIC is a special supplemental nutrition program for women, infants and children. It is a nutrition program for pregnant, breastfeeding women and families with children younger than 5 years old. To qualify you must meet income guidelines but if you receive Medicaid, SNAP or TANF, then you already meet the income eligibility guidelines for WIC. AccessHealth is a private, not-for-profit organization and a Federally Qualified Health Center. It's primary focus is the low-income population of Fort Bend and Waller counties but will not turn anyone away, regardless of income or circumstance. | T21: =IFERROR(__xludf.DUMMYFUNCTION("""COMPUTED_VALUE"""),FALSE) -> FALSE | U21: =IFERROR(__xludf.DUMMYFUNCTION("""COMPUTED_VALUE"""),FALSE) -> FALSE | V21: =IFERROR(__xludf.DUMMYFUNCTION("""COMPUTED_VALUE"""),"https://www.myaccesshealth.org/") -> https://www.myaccesshealth.org/ | W21: =IFERROR(__xludf.DUMMYFUNCTION("""COMPUTED_VALUE"""),"https://www.google.com/maps/place/Access+Health+Wharton+WIC+Clinic/@29.3292211,-96.0957272,16z/data=!3m1!4b1!4m6!3m5!1s0x864174e69c244ca1:0x19aa48ea44b3deee!8m2!3d29.3292164!4d-96.0931469!16s%2Fg%2F1td6b80l?entry=ttu&g_ep=EgoyMDI1MDYxNy4wIKXMDSoASAFQAw%3D"&"%3D") -> https://www.google.com/maps/place/Access+Health+Wharton+WIC+Clinic/@29.3292211,-96.0957272,16z/data=!3m1!4b1!4m6!3m5!1s0x864174e69c244ca1:0x19aa48ea44b3deee!8m2!3d29.3292164!4d-96.0931469!16s%2Fg%2F1td6b80l?entry=ttu&g_ep=EgoyMDI1MDYxNy4wIKXMDSoASAFQAw%3D%3D | Y21: =IFERROR(__xludf.DUMMYFUNCTION("""COMPUTED_VALUE"""),"Wharton") -> Wharton | Z21: =IFERROR(__xludf.DUMMYFUNCTION("""COMPUTED_VALUE"""),"Wharton") -> Wharton | AA21: =IFERROR(__xludf.DUMMYFUNCTION("""COMPUTED_VALUE"""),"AccessHealth") -> AccessHealth | AB21: =IFERROR(__xludf.DUMMYFUNCTION("""COMPUTED_VALUE"""),"Wharton") -> Wharton
A22: 21 | B22: =IFERROR(__xludf.DUMMYFUNCTION("""COMPUTED_VALUE"""),"[""99999""]") -> ["99999"] | C22: =IFERROR(__xludf.DUMMYFUNCTION("""COMPUTED_VALUE"""),"Accessia Health") -> Accessia Health | D22: =IFERROR(__xludf.DUMMYFUNCTION("""COMPUTED_VALUE"""),"3104 E Boundary Court") -> 3104 E Boundary Court | F22: =IFERROR(__xludf.DUMMYFUNCTION("""COMPUTED_VALUE"""),"Midlothian") -> Midlothian | G22: =IFERROR(__xludf.DUMMYFUNCTION("""COMPUTED_VALUE"""),"VA") -> VA | H22: =IFERROR(__xludf.DUMMYFUNCTION("""COMPUTED_VALUE"""),"23112") -> 23112 | I22: =IFERROR(__xludf.DUMMYFUNCTION("""COMPUTED_VALUE"""),"800-366-7741") -> 800-366-7741 | J22: =IFERROR(__xludf.DUMMYFUNCTION("""COMPUTED_VALUE"""),"37.44735944105023, -77.64545707622406") -> 37.44735944105023, -77.64545707622406 | K22: =IFERROR(__xludf.DUMMYFUNCTION("""COMPUTED_VALUE"""),"{""regular"":[{""days"":[""Mo"",""Tu"",""Th"",""Fr""],""open"":""08:30"",""close"":""17:00""},{""days"":[""We""],""open"":""09:30"",""close"":""17:00""}]}") -> {"regular":[{"days":["Mo","Tu","Th","Fr"],"open":"08:30","close":"17:00"},{"days":["We"],"open":"09:30","close":"17:00"}]} | L22: =IFERROR(__xludf.DUMMYFUNCTION("""COMPUTED_VALUE"""),"Apply online") -> Apply online | M22: =IFERROR(__xludf.DUMMYFUNCTION("""COMPUTED_VALUE"""),36.0) -> 36 | N22: =IFERROR(__xludf.DUMMYFUNCTION("""COMPUTED_VALUE"""),"Medical - Bill Payment") -> Medical - Bill Payment | O22: =IFERROR(__xludf.DUMMYFUNCTION("""COMPUTED_VALUE"""),1.0) -> 1 | P22: =IFERROR(__xludf.DUMMYFUNCTION("""COMPUTED_VALUE"""),"ACTIVE") -> ACTIVE | R22: =IFERROR(__xludf.DUMMYFUNCTION("""COMPUTED_VALUE"""),"Verified online") -> Verified online | S22: =IFERROR(__xludf.DUMMYFUNCTION("""COMPUTED_VALUE"""),"Offers financial assistance to eligible individuals to pay for health insurance premiums, medication copayments, travel and other essential medical expenses. Must meet income guidelines and a diagnosed, covered medication condition. Check eligibility and"&" apply online. A charitable patient assistance foundation.") -> Offers financial assistance to eligible individuals to pay for health insurance premiums, medication copayments, travel and other essential medical expenses. Must meet income guidelines and a diagnosed, covered medication condition. Check eligibility and apply online. A charitable patient assistance foundation. | T22: =IFERROR(__xludf.DUMMYFUNCTION("""COMPUTED_VALUE"""),FALSE) -> FALSE | U22: =IFERROR(__xludf.DUMMYFUNCTION("""COMPUTED_VALUE"""),FALSE) -> FALSE | V22: =IFERROR(__xludf.DUMMYFUNCTION("""COMPUTED_VALUE"""),"https://accessiahealth.org") -> https://accessiahealth.org | W22: =IFERROR(__xludf.DUMMYFUNCTION("""COMPUTED_VALUE"""),"https://www.google.com/maps/place/Accessia+Health/@37.447121,-77.6480803,17z/data=!3m1!4b1!4m6!3m5!1s0x89b173d0fbba5d41:0x4ec81be8dbc6a9e5!8m2!3d37.447121!4d-77.6455!16s%2Fg%2F113g6sbc5?entry=ttu&g_ep=EgoyMDI2MDEyMC4wIKXMDSoKLDEwMDc5MjA2OUgBUAM%3D") -> https://www.google.com/maps/place/Accessia+Health/@37.447121,-77.6480803,17z/data=!3m1!4b1!4m6!3m5!1s0x89b173d0fbba5d41:0x4ec81be8dbc6a9e5!8m2!3d37.447121!4d-77.6455!16s%2Fg%2F113g6sbc5?entry=ttu&g_ep=EgoyMDI2MDEyMC4wIKXMDSoKLDEwMDc5MjA2OUgBUAM%3D | Y22: =IFERROR(__xludf.DUMMYFUNCTION("""COMPUTED_VALUE"""),"Midlothian") -> Midlothian | Z22: =IFERROR(__xludf.DUMMYFUNCTION("""COMPUTED_VALUE"""),"Brandermill") -> Brandermill | AA22: =IFERROR(__xludf.DUMMYFUNCTION("""COMPUTED_VALUE"""),"Accessia Health") -> Accessia Health | AB22: =IFERROR(__xludf.DUMMYFUNCTION("""COMPUTED_VALUE"""),"Brandermill") -> Brandermill
A23: 22 | B23: =IFERROR(__xludf.DUMMYFUNCTION("""COMPUTED_VALUE"""),"[""77002"", ""77003"", ""77004"", ""77005"", ""77006"", ""77007"", ""77008"", ""77009"", ""77010"", ""77011"", ""77012"", ""77013"", ""77014"", ""77015"", ""77016"", ""77017"", ""77018"", ""77019"", ""77020"", ""77021"", ""77022"", ""77023"", ""77024"", "&"""77025"", ""77026"", ""77027"", ""77028"", ""77029"", ""77030"", ""77031"", ""77032"", ""77033"", ""77034"", ""77035"", ""77036"", ""77037"", ""77038"", ""77039"", ""77040"", ""77041"", ""77042"", ""77043"", ""77044"", ""77045"", ""77046"", ""77047"", """&"77048"", ""77049"", ""77050"", ""77051"", ""77053"", ""77054"", ""77055"", ""77056"", ""77057"", ""77058"", ""77059"", ""77060"", ""77061"", ""77062"", ""77063"", ""77064"", ""77065"", ""77066"", ""77067"", ""77068"", ""77069"", ""77070"", ""77071"", ""77"&"072"", ""77073"", ""77074"", ""77075"", ""77076"", ""77077"", ""77078"", ""77079"", ""77080"", ""77081"", ""77082"", ""77083"", ""77084"", ""77085"", ""77086"", ""77087"", ""77088"", ""77089"", ""77090"", ""77091"", ""77092"", ""77093"", ""77094"", ""7709"&"5"", ""77096"", ""77098"", ""77099"", ""77242"", ""77257"", ""77277"", ""77279""]") -> ["77002", "77003", "77004", "77005", "77006", "77007", "77008", "77009", "77010", "77011", "77012", "77013", "77014", "77015", "77016", "77017", "77018", "77019", "77020", "77021", "77022", "77023", "77024", "77025", "77026", "77027", "77028", "77029", "77030", "77031", "77032", "77033", "77034", "77035", "77036", "77037", "77038", "77039", "77040", "77041", "77042", "77043", "77044", "77045", "77046", "77047", "77048", "77049", "77050", "77051", "77053", "77054", "77055", "77056", "77057", "77058", "77059", "77060", "77061", "77062", "77063", "77064", "77065", "77066", "77067", "77068", "77069", "77070", "77071", "77072", "77073", "77074", "77075", "77076", "77077", "77078", "77079", "77080", "77081", "77082", "77083", "77084", "77085", "77086", "77087", "77088", "77089", "77090", "77091", "77092", "77093", "77094", "77095", "77096", "77098", "77099", "77242", "77257", "77277", "77279"] | C23: =IFERROR(__xludf.DUMMYFUNCTION("""COMPUTED_VALUE"""),"Acres Homes Multi-Service Center") -> Acres Homes Multi-Service Center | D23: =IFERROR(__xludf.DUMMYFUNCTION("""COMPUTED_VALUE"""),"6719 W Montgomery Road") -> 6719 W Montgomery Road | F23: =IFERROR(__xludf.DUMMYFUNCTION("""COMPUTED_VALUE"""),"Houston") -> Houston | G23: =IFERROR(__xludf.DUMMYFUNCTION("""COMPUTED_VALUE"""),"TX") -> TX | H23: =IFERROR(__xludf.DUMMYFUNCTION("""COMPUTED_VALUE"""),"77091") -> 77091 | I23: =IFERROR(__xludf.DUMMYFUNCTION("""COMPUTED_VALUE"""),"832-393-4145") -> 832-393-4145 | J23: =IFERROR(__xludf.DUMMYFUNCTION("""COMPUTED_VALUE"""),"29.857681948841, -95.42211162195217") -> 29.857681948841, -95.42211162195217 | K23: =IFERROR(__xludf.DUMMYFUNCTION("""COMPUTED_VALUE"""),"{""special"":[{""pattern"":""2nd Tu"",""open"":""08:00"",""close"":""11:00""}]}") -> {"special":[{"pattern":"2nd Tu","open":"08:00","close":"11:00"}]} | M23: =IFERROR(__xludf.DUMMYFUNCTION("""COMPUTED_VALUE"""),13.0) -> 13 | N23: =IFERROR(__xludf.DUMMYFUNCTION("""COMPUTED_VALUE"""),"Food") -> Food | O23: =IFERROR(__xludf.DUMMYFUNCTION("""COMPUTED_VALUE"""),1.0) -> 1 | P23: =IFERROR(__xludf.DUMMYFUNCTION("""COMPUTED_VALUE"""),"ACTIVE") -> ACTIVE | Q23: =IFERROR(__xludf.DUMMYFUNCTION("""COMPUTED_VALUE"""),46057.0) -> 46057 | R23: =IFERROR(__xludf.DUMMYFUNCTION("""COMPUTED_VALUE"""),"Verified online") -> Verified online | S23: =IFERROR(__xludf.DUMMYFUNCTION("""COMPUTED_VALUE"""),"Food Distribution by the Houston Food Bank for seniors over the age of 60 and families with children under five years.") -> Food Distribution by the Houston Food Bank for seniors over the age of 60 and families with children under five years. | T23: =IFERROR(__xludf.DUMMYFUNCTION("""COMPUTED_VALUE"""),TRUE) -> TRUE | U23: =IFERROR(__xludf.DUMMYFUNCTION("""COMPUTED_VALUE"""),FALSE) -> FALSE | V23: =IFERROR(__xludf.DUMMYFUNCTION("""COMPUTED_VALUE"""),"https://www.houstonhealth.org/services/multi-service-centers/acres-homes-multi-service-center") -> https://www.houstonhealth.org/services/multi-service-centers/acres-homes-multi-service-center | W23: =IFERROR(__xludf.DUMMYFUNCTION("""COMPUTED_VALUE"""),"https://www.google.com/maps/place/Acres+Homes+Multi-Service+Center/@29.8574912,-95.4247509,17z/data=!3m1!4b1!4m6!3m5!1s0x8640c7d963488d53:0x6044d3466dc08305!8m2!3d29.8574866!4d-95.422176!16s%2Fg%2F11g7z0pwk3?entry=ttu&g_ep=EgoyMDI2MDIwMS4wIKXMDSoKLDEwMDc5"&"MjA2OUgBUAM%3D") -> https://www.google.com/maps/place/Acres+Homes+Multi-Service+Center/@29.8574912,-95.4247509,17z/data=!3m1!4b1!4m6!3m5!1s0x8640c7d963488d53:0x6044d3466dc08305!8m2!3d29.8574866!4d-95.422176!16s%2Fg%2F11g7z0pwk3?entry=ttu&g_ep=EgoyMDI2MDIwMS4wIKXMDSoKLDEwMDc5MjA2OUgBUAM%3D | Y23: =IFERROR(__xludf.DUMMYFUNCTION("""COMPUTED_VALUE"""),"Houston") -> Houston | Z23: =IFERROR(__xludf.DUMMYFUNCTION("""COMPUTED_VALUE"""),"Acres Home, Garden Oaks North, Northside / Northline") -> Acres Home, Garden Oaks North, Northside / Northline | AA23: =IFERROR(__xludf.DUMMYFUNCTION("""COMPUTED_VALUE"""),"City of Houston") -> City of Houston | AB23: =IFERROR(__xludf.DUMMYFUNCTION("""COMPUTED_VALUE"""),"Northside / Northline") -> Northside / Northline
A24: 23 | B24: =IFERROR(__xludf.DUMMYFUNCTION("""COMPUTED_VALUE"""),"[""77002"", ""77003"", ""77004"", ""77005"", ""77006"", ""77007"", ""77008"", ""77009"", ""77010"", ""77011"", ""77012"", ""77013"", ""77014"", ""77015"", ""77016"", ""77017"", ""77018"", ""77019"", ""77020"", ""77021"", ""77022"", ""77023"", ""77024"", "&"""77025"", ""77026"", ""77027"", ""77028"", ""77029"", ""77030"", ""77031"", ""77032"", ""77033"", ""77034"", ""77035"", ""77036"", ""77037"", ""77038"", ""77039"", ""77040"", ""77041"", ""77042"", ""77043"", ""77044"", ""77045"", ""77046"", ""77047"", """&"77048"", ""77049"", ""77050"", ""77051"", ""77053"", ""77054"", ""77055"", ""77056"", ""77057"", ""77058"", ""77059"", ""77060"", ""77061"", ""77062"", ""77063"", ""77064"", ""77065"", ""77066"", ""77067"", ""77068"", ""77069"", ""77070"", ""77071"", ""77"&"072"", ""77073"", ""77074"", ""77075"", ""77076"", ""77077"", ""77078"", ""77079"", ""77080"", ""77081"", ""77082"", ""77083"", ""77084"", ""77085"", ""77086"", ""77087"", ""77088"", ""77089"", ""77090"", ""77091"", ""77092"", ""77093"", ""77094"", ""7709"&"5"", ""77096"", ""77098"", ""77099"", ""77242"", ""77257"", ""77277"", ""77279""]") -> ["77002", "77003", "77004", "77005", "77006", "77007", "77008", "77009", "77010", "77011", "77012", "77013", "77014", "77015", "77016", "77017", "77018", "77019", "77020", "77021", "77022", "77023", "77024", "77025", "77026", "77027", "77028", "77029", "77030", "77031", "77032", "77033", "77034", "77035", "77036", "77037", "77038", "77039", "77040", "77041", "77042", "77043", "77044", "77045", "77046", "77047", "77048", "77049", "77050", "77051", "77053", "77054", "77055", "77056", "77057", "77058", "77059", "77060", "77061", "77062", "77063", "77064", "77065", "77066", "77067", "77068", "77069", "77070", "77071", "77072", "77073", "77074", "77075", "77076", "77077", "77078", "77079", "77080", "77081", "77082", "77083", "77084", "77085", "77086", "77087", "77088", "77089", "77090", "77091", "77092", "77093", "77094", "77095", "77096", "77098", "77099", "77242", "77257", "77277", "77279"] | C24: =IFERROR(__xludf.DUMMYFUNCTION("""COMPUTED_VALUE"""),"Acres Homes Multi-Service Center") -> Acres Homes Multi-Service Center | D24: =IFERROR(__xludf.DUMMYFUNCTION("""COMPUTED_VALUE"""),"6719 W Montgomery Road") -> 6719 W Montgomery Road | F24: =IFERROR(__xludf.DUMMYFUNCTION("""COMPUTED_VALUE"""),"Houston") -> Houston | G24: =IFERROR(__xludf.DUMMYFUNCTION("""COMPUTED_VALUE"""),"TX") -> TX | H24: =IFERROR(__xludf.DUMMYFUNCTION("""COMPUTED_VALUE"""),"77091") -> 77091 | I24: =IFERROR(__xludf.DUMMYFUNCTION("""COMPUTED_VALUE"""),"832-393-4150") -> 832-393-4150 | J24: =IFERROR(__xludf.DUMMYFUNCTION("""COMPUTED_VALUE"""),"29.857681948841, -95.42211162195217") -> 29.857681948841, -95.42211162195217 | K24: =IFERROR(__xludf.DUMMYFUNCTION("""COMPUTED_VALUE"""),"{""regular"":[{""days"":[""Mo"",""Tu"",""We"",""Th""],""open"":""08:00"",""close"":""17:00""}]}") -> {"regular":[{"days":["Mo","Tu","We","Th"],"open":"08:00","close":"17:00"}]} | M24: =IFERROR(__xludf.DUMMYFUNCTION("""COMPUTED_VALUE"""),44.0) -> 44 | N24: =IFERROR(__xludf.DUMMYFUNCTION("""COMPUTED_VALUE"""),"Mother & Child") -> Mother & Child | O24: =IFERROR(__xludf.DUMMYFUNCTION("""COMPUTED_VALUE"""),1.0) -> 1 | P24: =IFERROR(__xludf.DUMMYFUNCTION("""COMPUTED_VALUE"""),"ACTIVE") -> ACTIVE | Q24: =IFERROR(__xludf.DUMMYFUNCTION("""COMPUTED_VALUE"""),46057.0) -> 46057 | R24: =IFERROR(__xludf.DUMMYFUNCTION("""COMPUTED_VALUE"""),"Verified online") -> Verified online | S24: =IFERROR(__xludf.DUMMYFUNCTION("""COMPUTED_VALUE"""),"Women, Infants and Children (WIC) Supplemental nutrition program providing health care referrals, nutrition education and nutritious foods to pregnant, breastfeeding and postpartum women and children under five who have nutrition health-related problems.") -> Women, Infants and Children (WIC) Supplemental nutrition program providing health care referrals, nutrition education and nutritious foods to pregnant, breastfeeding and postpartum women and children under five who have nutrition health-related problems. | T24: =IFERROR(__xludf.DUMMYFUNCTION("""COMPUTED_VALUE"""),TRUE) -> TRUE | U24: =IFERROR(__xludf.DUMMYFUNCTION("""COMPUTED_VALUE"""),FALSE) -> FALSE | V24: =IFERROR(__xludf.DUMMYFUNCTION("""COMPUTED_VALUE"""),"https://www.houstonhealth.org/services/multi-service-centers/acres-homes-multi-service-center") -> https://www.houstonhealth.org/services/multi-service-centers/acres-homes-multi-service-center | W24: =IFERROR(__xludf.DUMMYFUNCTION("""COMPUTED_VALUE"""),"https://www.google.com/maps/place/Acres+Homes+Multi-Service+Center/@29.8574912,-95.4247509,17z/data=!3m1!4b1!4m6!3m5!1s0x8640c7d963488d53:0x6044d3466dc08305!8m2!3d29.8574866!4d-95.422176!16s%2Fg%2F11g7z0pwk3?entry=ttu&g_ep=EgoyMDI2MDIwMS4wIKXMDSoKLDEwMDc5"&"MjA2OUgBUAM%3D") -> https://www.google.com/maps/place/Acres+Homes+Multi-Service+Center/@29.8574912,-95.4247509,17z/data=!3m1!4b1!4m6!3m5!1s0x8640c7d963488d53:0x6044d3466dc08305!8m2!3d29.8574866!4d-95.422176!16s%2Fg%2F11g7z0pwk3?entry=ttu&g_ep=EgoyMDI2MDIwMS4wIKXMDSoKLDEwMDc5MjA2OUgBUAM%3D | Y24: =IFERROR(__xludf.DUMMYFUNCTION("""COMPUTED_VALUE"""),"Houston") -> Houston | Z24: =IFERROR(__xludf.DUMMYFUNCTION("""COMPUTED_VALUE"""),"Acres Home, Garden Oaks North, Northside / Northline") -> Acres Home, Garden Oaks North, Northside / Northline | AA24: =IFERROR(__xludf.DUMMYFUNCTION("""COMPUTED_VALUE"""),"City of Houston") -> City of Houston | AB24: =IFERROR(__xludf.DUMMYFUNCTION("""COMPUTED_VALUE"""),"Northside / Northline") -> Northside / Northline
A25: 24 | B25: =IFERROR(__xludf.DUMMYFUNCTION("""COMPUTED_VALUE"""),"[""77002"", ""77003"", ""77004"", ""77005"", ""77006"", ""77007"", ""77008"", ""77009"", ""77010"", ""77011"", ""77012"", ""77013"", ""77014"", ""77015"", ""77016"", ""77017"", ""77018"", ""77019"", ""77020"", ""77021"", ""77022"", ""77023"", ""77024"", "&"""77025"", ""77026"", ""77027"", ""77028"", ""77029"", ""77030"", ""77031"", ""77032"", ""77033"", ""77034"", ""77035"", ""77036"", ""77037"", ""77038"", ""77039"", ""77040"", ""77041"", ""77042"", ""77043"", ""77044"", ""77045"", ""77046"", ""77047"", """&"77048"", ""77049"", ""77050"", ""77051"", ""77053"", ""77054"", ""77055"", ""77056"", ""77057"", ""77058"", ""77059"", ""77060"", ""77061"", ""77062"", ""77063"", ""77064"", ""77065"", ""77066"", ""77067"", ""77068"", ""77069"", ""77070"", ""77071"", ""77"&"072"", ""77073"", ""77074"", ""77075"", ""77076"", ""77077"", ""77078"", ""77079"", ""77080"", ""77081"", ""77082"", ""77083"", ""77084"", ""77085"", ""77086"", ""77087"", ""77088"", ""77089"", ""77090"", ""77091"", ""77092"", ""77093"", ""77094"", ""7709"&"5"", ""77096"", ""77098"", ""77099"", ""77242"", ""77257"", ""77277"", ""77279""]") -> ["77002", "77003", "77004", "77005", "77006", "77007", "77008", "77009", "77010", "77011", "77012", "77013", "77014", "77015", "77016", "77017", "77018", "77019", "77020", "77021", "77022", "77023", "77024", "77025", "77026", "77027", "77028", "77029", "77030", "77031", "77032", "77033", "77034", "77035", "77036", "77037", "77038", "77039", "77040", "77041", "77042", "77043", "77044", "77045", "77046", "77047", "77048", "77049", "77050", "77051", "77053", "77054", "77055", "77056", "77057", "77058", "77059", "77060", "77061", "77062", "77063", "77064", "77065", "77066", "77067", "77068", "77069", "77070", "77071", "77072", "77073", "77074", "77075", "77076", "77077", "77078", "77079", "77080", "77081", "77082", "77083", "77084", "77085", "77086", "77087", "77088", "77089", "77090", "77091", "77092", "77093", "77094", "77095", "77096", "77098", "77099", "77242", "77257", "77277", "77279"] | C25: =IFERROR(__xludf.DUMMYFUNCTION("""COMPUTED_VALUE"""),"Acres Homes Multi-Service Center") -> Acres Homes Multi-Service Center | D25: =IFERROR(__xludf.DUMMYFUNCTION("""COMPUTED_VALUE"""),"6719 W Montgomery Road") -> 6719 W Montgomery Road | F25: =IFERROR(__xludf.DUMMYFUNCTION("""COMPUTED_VALUE"""),"Houston") -> Houston | G25: =IFERROR(__xludf.DUMMYFUNCTION("""COMPUTED_VALUE"""),"TX") -> TX | H25: =IFERROR(__xludf.DUMMYFUNCTION("""COMPUTED_VALUE"""),"77091") -> 77091 | I25: =IFERROR(__xludf.DUMMYFUNCTION("""COMPUTED_VALUE"""),"713-694-1619") -> 713-694-1619 | J25: =IFERROR(__xludf.DUMMYFUNCTION("""COMPUTED_VALUE"""),"29.857681948841, -95.42211162195217") -> 29.857681948841, -95.42211162195217 | K25: =IFERROR(__xludf.DUMMYFUNCTION("""COMPUTED_VALUE"""),"{""regular"":[{""days"":[""Mo"",""Tu"",""We"",""Th""],""open"":""08:00"",""close"":""17:00""}]}") -> {"regular":[{"days":["Mo","Tu","We","Th"],"open":"08:00","close":"17:00"}]} | M25: =IFERROR(__xludf.DUMMYFUNCTION("""COMPUTED_VALUE"""),44.0) -> 44 | N25: =IFERROR(__xludf.DUMMYFUNCTION("""COMPUTED_VALUE"""),"Mother & Child") -> Mother & Child | O25: =IFERROR(__xludf.DUMMYFUNCTION("""COMPUTED_VALUE"""),1.0) -> 1 | P25: =IFERROR(__xludf.DUMMYFUNCTION("""COMPUTED_VALUE"""),"ACTIVE") -> ACTIVE | Q25: =IFERROR(__xludf.DUMMYFUNCTION("""COMPUTED_VALUE"""),46057.0) -> 46057 | R25: =IFERROR(__xludf.DUMMYFUNCTION("""COMPUTED_VALUE"""),"Verified online") -> Verified online | S25: =IFERROR(__xludf.DUMMYFUNCTION("""COMPUTED_VALUE"""),"Head Start For children upto 5 years old") -> Head Start For children upto 5 years old | T25: =IFERROR(__xludf.DUMMYFUNCTION("""COMPUTED_VALUE"""),TRUE) -> TRUE | U25: =IFERROR(__xludf.DUMMYFUNCTION("""COMPUTED_VALUE"""),FALSE) -> FALSE | V25: =IFERROR(__xludf.DUMMYFUNCTION("""COMPUTED_VALUE"""),"https://www.houstonhealth.org/services/multi-service-centers/acres-homes-multi-service-center") -> https://www.houstonhealth.org/services/multi-service-centers/acres-homes-multi-service-center | W25: =IFERROR(__xludf.DUMMYFUNCTION("""COMPUTED_VALUE"""),"https://www.google.com/maps/place/Acres+Homes+Multi-Service+Center/@29.8574912,-95.4247509,17z/data=!3m1!4b1!4m6!3m5!1s0x8640c7d963488d53:0x6044d3466dc08305!8m2!3d29.8574866!4d-95.422176!16s%2Fg%2F11g7z0pwk3?entry=ttu&g_ep=EgoyMDI2MDIwMS4wIKXMDSoKLDEwMDc5"&"MjA2OUgBUAM%3D") -> https://www.google.com/maps/place/Acres+Homes+Multi-Service+Center/@29.8574912,-95.4247509,17z/data=!3m1!4b1!4m6!3m5!1s0x8640c7d963488d53:0x6044d3466dc08305!8m2!3d29.8574866!4d-95.422176!16s%2Fg%2F11g7z0pwk3?entry=ttu&g_ep=EgoyMDI2MDIwMS4wIKXMDSoKLDEwMDc5MjA2OUgBUAM%3D | Y25: =IFERROR(__xludf.DUMMYFUNCTION("""COMPUTED_VALUE"""),"Harris") -> Harris | Z25: =IFERROR(__xludf.DUMMYFUNCTION("""COMPUTED_VALUE"""),"Acres Home, Garden Oaks North, Northside / Northline") -> Acres Home, Garden Oaks North, Northside / Northline | AA25: =IFERROR(__xludf.DUMMYFUNCTION("""COMPUTED_VALUE"""),"City of Houston") -> City of Houston | AB25: =IFERROR(__xludf.DUMMYFUNCTION("""COMPUTED_VALUE"""),"Northside / Northline") -> Northside / Northline
A26: 25 | B26: =IFERROR(__xludf.DUMMYFUNCTION("""COMPUTED_VALUE"""),"[""99999""]") -> ["99999"] | C26: =IFERROR(__xludf.DUMMYFUNCTION("""COMPUTED_VALUE"""),"Adult & Teen Challenge") -> Adult & Teen Challenge | D26: =IFERROR(__xludf.DUMMYFUNCTION("""COMPUTED_VALUE"""),"30310 Misty Meadow Drive") -> 30310 Misty Meadow Drive | F26: =IFERROR(__xludf.DUMMYFUNCTION("""COMPUTED_VALUE"""),"Magnolia") -> Magnolia | G26: =IFERROR(__xludf.DUMMYFUNCTION("""COMPUTED_VALUE"""),"TX") -> TX | H26: =IFERROR(__xludf.DUMMYFUNCTION("""COMPUTED_VALUE"""),"77355") -> 77355 | I26: =IFERROR(__xludf.DUMMYFUNCTION("""COMPUTED_VALUE"""),"281-259-5600") -> 281-259-5600 | J26: =IFERROR(__xludf.DUMMYFUNCTION("""COMPUTED_VALUE"""),"30.1844886166487, -95.7100498405959") -> 30.1844886166487, -95.7100498405959 | K26: =IFERROR(__xludf.DUMMYFUNCTION("""COMPUTED_VALUE"""),"{""regular"":[{""days"":[""Mo"",""Tu"",""We"",""Th"",""Fr"",""Sa""],""open"":null,""close"":null}]}") -> {"regular":[{"days":["Mo","Tu","We","Th","Fr","Sa"],"open":null,"close":null}]} | M26: =IFERROR(__xludf.DUMMYFUNCTION("""COMPUTED_VALUE"""),34.0) -> 34 | N26: =IFERROR(__xludf.DUMMYFUNCTION("""COMPUTED_VALUE"""),"Medical - Addiction Recovery") -> Medical - Addiction Recovery | O26: =IFERROR(__xludf.DUMMYFUNCTION("""COMPUTED_VALUE"""),1.0) -> 1 | P26: =IFERROR(__xludf.DUMMYFUNCTION("""COMPUTED_VALUE"""),"ACTIVE") -> ACTIVE | Q26: =IFERROR(__xludf.DUMMYFUNCTION("""COMPUTED_VALUE"""),45765.0) -> 45765 | S26: =IFERROR(__xludf.DUMMYFUNCTION("""COMPUTED_VALUE"""),"Residential recovery program for adults and teens. Committed to working for a full year. Not free, limited cost.") -> Residential recovery program for adults and teens. Committed to working for a full year. Not free, limited cost. | T26: =IFERROR(__xludf.DUMMYFUNCTION("""COMPUTED_VALUE"""),FALSE) -> FALSE | U26: =IFERROR(__xludf.DUMMYFUNCTION("""COMPUTED_VALUE"""),FALSE) -> FALSE | V26: =IFERROR(__xludf.DUMMYFUNCTION("""COMPUTED_VALUE"""),"https://houstonmensrehab.com/") -> https://houstonmensrehab.com/ | W26: =IFERROR(__xludf.DUMMYFUNCTION("""COMPUTED_VALUE"""),"https://www.google.com/maps/place/Adult+%26+Teen+Challenge+Houston+Men's/@30.1843018,-95.7124219,17z/data=!3m1!4b1!4m6!3m5!1s0x86472837f10aa7eb:0x7533c718c1171d3b!8m2!3d30.1842972!4d-95.7098416!16s%2Fg%2F1tczf8yf?entry=ttu&g_ep=EgoyMDI1MDQxNi4xIKXMDSoASAF"&"QAw%3D%3D") -> https://www.google.com/maps/place/Adult+%26+Teen+Challenge+Houston+Men's/@30.1843018,-95.7124219,17z/data=!3m1!4b1!4m6!3m5!1s0x86472837f10aa7eb:0x7533c718c1171d3b!8m2!3d30.1842972!4d-95.7098416!16s%2Fg%2F1tczf8yf?entry=ttu&g_ep=EgoyMDI1MDQxNi4xIKXMDSoASAFQAw%3D%3D | Y26: =IFERROR(__xludf.DUMMYFUNCTION("""COMPUTED_VALUE"""),"Magnolia") -> Magnolia | Z26: =IFERROR(__xludf.DUMMYFUNCTION("""COMPUTED_VALUE"""),"Magnolia") -> Magnolia | AA26: =IFERROR(__xludf.DUMMYFUNCTION("""COMPUTED_VALUE"""),"Adult & Teen Challenge") -> Adult & Teen Challenge | AB26: =IFERROR(__xludf.DUMMYFUNCTION("""COMPUTED_VALUE"""),"Magnolia") -> Magnolia
A27: 26 | B27: =IFERROR(__xludf.DUMMYFUNCTION("""COMPUTED_VALUE"""),"[""77002"", ""77003"", ""77004"", ""77005"", ""77006"", ""77007"", ""77008"", ""77009"", ""77010"", ""77011"", ""77012"", ""77013"", ""77014"", ""77015"", ""77016"", ""77017"", ""77018"", ""77019"", ""77020"", ""77021"", ""77022"", ""77023"", ""77024"", "&"""77025"", ""77026"", ""77027"", ""77028"", ""77029"", ""77030"", ""77031"", ""77032"", ""77033"", ""77034"", ""77035"", ""77036"", ""77037"", ""77038"", ""77039"", ""77040"", ""77041"", ""77042"", ""77043"", ""77044"", ""77045"", ""77046"", ""77047"", """&"77048"", ""77049"", ""77050"", ""77051"", ""77054"", ""77055"", ""77056"", ""77057"", ""77058"", ""77059"", ""77060"", ""77061"", ""77062"", ""77063"", ""77064"", ""77065"", ""77066"", ""77067"", ""77068"", ""77069"", ""77070"", ""77071"", ""77072"", ""77"&"073"", ""77074"", ""77075"", ""77076"", ""77077"", ""77078"", ""77079"", ""77080"", ""77081"", ""77082"", ""77083"", ""77084"", ""77085"", ""77086"", ""77087"", ""77088"", ""77089"", ""77090"", ""77091"", ""77092"", ""77093"", ""77094"", ""77095"", ""7709"&"6"", ""77098"", ""77099"", ""77210"", ""77231"", ""77242"", ""77257"", ""77277"", ""77279"", ""77336"", ""77338"", ""77339"", ""77345"", ""77346"", ""77347"", ""77357"", ""77365"", ""77373"", ""77375"", ""77377"", ""77379"", ""77383"", ""77387"", ""77388"&""", ""77389"", ""77393"", ""77396"", ""77401"", ""77410"", ""77429"", ""77433"", ""77447"", ""77449"", ""77450"", ""77493"", ""77501"", ""77502"", ""77503"", ""77504"", ""77505"", ""77506"", ""77507"", ""77508"", ""77520"", ""77521"", ""77530"", ""77532"""&", ""77535"", ""77536"", ""77546"", ""77547"", ""77562"", ""77571"", ""77581"", ""77586"", ""77587"", ""77598""]") -> ["77002", "77003", "77004", "77005", "77006", "77007", "77008", "77009", "77010", "77011", "77012", "77013", "77014", "77015", "77016", "77017", "77018", "77019", "77020", "77021", "77022", "77023", "77024", "77025", "77026", "77027", "77028", "77029", "77030", "77031", "77032", "77033", "77034", "77035", "77036", "77037", "77038", "77039", "77040", "77041", "77042", "77043", "77044", "77045", "77046", "77047", "77048", "77049", "77050", "77051", "77054", "77055", "77056", "77057", "77058", "77059", "77060", "77061", "77062", "77063", "77064", "77065", "77066", "77067", "77068", "77069", "77070", "77071", "77072", "77073", "77074", "77075", "77076", "77077", "77078", "77079", "77080", "77081", "77082", "77083", "77084", "77085", "77086", "77087", "77088", "77089", "77090", "77091", "77092", "77093", "77094", "77095", "77096", "77098", "77099", "77210", "77231", "77242", "77257", "77277", "77279", "77336", "77338", "77339", "77345", "77346", "77347", "77357", "77365", "77373", "77375", "77377", "77379", "77383", "77387", "77388", "77389", "77393", "77396", "77401", "77410", "77429", "77433", "77447", "77449", "77450", "77493", "77501", "77502", "77503", "77504", "77505", "77506", "77507", "77508", "77520", "77521", "77530", "77532", "77535", "77536", "77546", "77547", "77562", "77571", "77581", "77586", "77587", "77598"] | C27: =IFERROR(__xludf.DUMMYFUNCTION("""COMPUTED_VALUE"""),"Aid to Victims of Domestic Abuse (AVDA)") -> Aid to Victims of Domestic Abuse (AVDA) | D27: =IFERROR(__xludf.DUMMYFUNCTION("""COMPUTED_VALUE"""),"1001 Texas Avenue") -> 1001 Texas Avenue | E27: =IFERROR(__xludf.DUMMYFUNCTION("""COMPUTED_VALUE"""),"Suite 600") -> Suite 600 | F27: =IFERROR(__xludf.DUMMYFUNCTION("""COMPUTED_VALUE"""),"Houston") -> Houston | G27: =IFERROR(__xludf.DUMMYFUNCTION("""COMPUTED_VALUE"""),"TX") -> TX | H27: =IFERROR(__xludf.DUMMYFUNCTION("""COMPUTED_VALUE"""),"77002") -> 77002 | I27: =IFERROR(__xludf.DUMMYFUNCTION("""COMPUTED_VALUE"""),"713-224-9911") -> 713-224-9911 | J27: =IFERROR(__xludf.DUMMYFUNCTION("""COMPUTED_VALUE"""),"29.75987665, -95.3617820466487") -> 29.75987665, -95.3617820466487 | K27: =IFERROR(__xludf.DUMMYFUNCTION("""COMPUTED_VALUE"""),"{""regular"":[{""days"":[""Mo"",""Tu"",""We"",""Th"",""Fr""],""open"":""08:00"",""close"":""17:00""}]}") -> {"regular":[{"days":["Mo","Tu","We","Th","Fr"],"open":"08:00","close":"17:00"}]} | M27: =IFERROR(__xludf.DUMMYFUNCTION("""COMPUTED_VALUE"""),42.0) -> 42 | N27: =IFERROR(__xludf.DUMMYFUNCTION("""COMPUTED_VALUE"""),"Domestic Abuse - Other") -> Domestic Abuse - Other | O27: =IFERROR(__xludf.DUMMYFUNCTION("""COMPUTED_VALUE"""),1.0) -> 1 | P27: =IFERROR(__xludf.DUMMYFUNCTION("""COMPUTED_VALUE"""),"ACTIVE") -> ACTIVE | Q27: =IFERROR(__xludf.DUMMYFUNCTION("""COMPUTED_VALUE"""),46040.0) -> 46040 | R27: =IFERROR(__xludf.DUMMYFUNCTION("""COMPUTED_VALUE"""),"Verified online") -> Verified online | S27: =IFERROR(__xludf.DUMMYFUNCTION("""COMPUTED_VALUE"""),"Fee based Battering Intervention and Prevention Program (BIPP) provides tools to end physical, verbal or emotional abuse. These are weekly sessions available in both English and Spanish. Free counseling services for adult survivors and children (3 years"&" and older) of abusive relationships. Available in English and Spanish") -> Fee based Battering Intervention and Prevention Program (BIPP) provides tools to end physical, verbal or emotional abuse. These are weekly sessions available in both English and Spanish. Free counseling services for adult survivors and children (3 years and older) of abusive relationships. Available in English and Spanish | T27: =IFERROR(__xludf.DUMMYFUNCTION("""COMPUTED_VALUE"""),FALSE) -> FALSE | U27: =IFERROR(__xludf.DUMMYFUNCTION("""COMPUTED_VALUE"""),FALSE) -> FALSE | V27: =IFERROR(__xludf.DUMMYFUNCTION("""COMPUTED_VALUE"""),"https://avda.org/") -> https://avda.org/ | W27: =IFERROR(__xludf.DUMMYFUNCTION("""COMPUTED_VALUE"""),"https://www.google.com/maps/place/AVDA+(Aid+to+Victims+of+Domestic+Abuse)/@29.7600419,-95.3669883,17z/data=!3m2!4b1!5s0x8640c6aa65c8eea5:0x1dd626e1f5b80a6!4m6!3m5!1s0x8640bf13bd360545:0x6f740c2de58717e4!8m2!3d29.760042!4d-95.362112!16s%2Fg%2F1tdww1xs?entr"&"y=ttu&g_ep=EgoyMDI2MDExMy4wIKXMDSoKLDEwMDc5MjA2OUgBUAM%3D") -> https://www.google.com/maps/place/AVDA+(Aid+to+Victims+of+Domestic+Abuse)/@29.7600419,-95.3669883,17z/data=!3m2!4b1!5s0x8640c6aa65c8eea5:0x1dd626e1f5b80a6!4m6!3m5!1s0x8640bf13bd360545:0x6f740c2de58717e4!8m2!3d29.760042!4d-95.362112!16s%2Fg%2F1tdww1xs?entry=ttu&g_ep=EgoyMDI2MDExMy4wIKXMDSoKLDEwMDc5MjA2OUgBUAM%3D | Y27: =IFERROR(__xludf.DUMMYFUNCTION("""COMPUTED_VALUE"""),"Houston") -> Houston | Z27: =IFERROR(__xludf.DUMMYFUNCTION("""COMPUTED_VALUE"""),"Central Business District, Downtown Houston, East Downtown, South Central Houston, Theater District, University Place, Warehouse District") -> Central Business District, Downtown Houston, East Downtown, South Central Houston, Theater District, University Place, Warehouse District | AA27: =IFERROR(__xludf.DUMMYFUNCTION("""COMPUTED_VALUE"""),"Aid to Victims of Domestic Abuse (AVDA)") -> Aid to Victims of Domestic Abuse (AVDA) | AB27: =IFERROR(__xludf.DUMMYFUNCTION("""COMPUTED_VALUE"""),"Downtown Houston") -> Downtown Houston
A28: 27 | B28: =IFERROR(__xludf.DUMMYFUNCTION("""COMPUTED_VALUE"""),"[""77053"", ""77406"", ""77407"", ""77417"", ""77430"", ""77441"", ""77444"", ""77451"", ""77459"", ""77461"", ""77464"", ""77469"", ""77471"", ""77476"", ""77477"", ""77478"", ""77479"", ""77481"", ""77485"", ""77487"", ""77489"", ""77494"", ""77496"", "&"""77498"", ""77545"", ""77583"", ""77584""]") -> ["77053", "77406", "77407", "77417", "77430", "77441", "77444", "77451", "77459", "77461", "77464", "77469", "77471", "77476", "77477", "77478", "77479", "77481", "77485", "77487", "77489", "77494", "77496", "77498", "77545", "77583", "77584"] | C28: =IFERROR(__xludf.DUMMYFUNCTION("""COMPUTED_VALUE"""),"Aid to Victims of Domestic Abuse (AVDA)") -> Aid to Victims of Domestic Abuse (AVDA) | D28: =IFERROR(__xludf.DUMMYFUNCTION("""COMPUTED_VALUE"""),"12300 Parc Crest Drive") -> 12300 Parc Crest Drive | E28: =IFERROR(__xludf.DUMMYFUNCTION("""COMPUTED_VALUE"""),"Suite 140") -> Suite 140 | F28: =IFERROR(__xludf.DUMMYFUNCTION("""COMPUTED_VALUE"""),"Stafford") -> Stafford | G28: =IFERROR(__xludf.DUMMYFUNCTION("""COMPUTED_VALUE"""),"TX") -> TX | H28: =IFERROR(__xludf.DUMMYFUNCTION("""COMPUTED_VALUE"""),"77477") -> 77477 | I28: =IFERROR(__xludf.DUMMYFUNCTION("""COMPUTED_VALUE"""),"281-207-2312") -> 281-207-2312 | J28: =IFERROR(__xludf.DUMMYFUNCTION("""COMPUTED_VALUE"""),"29.64299514221335, -95.5686900498753") -> 29.64299514221335, -95.5686900498753 | K28: =IFERROR(__xludf.DUMMYFUNCTION("""COMPUTED_VALUE"""),"{""regular"":[{""days"":[""Mo"",""Tu"",""We"",""Th"",""Fr""],""open"":""08:00"",""close"":""17:00""}]}") -> {"regular":[{"days":["Mo","Tu","We","Th","Fr"],"open":"08:00","close":"17:00"}]} | M28: =IFERROR(__xludf.DUMMYFUNCTION("""COMPUTED_VALUE"""),42.0) -> 42 | N28: =IFERROR(__xludf.DUMMYFUNCTION("""COMPUTED_VALUE"""),"Domestic Abuse - Other") -> Domestic Abuse - Other | O28: =IFERROR(__xludf.DUMMYFUNCTION("""COMPUTED_VALUE"""),1.0) -> 1 | P28: =IFERROR(__xludf.DUMMYFUNCTION("""COMPUTED_VALUE"""),"ACTIVE") -> ACTIVE | Q28: =IFERROR(__xludf.DUMMYFUNCTION("""COMPUTED_VALUE"""),46040.0) -> 46040 | R28: =IFERROR(__xludf.DUMMYFUNCTION("""COMPUTED_VALUE"""),"Verified online") -> Verified online | S28: =IFERROR(__xludf.DUMMYFUNCTION("""COMPUTED_VALUE"""),"Fee based Battering Intervention and Prevention Program (BIPP) provides tools to end physical, verbal or emotional abuse. These are weekly sessions available in both English and Spanish. Free counseling services for adult survivors and children (3 years"&" and older) of abusive relationships. Available in English and Spanish") -> Fee based Battering Intervention and Prevention Program (BIPP) provides tools to end physical, verbal or emotional abuse. These are weekly sessions available in both English and Spanish. Free counseling services for adult survivors and children (3 years and older) of abusive relationships. Available in English and Spanish | T28: =IFERROR(__xludf.DUMMYFUNCTION("""COMPUTED_VALUE"""),FALSE) -> FALSE | U28: =IFERROR(__xludf.DUMMYFUNCTION("""COMPUTED_VALUE"""),FALSE) -> FALSE | V28: =IFERROR(__xludf.DUMMYFUNCTION("""COMPUTED_VALUE"""),"https://avda.org/") -> https://avda.org/ | W28: =IFERROR(__xludf.DUMMYFUNCTION("""COMPUTED_VALUE"""),"https://www.google.com/maps/place/12300+Parc+Crest+Dr,+Stafford,+TX+77477/@29.6427714,-95.571324,17z/data=!3m1!4b1!4m6!3m5!1s0x8640e7db8e5876c1:0xe77e74e1dbfaf7a8!8m2!3d29.6427714!4d-95.5687437!16s%2Fg%2F11bw4ptrpn?entry=ttu&g_ep=EgoyMDI2MDExMy4wIKXMDSoKL"&"DEwMDc5MjA2OUgBUAM%3D") -> https://www.google.com/maps/place/12300+Parc+Crest+Dr,+Stafford,+TX+77477/@29.6427714,-95.571324,17z/data=!3m1!4b1!4m6!3m5!1s0x8640e7db8e5876c1:0xe77e74e1dbfaf7a8!8m2!3d29.6427714!4d-95.5687437!16s%2Fg%2F11bw4ptrpn?entry=ttu&g_ep=EgoyMDI2MDExMy4wIKXMDSoKLDEwMDc5MjA2OUgBUAM%3D | Y28: =IFERROR(__xludf.DUMMYFUNCTION("""COMPUTED_VALUE"""),"Stafford") -> Stafford | Z28: =IFERROR(__xludf.DUMMYFUNCTION("""COMPUTED_VALUE"""),"Clark Plaza One, Corporate Bus Park, Greenbriar Southwest, Stafford, The Fountains") -> Clark Plaza One, Corporate Bus Park, Greenbriar Southwest, Stafford, The Fountains | AA28: =IFERROR(__xludf.DUMMYFUNCTION("""COMPUTED_VALUE"""),"Aid to Victims of Domestic Abuse (AVDA)") -> Aid to Victims of Domestic Abuse (AVDA) | AB28: =IFERROR(__xludf.DUMMYFUNCTION("""COMPUTED_VALUE"""),"Stafford") -> Stafford
A29: 28 | B29: =IFERROR(__xludf.DUMMYFUNCTION("""COMPUTED_VALUE"""),"[""77363"", ""77418"", ""77423"", ""77426"", ""77445"", ""77446"", ""77452"", ""77466"", ""77474"", ""77484"", ""77492"", ""77833"", ""77835"", ""77868"", ""77880"", ""78932"", ""78946""]") -> ["77363", "77418", "77423", "77426", "77445", "77446", "77452", "77466", "77474", "77484", "77492", "77833", "77835", "77868", "77880", "78932", "78946"] | C29: =IFERROR(__xludf.DUMMYFUNCTION("""COMPUTED_VALUE"""),"Aid to Victims of Domestic Abuse (AVDA)") -> Aid to Victims of Domestic Abuse (AVDA) | D29: =IFERROR(__xludf.DUMMYFUNCTION("""COMPUTED_VALUE"""),"910 Ninth Street") -> 910 Ninth Street | F29: =IFERROR(__xludf.DUMMYFUNCTION("""COMPUTED_VALUE"""),"Hempstead") -> Hempstead | G29: =IFERROR(__xludf.DUMMYFUNCTION("""COMPUTED_VALUE"""),"TX") -> TX | H29: =IFERROR(__xludf.DUMMYFUNCTION("""COMPUTED_VALUE"""),"77445") -> 77445 | I29: =IFERROR(__xludf.DUMMYFUNCTION("""COMPUTED_VALUE"""),"979-826-3290") -> 979-826-3290 | J29: =IFERROR(__xludf.DUMMYFUNCTION("""COMPUTED_VALUE"""),"30.09638046314288, -96.0769752947155") -> 30.09638046314288, -96.0769752947155 | K29: =IFERROR(__xludf.DUMMYFUNCTION("""COMPUTED_VALUE"""),"{""regular"":[{""days"":[""Mo"",""Tu"",""We"",""Th"",""Fr""],""open"":""08:00"",""close"":""17:00""}]}") -> {"regular":[{"days":["Mo","Tu","We","Th","Fr"],"open":"08:00","close":"17:00"}]} | M29: =IFERROR(__xludf.DUMMYFUNCTION("""COMPUTED_VALUE"""),42.0) -> 42 | N29: =IFERROR(__xludf.DUMMYFUNCTION("""COMPUTED_VALUE"""),"Domestic Abuse - Other") -> Domestic Abuse - Other | O29: =IFERROR(__xludf.DUMMYFUNCTION("""COMPUTED_VALUE"""),1.0) -> 1 | P29: =IFERROR(__xludf.DUMMYFUNCTION("""COMPUTED_VALUE"""),"ACTIVE") -> ACTIVE | Q29: =IFERROR(__xludf.DUMMYFUNCTION("""COMPUTED_VALUE"""),46040.0) -> 46040 | R29: =IFERROR(__xludf.DUMMYFUNCTION("""COMPUTED_VALUE"""),"Verified online") -> Verified online | S29: =IFERROR(__xludf.DUMMYFUNCTION("""COMPUTED_VALUE"""),"Fee based Battering Intervention and Prevention Program (BIPP) provides tools to end physical, verbal or emotional abuse. These are weekly sessions available in both English and Spanish. Free counseling services for adult survivors and children (3 years"&" and older) of abusive relationships. Available in English and Spanish") -> Fee based Battering Intervention and Prevention Program (BIPP) provides tools to end physical, verbal or emotional abuse. These are weekly sessions available in both English and Spanish. Free counseling services for adult survivors and children (3 years and older) of abusive relationships. Available in English and Spanish | T29: =IFERROR(__xludf.DUMMYFUNCTION("""COMPUTED_VALUE"""),FALSE) -> FALSE | U29: =IFERROR(__xludf.DUMMYFUNCTION("""COMPUTED_VALUE"""),FALSE) -> FALSE | V29: =IFERROR(__xludf.DUMMYFUNCTION("""COMPUTED_VALUE"""),"https://avda.org/") -> https://avda.org/ | W29: =IFERROR(__xludf.DUMMYFUNCTION("""COMPUTED_VALUE"""),"https://www.google.com/maps/place/910+9th+St,+Hempstead,+TX+77445/@30.0961763,-96.0795556,17z/data=!3m1!4b1!4m6!3m5!1s0x8646b5f1b69d9005:0x358dea5554b4780d!8m2!3d30.0961763!4d-96.0769753!16s%2Fg%2F11c4jtyf3r?entry=ttu&g_ep=EgoyMDI2MDExMy4wIKXMDSoKLDEwMDc5"&"MjA2OUgBUAM%3D") -> https://www.google.com/maps/place/910+9th+St,+Hempstead,+TX+77445/@30.0961763,-96.0795556,17z/data=!3m1!4b1!4m6!3m5!1s0x8646b5f1b69d9005:0x358dea5554b4780d!8m2!3d30.0961763!4d-96.0769753!16s%2Fg%2F11c4jtyf3r?entry=ttu&g_ep=EgoyMDI2MDExMy4wIKXMDSoKLDEwMDc5MjA2OUgBUAM%3D | Y29: =IFERROR(__xludf.DUMMYFUNCTION("""COMPUTED_VALUE"""),"Hempstead") -> Hempstead | Z29: =IFERROR(__xludf.DUMMYFUNCTION("""COMPUTED_VALUE"""),"Hempstead, Northside") -> Hempstead, Northside | AA29: =IFERROR(__xludf.DUMMYFUNCTION("""COMPUTED_VALUE"""),"Aid to Victims of Domestic Abuse (AVDA)") -> Aid to Victims of Domestic Abuse (AVDA) | AB29: =IFERROR(__xludf.DUMMYFUNCTION("""COMPUTED_VALUE"""),"Hempstead") -> Hempstead
A30: 29 | B30: =IFERROR(__xludf.DUMMYFUNCTION("""COMPUTED_VALUE"""),"[""77002"", ""77003"", ""77004"", ""77005"", ""77006"", ""77007"", ""77008"", ""77009"", ""77010"", ""77011"", ""77012"", ""77013"", ""77014"", ""77015"", ""77016"", ""77017"", ""77018"", ""77019"", ""77020"", ""77021"", ""77022"", ""77023"", ""77024"", "&"""77025"", ""77026"", ""77027"", ""77028"", ""77029"", ""77030"", ""77031"", ""77032"", ""77033"", ""77034"", ""77035"", ""77036"", ""77037"", ""77038"", ""77039"", ""77040"", ""77041"", ""77042"", ""77043"", ""77044"", ""77045"", ""77046"", ""77047"", """&"77048"", ""77049"", ""77050"", ""77051"", ""77054"", ""77055"", ""77056"", ""77057"", ""77058"", ""77059"", ""77060"", ""77061"", ""77062"", ""77063"", ""77064"", ""77065"", ""77066"", ""77067"", ""77068"", ""77069"", ""77070"", ""77071"", ""77072"", ""77"&"073"", ""77074"", ""77075"", ""77076"", ""77077"", ""77078"", ""77079"", ""77080"", ""77081"", ""77082"", ""77083"", ""77084"", ""77085"", ""77086"", ""77087"", ""77088"", ""77089"", ""77090"", ""77091"", ""77092"", ""77093"", ""77094"", ""77095"", ""7709"&"6"", ""77098"", ""77099"", ""77210"", ""77231"", ""77242"", ""77257"", ""77277"", ""77279"", ""77336"", ""77338"", ""77339"", ""77345"", ""77346"", ""77347"", ""77357"", ""77365"", ""77373"", ""77375"", ""77377"", ""77379"", ""77383"", ""77387"", ""77388"&""", ""77389"", ""77393"", ""77396"", ""77401"", ""77410"", ""77429"", ""77433"", ""77447"", ""77449"", ""77450"", ""77493"", ""77501"", ""77502"", ""77503"", ""77504"", ""77505"", ""77506"", ""77507"", ""77508"", ""77520"", ""77521"", ""77530"", ""77532"""&", ""77535"", ""77536"", ""77546"", ""77547"", ""77562"", ""77571"", ""77581"", ""77586"", ""77587"", ""77598""]") -> ["77002", "77003", "77004", "77005", "77006", "77007", "77008", "77009", "77010", "77011", "77012", "77013", "77014", "77015", "77016", "77017", "77018", "77019", "77020", "77021", "77022", "77023", "77024", "77025", "77026", "77027", "77028", "77029", "77030", "77031", "77032", "77033", "77034", "77035", "77036", "77037", "77038", "77039", "77040", "77041", "77042", "77043", "77044", "77045", "77046", "77047", "77048", "77049", "77050", "77051", "77054", "77055", "77056", "77057", "77058", "77059", "77060", "77061", "77062", "77063", "77064", "77065", "77066", "77067", "77068", "77069", "77070", "77071", "77072", "77073", "77074", "77075", "77076", "77077", "77078", "77079", "77080", "77081", "77082", "77083", "77084", "77085", "77086", "77087", "77088", "77089", "77090", "77091", "77092", "77093", "77094", "77095", "77096", "77098", "77099", "77210", "77231", "77242", "77257", "77277", "77279", "77336", "77338", "77339", "77345", "77346", "77347", "77357", "77365", "77373", "77375", "77377", "77379", "77383", "77387", "77388", "77389", "77393", "77396", "77401", "77410", "77429", "77433", "77447", "77449", "77450", "77493", "77501", "77502", "77503", "77504", "77505", "77506", "77507", "77508", "77520", "77521", "77530", "77532", "77535", "77536", "77546", "77547", "77562", "77571", "77581", "77586", "77587", "77598"] | C30: =IFERROR(__xludf.DUMMYFUNCTION("""COMPUTED_VALUE"""),"Aid to Victims of Domestic Abuse (AVDA)") -> Aid to Victims of Domestic Abuse (AVDA) | D30: =IFERROR(__xludf.DUMMYFUNCTION("""COMPUTED_VALUE"""),"1001 Texas Avenue") -> 1001 Texas Avenue | E30: =IFERROR(__xludf.DUMMYFUNCTION("""COMPUTED_VALUE"""),"Suite 600") -> Suite 600 | F30: =IFERROR(__xludf.DUMMYFUNCTION("""COMPUTED_VALUE"""),"Houston") -> Houston | G30: =IFERROR(__xludf.DUMMYFUNCTION("""COMPUTED_VALUE"""),"TX") -> TX | H30: =IFERROR(__xludf.DUMMYFUNCTION("""COMPUTED_VALUE"""),"77002") -> 77002 | I30: =IFERROR(__xludf.DUMMYFUNCTION("""COMPUTED_VALUE"""),"713-224-9911") -> 713-224-9911 | J30: =IFERROR(__xludf.DUMMYFUNCTION("""COMPUTED_VALUE"""),"29.75987665, -95.3617820466487") -> 29.75987665, -95.3617820466487 | K30: =IFERROR(__xludf.DUMMYFUNCTION("""COMPUTED_VALUE"""),"{""regular"":[{""days"":[""Mo"",""Tu"",""We"",""Th"",""Fr""],""open"":""08:00"",""close"":""17:00""}]}") -> {"regular":[{"days":["Mo","Tu","We","Th","Fr"],"open":"08:00","close":"17:00"}]} | M30: =IFERROR(__xludf.DUMMYFUNCTION("""COMPUTED_VALUE"""),54.0) -> 54 | N30: =IFERROR(__xludf.DUMMYFUNCTION("""COMPUTED_VALUE"""),"Legal") -> Legal | O30: =IFERROR(__xludf.DUMMYFUNCTION("""COMPUTED_VALUE"""),1.0) -> 1 | P30: =IFERROR(__xludf.DUMMYFUNCTION("""COMPUTED_VALUE"""),"ACTIVE") -> ACTIVE | Q30: =IFERROR(__xludf.DUMMYFUNCTION("""COMPUTED_VALUE"""),46040.0) -> 46040 | R30: =IFERROR(__xludf.DUMMYFUNCTION("""COMPUTED_VALUE"""),"Verified online") -> Verified online | S30: =IFERROR(__xludf.DUMMYFUNCTION("""COMPUTED_VALUE"""),"Free legal advice and representation for individuals who have experienced a pattern of physical, sexual or emotional abuse by partner in the past few year or has minor children who have been abused by partner. Must have been a Texas resident for six month"&"s and for the preceding three months in Austin, Grimes, Harris, Fort Bend Waller or Washington counties. Immigration status or citizenship is not an eligibility criteria.") -> Free legal advice and representation for individuals who have experienced a pattern of physical, sexual or emotional abuse by partner in the past few year or has minor children who have been abused by partner. Must have been a Texas resident for six months and for the preceding three months in Austin, Grimes, Harris, Fort Bend Waller or Washington counties. Immigration status or citizenship is not an eligibility criteria. | T30: =IFERROR(__xludf.DUMMYFUNCTION("""COMPUTED_VALUE"""),FALSE) -> FALSE | U30: =IFERROR(__xludf.DUMMYFUNCTION("""COMPUTED_VALUE"""),FALSE) -> FALSE | V30: =IFERROR(__xludf.DUMMYFUNCTION("""COMPUTED_VALUE"""),"https://avda.org/get-help/legal-aid/") -> https://avda.org/get-help/legal-aid/ | W30: =IFERROR(__xludf.DUMMYFUNCTION("""COMPUTED_VALUE"""),"https://www.google.com/maps/place/AVDA+(Aid+to+Victims+of+Domestic+Abuse)/@29.7600419,-95.3669883,17z/data=!3m2!4b1!5s0x8640c6aa65c8eea5:0x1dd626e1f5b80a6!4m6!3m5!1s0x8640bf13bd360545:0x6f740c2de58717e4!8m2!3d29.760042!4d-95.362112!16s%2Fg%2F1tdww1xs?entr"&"y=ttu&g_ep=EgoyMDI2MDExMy4wIKXMDSoKLDEwMDc5MjA2OUgBUAM%3D") -> https://www.google.com/maps/place/AVDA+(Aid+to+Victims+of+Domestic+Abuse)/@29.7600419,-95.3669883,17z/data=!3m2!4b1!5s0x8640c6aa65c8eea5:0x1dd626e1f5b80a6!4m6!3m5!1s0x8640bf13bd360545:0x6f740c2de58717e4!8m2!3d29.760042!4d-95.362112!16s%2Fg%2F1tdww1xs?entry=ttu&g_ep=EgoyMDI2MDExMy4wIKXMDSoKLDEwMDc5MjA2OUgBUAM%3D | Y30: =IFERROR(__xludf.DUMMYFUNCTION("""COMPUTED_VALUE"""),"Houston") -> Houston | Z30: =IFERROR(__xludf.DUMMYFUNCTION("""COMPUTED_VALUE"""),"Central Business District, Downtown Houston, East Downtown, South Central Houston, Theater District, University Place, Warehouse District") -> Central Business District, Downtown Houston, East Downtown, South Central Houston, Theater District, University Place, Warehouse District | AA30: =IFERROR(__xludf.DUMMYFUNCTION("""COMPUTED_VALUE"""),"Aid to Victims of Domestic Abuse (AVDA)") -> Aid to Victims of Domestic Abuse (AVDA) | AB30: =IFERROR(__xludf.DUMMYFUNCTION("""COMPUTED_VALUE"""),"Downtown Houston") -> Downtown Houston
A31: 30 | B31: =IFERROR(__xludf.DUMMYFUNCTION("""COMPUTED_VALUE"""),"[""77053"", ""77406"", ""77407"", ""77417"", ""77430"", ""77441"", ""77444"", ""77451"", ""77459"", ""77461"", ""77464"", ""77469"", ""77471"", ""77476"", ""77477"", ""77478"", ""77479"", ""77481"", ""77485"", ""77487"", ""77489"", ""77494"", ""77496"", "&"""77498"", ""77545"", ""77583"", ""77584""]") -> ["77053", "77406", "77407", "77417", "77430", "77441", "77444", "77451", "77459", "77461", "77464", "77469", "77471", "77476", "77477", "77478", "77479", "77481", "77485", "77487", "77489", "77494", "77496", "77498", "77545", "77583", "77584"] | C31: =IFERROR(__xludf.DUMMYFUNCTION("""COMPUTED_VALUE"""),"Aid to Victims of Domestic Abuse (AVDA)") -> Aid to Victims of Domestic Abuse (AVDA) | D31: =IFERROR(__xludf.DUMMYFUNCTION("""COMPUTED_VALUE"""),"12300 Parc Crest Drive") -> 12300 Parc Crest Drive | E31: =IFERROR(__xludf.DUMMYFUNCTION("""COMPUTED_VALUE"""),"Suite 140") -> Suite 140 | F31: =IFERROR(__xludf.DUMMYFUNCTION("""COMPUTED_VALUE"""),"Stafford") -> Stafford | G31: =IFERROR(__xludf.DUMMYFUNCTION("""COMPUTED_VALUE"""),"TX") -> TX | H31: =IFERROR(__xludf.DUMMYFUNCTION("""COMPUTED_VALUE"""),"77477") -> 77477 | I31: =IFERROR(__xludf.DUMMYFUNCTION("""COMPUTED_VALUE"""),"281-207-2312") -> 281-207-2312 | J31: =IFERROR(__xludf.DUMMYFUNCTION("""COMPUTED_VALUE"""),"29.64299514221335, -95.5686900498753") -> 29.64299514221335, -95.5686900498753 | K31: =IFERROR(__xludf.DUMMYFUNCTION("""COMPUTED_VALUE"""),"{""regular"":[{""days"":[""Mo"",""Tu"",""We"",""Th"",""Fr""],""open"":""08:00"",""close"":""17:00""}]}") -> {"regular":[{"days":["Mo","Tu","We","Th","Fr"],"open":"08:00","close":"17:00"}]} | M31: =IFERROR(__xludf.DUMMYFUNCTION("""COMPUTED_VALUE"""),54.0) -> 54 | N31: =IFERROR(__xludf.DUMMYFUNCTION("""COMPUTED_VALUE"""),"Legal") -> Legal | O31: =IFERROR(__xludf.DUMMYFUNCTION("""COMPUTED_VALUE"""),1.0) -> 1 | P31: =IFERROR(__xludf.DUMMYFUNCTION("""COMPUTED_VALUE"""),"ACTIVE") -> ACTIVE | Q31: =IFERROR(__xludf.DUMMYFUNCTION("""COMPUTED_VALUE"""),46040.0) -> 46040 | R31: =IFERROR(__xludf.DUMMYFUNCTION("""COMPUTED_VALUE"""),"Verified online") -> Verified online | S31: =IFERROR(__xludf.DUMMYFUNCTION("""COMPUTED_VALUE"""),"Free legal advice and representation for individuals who have experienced a pattern of physical, sexual or emotional abuse by partner in the past few year or has minor children who have been abused by partner. Must have been a Texas resident for six month"&"s and for the preceding three months in Austin, Grimes, Harris, Fort Bend Waller or Washington counties. Immigration status or citizenship is not an eligibility criteria.") -> Free legal advice and representation for individuals who have experienced a pattern of physical, sexual or emotional abuse by partner in the past few year or has minor children who have been abused by partner. Must have been a Texas resident for six months and for the preceding three months in Austin, Grimes, Harris, Fort Bend Waller or Washington counties. Immigration status or citizenship is not an eligibility criteria. | T31: =IFERROR(__xludf.DUMMYFUNCTION("""COMPUTED_VALUE"""),FALSE) -> FALSE | U31: =IFERROR(__xludf.DUMMYFUNCTION("""COMPUTED_VALUE"""),FALSE) -> FALSE | V31: =IFERROR(__xludf.DUMMYFUNCTION("""COMPUTED_VALUE"""),"https://avda.org/get-help/legal-aid/") -> https://avda.org/get-help/legal-aid/ | W31: =IFERROR(__xludf.DUMMYFUNCTION("""COMPUTED_VALUE"""),"https://www.google.com/maps/place/12300+Parc+Crest+Dr,+Stafford,+TX+77477/@29.6427714,-95.571324,17z/data=!3m1!4b1!4m6!3m5!1s0x8640e7db8e5876c1:0xe77e74e1dbfaf7a8!8m2!3d29.6427714!4d-95.5687437!16s%2Fg%2F11bw4ptrpn?entry=ttu&g_ep=EgoyMDI2MDExMy4wIKXMDSoKL"&"DEwMDc5MjA2OUgBUAM%3D") -> https://www.google.com/maps/place/12300+Parc+Crest+Dr,+Stafford,+TX+77477/@29.6427714,-95.571324,17z/data=!3m1!4b1!4m6!3m5!1s0x8640e7db8e5876c1:0xe77e74e1dbfaf7a8!8m2!3d29.6427714!4d-95.5687437!16s%2Fg%2F11bw4ptrpn?entry=ttu&g_ep=EgoyMDI2MDExMy4wIKXMDSoKLDEwMDc5MjA2OUgBUAM%3D | Y31: =IFERROR(__xludf.DUMMYFUNCTION("""COMPUTED_VALUE"""),"Stafford") -> Stafford | Z31: =IFERROR(__xludf.DUMMYFUNCTION("""COMPUTED_VALUE"""),"Clark Plaza One, Corporate Bus Park, Greenbriar Southwest, Stafford, The Fountains") -> Clark Plaza One, Corporate Bus Park, Greenbriar Southwest, Stafford, The Fountains | AA31: =IFERROR(__xludf.DUMMYFUNCTION("""COMPUTED_VALUE"""),"Aid to Victims of Domestic Abuse (AVDA)") -> Aid to Victims of Domestic Abuse (AVDA) | AB31: =IFERROR(__xludf.DUMMYFUNCTION("""COMPUTED_VALUE"""),"Stafford") -> Stafford
A32: 31 | B32: =IFERROR(__xludf.DUMMYFUNCTION("""COMPUTED_VALUE"""),"[""77363"", ""77418"", ""77423"", ""77426"", ""77445"", ""77446"", ""77452"", ""77466"", ""77474"", ""77484"", ""77492"", ""77833"", ""77835"", ""77868"", ""77880"", ""78932"", ""78946""]") -> ["77363", "77418", "77423", "77426", "77445", "77446", "77452", "77466", "77474", "77484", "77492", "77833", "77835", "77868", "77880", "78932", "78946"] | C32: =IFERROR(__xludf.DUMMYFUNCTION("""COMPUTED_VALUE"""),"Aid to Victims of Domestic Abuse (AVDA)") -> Aid to Victims of Domestic Abuse (AVDA) | D32: =IFERROR(__xludf.DUMMYFUNCTION("""COMPUTED_VALUE"""),"910 Ninth Street") -> 910 Ninth Street | F32: =IFERROR(__xludf.DUMMYFUNCTION("""COMPUTED_VALUE"""),"Hempstead") -> Hempstead | G32: =IFERROR(__xludf.DUMMYFUNCTION("""COMPUTED_VALUE"""),"TX") -> TX | H32: =IFERROR(__xludf.DUMMYFUNCTION("""COMPUTED_VALUE"""),"77445") -> 77445 | I32: =IFERROR(__xludf.DUMMYFUNCTION("""COMPUTED_VALUE"""),"979-826-3290") -> 979-826-3290 | J32: =IFERROR(__xludf.DUMMYFUNCTION("""COMPUTED_VALUE"""),"30.09638046314288, -96.0769752947155") -> 30.09638046314288, -96.0769752947155 | K32: =IFERROR(__xludf.DUMMYFUNCTION("""COMPUTED_VALUE"""),"{""regular"":[{""days"":[""Mo"",""Tu"",""We"",""Th"",""Fr""],""open"":""08:00"",""close"":""17:00""}]}") -> {"regular":[{"days":["Mo","Tu","We","Th","Fr"],"open":"08:00","close":"17:00"}]} | M32: =IFERROR(__xludf.DUMMYFUNCTION("""COMPUTED_VALUE"""),54.0) -> 54 | N32: =IFERROR(__xludf.DUMMYFUNCTION("""COMPUTED_VALUE"""),"Legal") -> Legal | O32: =IFERROR(__xludf.DUMMYFUNCTION("""COMPUTED_VALUE"""),1.0) -> 1 | P32: =IFERROR(__xludf.DUMMYFUNCTION("""COMPUTED_VALUE"""),"ACTIVE") -> ACTIVE | Q32: =IFERROR(__xludf.DUMMYFUNCTION("""COMPUTED_VALUE"""),46040.0) -> 46040 | R32: =IFERROR(__xludf.DUMMYFUNCTION("""COMPUTED_VALUE"""),"Verified online") -> Verified online | S32: =IFERROR(__xludf.DUMMYFUNCTION("""COMPUTED_VALUE"""),"Free legal advice and representation for individuals who have experienced a pattern of physical, sexual or emotional abuse by partner in the past few year or has minor children who have been abused by partner. Must have been a Texas resident for six month"&"s and for the preceding three months in Austin, Grimes, Harris, Fort Bend Waller or Washington counties. Immigration status or citizenship is not an eligibility criteria.") -> Free legal advice and representation for individuals who have experienced a pattern of physical, sexual or emotional abuse by partner in the past few year or has minor children who have been abused by partner. Must have been a Texas resident for six months and for the preceding three months in Austin, Grimes, Harris, Fort Bend Waller or Washington counties. Immigration status or citizenship is not an eligibility criteria. | T32: =IFERROR(__xludf.DUMMYFUNCTION("""COMPUTED_VALUE"""),FALSE) -> FALSE | U32: =IFERROR(__xludf.DUMMYFUNCTION("""COMPUTED_VALUE"""),FALSE) -> FALSE | V32: =IFERROR(__xludf.DUMMYFUNCTION("""COMPUTED_VALUE"""),"https://avda.org/get-help/legal-aid/") -> https://avda.org/get-help/legal-aid/ | W32: =IFERROR(__xludf.DUMMYFUNCTION("""COMPUTED_VALUE"""),"https://www.google.com/maps/place/910+9th+St,+Hempstead,+TX+77445/@30.0961763,-96.0795556,17z/data=!3m1!4b1!4m6!3m5!1s0x8646b5f1b69d9005:0x358dea5554b4780d!8m2!3d30.0961763!4d-96.0769753!16s%2Fg%2F11c4jtyf3r?entry=ttu&g_ep=EgoyMDI2MDExMy4wIKXMDSoKLDEwMDc5"&"MjA2OUgBUAM%3D") -> https://www.google.com/maps/place/910+9th+St,+Hempstead,+TX+77445/@30.0961763,-96.0795556,17z/data=!3m1!4b1!4m6!3m5!1s0x8646b5f1b69d9005:0x358dea5554b4780d!8m2!3d30.0961763!4d-96.0769753!16s%2Fg%2F11c4jtyf3r?entry=ttu&g_ep=EgoyMDI2MDExMy4wIKXMDSoKLDEwMDc5MjA2OUgBUAM%3D | Y32: =IFERROR(__xludf.DUMMYFUNCTION("""COMPUTED_VALUE"""),"Hempstead") -> Hempstead | Z32: =IFERROR(__xludf.DUMMYFUNCTION("""COMPUTED_VALUE"""),"Hempstead, Northside") -> Hempstead, Northside | AA32: =IFERROR(__xludf.DUMMYFUNCTION("""COMPUTED_VALUE"""),"Aid to Victims of Domestic Abuse (AVDA)") -> Aid to Victims of Domestic Abuse (AVDA) | AB32: =IFERROR(__xludf.DUMMYFUNCTION("""COMPUTED_VALUE"""),"Hempstead") -> Hempstead
A33: 32 | B33: =IFERROR(__xludf.DUMMYFUNCTION("""COMPUTED_VALUE"""),"[""99999""]") -> ["99999"] | C33: =IFERROR(__xludf.DUMMYFUNCTION("""COMPUTED_VALUE"""),"Airline Children & Women's Center") -> Airline Children & Women's Center | D33: =IFERROR(__xludf.DUMMYFUNCTION("""COMPUTED_VALUE"""),"5808 Airline Drive") -> 5808 Airline Drive | F33: =IFERROR(__xludf.DUMMYFUNCTION("""COMPUTED_VALUE"""),"Houston") -> Houston | G33: =IFERROR(__xludf.DUMMYFUNCTION("""COMPUTED_VALUE"""),"TX") -> TX | H33: =IFERROR(__xludf.DUMMYFUNCTION("""COMPUTED_VALUE"""),"77076") -> 77076 | I33: =IFERROR(__xludf.DUMMYFUNCTION("""COMPUTED_VALUE"""),"713-695-4013") -> 713-695-4013 | J33: =IFERROR(__xludf.DUMMYFUNCTION("""COMPUTED_VALUE"""),"29.7803014, -95.3098685") -> 29.7803014, -95.3098685 | K33: =IFERROR(__xludf.DUMMYFUNCTION("""COMPUTED_VALUE"""),"{""regular"":[{""days"":[""Mo"",""Tu"",""We"",""Th""],""open"":""07:30"",""close"":""20:00""},{""days"":[""Fr""],""open"":""07:30"",""close"":""17:00""}]}") -> {"regular":[{"days":["Mo","Tu","We","Th"],"open":"07:30","close":"20:00"},{"days":["Fr"],"open":"07:30","close":"17:00"}]} | L33: =IFERROR(__xludf.DUMMYFUNCTION("""COMPUTED_VALUE"""),"Appointment required") -> Appointment required | M33: =IFERROR(__xludf.DUMMYFUNCTION("""COMPUTED_VALUE"""),31.0) -> 31 | N33: =IFERROR(__xludf.DUMMYFUNCTION("""COMPUTED_VALUE"""),"Medical - Primary Care") -> Medical - Primary Care | O33: =IFERROR(__xludf.DUMMYFUNCTION("""COMPUTED_VALUE"""),1.0) -> 1 | P33: =IFERROR(__xludf.DUMMYFUNCTION("""COMPUTED_VALUE"""),"ACTIVE") -> ACTIVE | Q33: =IFERROR(__xludf.DUMMYFUNCTION("""COMPUTED_VALUE"""),46049.0) -> 46049 | R33: =IFERROR(__xludf.DUMMYFUNCTION("""COMPUTED_VALUE"""),"Verified online") -> Verified online | S33: =IFERROR(__xludf.DUMMYFUNCTION("""COMPUTED_VALUE"""),"Pediatrics, women's health and maternity care. Women's health including pre and postnatal care for mother and baby Uninsured patients pay what is affordable based on income and family size. Will help determine if you qualify for medical assistance program"&"s and help enroll, if you are. Limited number of same day appointments.") -> Pediatrics, women's health and maternity care. Women's health including pre and postnatal care for mother and baby Uninsured patients pay what is affordable based on income and family size. Will help determine if you qualify for medical assistance programs and help enroll, if you are. Limited number of same day appointments. | T33: =IFERROR(__xludf.DUMMYFUNCTION("""COMPUTED_VALUE"""),FALSE) -> FALSE | U33: =IFERROR(__xludf.DUMMYFUNCTION("""COMPUTED_VALUE"""),FALSE) -> FALSE | V33: =IFERROR(__xludf.DUMMYFUNCTION("""COMPUTED_VALUE"""),"https://www.denverharborhealthcenter.org") -> https://www.denverharborhealthcenter.org | W33: =IFERROR(__xludf.DUMMYFUNCTION("""COMPUTED_VALUE"""),"https://www.google.com/maps/place/Vecino's+Denver+Harbor+Family+Health+Center/@29.7804606,-95.3124257,16z/data=!3m1!4b1!4m6!3m5!1s0x8640bbfe0493ec21:0xa8baa6b440546cf3!8m2!3d29.780456!4d-95.3098454!16s%2Fg%2F1td9whln?entry=ttu&g_ep=EgoyMDI0MDkwNC4wIKXMDSo"&"ASAFQAw%3D%3D") -> https://www.google.com/maps/place/Vecino's+Denver+Harbor+Family+Health+Center/@29.7804606,-95.3124257,16z/data=!3m1!4b1!4m6!3m5!1s0x8640bbfe0493ec21:0xa8baa6b440546cf3!8m2!3d29.780456!4d-95.3098454!16s%2Fg%2F1td9whln?entry=ttu&g_ep=EgoyMDI0MDkwNC4wIKXMDSoASAFQAw%3D%3D | Y33: =IFERROR(__xludf.DUMMYFUNCTION("""COMPUTED_VALUE"""),"Houston") -> Houston | Z33: =IFERROR(__xludf.DUMMYFUNCTION("""COMPUTED_VALUE"""),"Independence Heights, Northline, Northside / Northline") -> Independence Heights, Northline, Northside / Northline | AA33: =IFERROR(__xludf.DUMMYFUNCTION("""COMPUTED_VALUE"""),"Vecino Health Centers") -> Vecino Health Centers | AB33: =IFERROR(__xludf.DUMMYFUNCTION("""COMPUTED_VALUE"""),"Denver Harbor / Port Houston") -> Denver Harbor / Port Houston
A34: 33 | B34: =IFERROR(__xludf.DUMMYFUNCTION("""COMPUTED_VALUE"""),"[""99999""]") -> ["99999"] | C34: =IFERROR(__xludf.DUMMYFUNCTION("""COMPUTED_VALUE"""),"Aishel House") -> Aishel House | D34: =IFERROR(__xludf.DUMMYFUNCTION("""COMPUTED_VALUE"""),"1955 University Blvd") -> 1955 University Blvd | F34: =IFERROR(__xludf.DUMMYFUNCTION("""COMPUTED_VALUE"""),"Houston") -> Houston | G34: =IFERROR(__xludf.DUMMYFUNCTION("""COMPUTED_VALUE"""),"TX") -> TX | H34: =IFERROR(__xludf.DUMMYFUNCTION("""COMPUTED_VALUE"""),"77030") -> 77030 | I34: =IFERROR(__xludf.DUMMYFUNCTION("""COMPUTED_VALUE"""),"713-522-2004") -> 713-522-2004 | J34: =IFERROR(__xludf.DUMMYFUNCTION("""COMPUTED_VALUE"""),"29.712198982313293, -95.40376502706353") -> 29.712198982313293, -95.40376502706353 | K34: =IFERROR(__xludf.DUMMYFUNCTION("""COMPUTED_VALUE"""),"{""regular"":[{""days"":[""Mo"",""Tu"",""We"",""Th"",""Fr""],""open"":""09:00"",""close"":""17:00""}]}") -> {"regular":[{"days":["Mo","Tu","We","Th","Fr"],"open":"09:00","close":"17:00"}]} | L34: =IFERROR(__xludf.DUMMYFUNCTION("""COMPUTED_VALUE"""),"Apply online") -> Apply online | M34: =IFERROR(__xludf.DUMMYFUNCTION("""COMPUTED_VALUE"""),37.0) -> 37 | N34: =IFERROR(__xludf.DUMMYFUNCTION("""COMPUTED_VALUE"""),"Medical - Housing") -> Medical - Housing | O34: =IFERROR(__xludf.DUMMYFUNCTION("""COMPUTED_VALUE"""),1.0) -> 1 | P34: =IFERROR(__xludf.DUMMYFUNCTION("""COMPUTED_VALUE"""),"ACTIVE") -> ACTIVE | Q34: =IFERROR(__xludf.DUMMYFUNCTION("""COMPUTED_VALUE"""),46036.0) -> 46036 | R34: =IFERROR(__xludf.DUMMYFUNCTION("""COMPUTED_VALUE"""),"Verified online") -> Verified online | S34: =IFERROR(__xludf.DUMMYFUNCTION("""COMPUTED_VALUE"""),"Provides patients and families visiting the Texas Medical center with accommodations, transportation, meals, childcare and counseling. Medical housing.") -> Provides patients and families visiting the Texas Medical center with accommodations, transportation, meals, childcare and counseling. Medical housing. | T34: =IFERROR(__xludf.DUMMYFUNCTION("""COMPUTED_VALUE"""),FALSE) -> FALSE | U34: =IFERROR(__xludf.DUMMYFUNCTION("""COMPUTED_VALUE"""),FALSE) -> FALSE | V34: =IFERROR(__xludf.DUMMYFUNCTION("""COMPUTED_VALUE"""),"https://www.aishelhouse.org/patients/stay-with-us/") -> https://www.aishelhouse.org/patients/stay-with-us/ | W34: =IFERROR(__xludf.DUMMYFUNCTION("""COMPUTED_VALUE"""),"https://www.google.com/maps/place/Aishel+House/@29.7118263,-95.4063507,16z/data=!3m1!4b1!4m6!3m5!1s0x8640c07016137dbf:0x16c023b2074d0f7a!8m2!3d29.7118263!4d-95.4037704!16s%2Fg%2F1tjt29qf?entry=ttu&g_ep=EgoyMDI2MDExMS4wIKXMDSoKLDEwMDc5MjA2OUgBUAM%3D") -> https://www.google.com/maps/place/Aishel+House/@29.7118263,-95.4063507,16z/data=!3m1!4b1!4m6!3m5!1s0x8640c07016137dbf:0x16c023b2074d0f7a!8m2!3d29.7118263!4d-95.4037704!16s%2Fg%2F1tjt29qf?entry=ttu&g_ep=EgoyMDI2MDExMS4wIKXMDSoKLDEwMDc5MjA2OUgBUAM%3D | Y34: =IFERROR(__xludf.DUMMYFUNCTION("""COMPUTED_VALUE"""),"Houston") -> Houston | Z34: =IFERROR(__xludf.DUMMYFUNCTION("""COMPUTED_VALUE"""),"Central Southwest, Houston Museum District, South Central Houston, Southgate, Texas Medical Center") -> Central Southwest, Houston Museum District, South Central Houston, Southgate, Texas Medical Center | AA34: =IFERROR(__xludf.DUMMYFUNCTION("""COMPUTED_VALUE"""),"Aishel House") -> Aishel House | AB34: =IFERROR(__xludf.DUMMYFUNCTION("""COMPUTED_VALUE"""),"South Central Houston") -> South Central Houston
A35: 34 | B35: =IFERROR(__xludf.DUMMYFUNCTION("""COMPUTED_VALUE"""),"[""77025"", ""77030"", ""77031"", ""77035"", ""77036"", ""77045"", ""77046"", ""77054"", ""77071"", ""77072"", ""77074"", ""77081"", ""77083"", ""77085"", ""77096"", ""77099""]") -> ["77025", "77030", "77031", "77035", "77036", "77045", "77046", "77054", "77071", "77072", "77074", "77081", "77083", "77085", "77096", "77099"] | C35: =IFERROR(__xludf.DUMMYFUNCTION("""COMPUTED_VALUE"""),"Alexander Jewish Family Service") -> Alexander Jewish Family Service | D35: =IFERROR(__xludf.DUMMYFUNCTION("""COMPUTED_VALUE"""),"4131 S. Braeswood Blvd") -> 4131 S. Braeswood Blvd | F35: =IFERROR(__xludf.DUMMYFUNCTION("""COMPUTED_VALUE"""),"Houston") -> Houston | G35: =IFERROR(__xludf.DUMMYFUNCTION("""COMPUTED_VALUE"""),"TX") -> TX | H35: =IFERROR(__xludf.DUMMYFUNCTION("""COMPUTED_VALUE"""),"77025") -> 77025 | I35: =IFERROR(__xludf.DUMMYFUNCTION("""COMPUTED_VALUE"""),"713-986-7837") -> 713-986-7837 | J35: =IFERROR(__xludf.DUMMYFUNCTION("""COMPUTED_VALUE"""),"29.68805345, -95.4440327818119") -> 29.68805345, -95.4440327818119 | K35: =IFERROR(__xludf.DUMMYFUNCTION("""COMPUTED_VALUE"""),"{""regular"":[{""days"":[""Tu"",""We"",""Th""],""open"":""10:00"",""close"":""12:00""}]}") -> {"regular":[{"days":["Tu","We","Th"],"open":"10:00","close":"12:00"}]} | L35: =IFERROR(__xludf.DUMMYFUNCTION("""COMPUTED_VALUE"""),"2nd Week of Month Only") -> 2nd Week of Month Only | M35: =IFERROR(__xludf.DUMMYFUNCTION("""COMPUTED_VALUE"""),11.0) -> 11 | N35: =IFERROR(__xludf.DUMMYFUNCTION("""COMPUTED_VALUE"""),"Rent") -> Rent | O35: =IFERROR(__xludf.DUMMYFUNCTION("""COMPUTED_VALUE"""),1.0) -> 1 | P35: =IFERROR(__xludf.DUMMYFUNCTION("""COMPUTED_VALUE"""),"ACTIVE") -> ACTIVE | Q35: =IFERROR(__xludf.DUMMYFUNCTION("""COMPUTED_VALUE"""),45793.0) -> 45793 | R35: =IFERROR(__xludf.DUMMYFUNCTION("""COMPUTED_VALUE"""),"Verified by phone") -> Verified by phone | S35: =IFERROR(__xludf.DUMMYFUNCTION("""COMPUTED_VALUE"""),"Talk to case worker about requirements.") -> Talk to case worker about requirements. | T35: =IFERROR(__xludf.DUMMYFUNCTION("""COMPUTED_VALUE"""),FALSE) -> FALSE | U35: =IFERROR(__xludf.DUMMYFUNCTION("""COMPUTED_VALUE"""),FALSE) -> FALSE | V35: =IFERROR(__xludf.DUMMYFUNCTION("""COMPUTED_VALUE"""),"https://www.alexanderjfs.org/") -> https://www.alexanderjfs.org/ | W35: =IFERROR(__xludf.DUMMYFUNCTION("""COMPUTED_VALUE"""),"https://maps.app.goo.gl/FEhdBRkjwU1f7Fgh9") -> https://maps.app.goo.gl/FEhdBRkjwU1f7Fgh9 | Y35: =IFERROR(__xludf.DUMMYFUNCTION("""COMPUTED_VALUE"""),"Houston") -> Houston | Z35: =IFERROR(__xludf.DUMMYFUNCTION("""COMPUTED_VALUE"""),"Braeswood, Braeswood Place, Knollwood Village") -> Braeswood, Braeswood Place, Knollwood Village | AA35: =IFERROR(__xludf.DUMMYFUNCTION("""COMPUTED_VALUE"""),"Alexander Jewish Family Service") -> Alexander Jewish Family Service | AB35: =IFERROR(__xludf.DUMMYFUNCTION("""COMPUTED_VALUE"""),"Braeswood") -> Braeswood
A36: 35 | B36: =IFERROR(__xludf.DUMMYFUNCTION("""COMPUTED_VALUE"""),"[""77025"", ""77030"", ""77031"", ""77035"", ""77036"", ""77045"", ""77046"", ""77054"", ""77071"", ""77072"", ""77074"", ""77081"", ""77083"", ""77085"", ""77096"", ""77099""]") -> ["77025", "77030", "77031", "77035", "77036", "77045", "77046", "77054", "77071", "77072", "77074", "77081", "77083", "77085", "77096", "77099"] | C36: =IFERROR(__xludf.DUMMYFUNCTION("""COMPUTED_VALUE"""),"Alexander Jewish Family Service") -> Alexander Jewish Family Service | D36: =IFERROR(__xludf.DUMMYFUNCTION("""COMPUTED_VALUE"""),"4131 S. Braeswood Blvd") -> 4131 S. Braeswood Blvd | F36: =IFERROR(__xludf.DUMMYFUNCTION("""COMPUTED_VALUE"""),"Houston") -> Houston | G36: =IFERROR(__xludf.DUMMYFUNCTION("""COMPUTED_VALUE"""),"TX") -> TX | H36: =IFERROR(__xludf.DUMMYFUNCTION("""COMPUTED_VALUE"""),"77025") -> 77025 | I36: =IFERROR(__xludf.DUMMYFUNCTION("""COMPUTED_VALUE"""),"713-986-7837") -> 713-986-7837 | J36: =IFERROR(__xludf.DUMMYFUNCTION("""COMPUTED_VALUE"""),"29.68805345, -95.4440327818119") -> 29.68805345, -95.4440327818119 | K36: =IFERROR(__xludf.DUMMYFUNCTION("""COMPUTED_VALUE"""),"{""regular"":[{""days"":[""Tu"",""We"",""Th""],""open"":""10:00"",""close"":""12:00""}]}") -> {"regular":[{"days":["Tu","We","Th"],"open":"10:00","close":"12:00"}]} | L36: =IFERROR(__xludf.DUMMYFUNCTION("""COMPUTED_VALUE"""),"2nd Week of Month Only") -> 2nd Week of Month Only | M36: =IFERROR(__xludf.DUMMYFUNCTION("""COMPUTED_VALUE"""),12.0) -> 12 | N36: =IFERROR(__xludf.DUMMYFUNCTION("""COMPUTED_VALUE"""),"Utilities") -> Utilities | O36: =IFERROR(__xludf.DUMMYFUNCTION("""COMPUTED_VALUE"""),1.0) -> 1 | P36: =IFERROR(__xludf.DUMMYFUNCTION("""COMPUTED_VALUE"""),"ACTIVE") -> ACTIVE | Q36: =IFERROR(__xludf.DUMMYFUNCTION("""COMPUTED_VALUE"""),45793.0) -> 45793 | R36: =IFERROR(__xludf.DUMMYFUNCTION("""COMPUTED_VALUE"""),"Verified by phone") -> Verified by phone | S36: =IFERROR(__xludf.DUMMYFUNCTION("""COMPUTED_VALUE"""),"Talk to case worker about requirements.") -> Talk to case worker about requirements. | T36: =IFERROR(__xludf.DUMMYFUNCTION("""COMPUTED_VALUE"""),FALSE) -> FALSE | U36: =IFERROR(__xludf.DUMMYFUNCTION("""COMPUTED_VALUE"""),FALSE) -> FALSE | V36: =IFERROR(__xludf.DUMMYFUNCTION("""COMPUTED_VALUE"""),"https://www.alexanderjfs.org/") -> https://www.alexanderjfs.org/ | W36: =IFERROR(__xludf.DUMMYFUNCTION("""COMPUTED_VALUE"""),"https://maps.app.goo.gl/FEhdBRkjwU1f7Fgh9") -> https://maps.app.goo.gl/FEhdBRkjwU1f7Fgh9 | Y36: =IFERROR(__xludf.DUMMYFUNCTION("""COMPUTED_VALUE"""),"Houston") -> Houston | Z36: =IFERROR(__xludf.DUMMYFUNCTION("""COMPUTED_VALUE"""),"Braeswood, Braeswood Place, Knollwood Village") -> Braeswood, Braeswood Place, Knollwood Village | AA36: =IFERROR(__xludf.DUMMYFUNCTION("""COMPUTED_VALUE"""),"Alexander Jewish Family Service") -> Alexander Jewish Family Service | AB36: =IFERROR(__xludf.DUMMYFUNCTION("""COMPUTED_VALUE"""),"Braeswood") -> Braeswood
A37: 36 | B37: =IFERROR(__xludf.DUMMYFUNCTION("""COMPUTED_VALUE"""),"[""77025"", ""77030"", ""77031"", ""77035"", ""77036"", ""77045"", ""77046"", ""77054"", ""77071"", ""77072"", ""77074"", ""77081"", ""77083"", ""77085"", ""77096"", ""77099""]") -> ["77025", "77030", "77031", "77035", "77036", "77045", "77046", "77054", "77071", "77072", "77074", "77081", "77083", "77085", "77096", "77099"] | C37: =IFERROR(__xludf.DUMMYFUNCTION("""COMPUTED_VALUE"""),"Alexander Jewish Family Service") -> Alexander Jewish Family Service | D37: =IFERROR(__xludf.DUMMYFUNCTION("""COMPUTED_VALUE"""),"4131 S. Braeswood Blvd") -> 4131 S. Braeswood Blvd | F37: =IFERROR(__xludf.DUMMYFUNCTION("""COMPUTED_VALUE"""),"Houston") -> Houston | G37: =IFERROR(__xludf.DUMMYFUNCTION("""COMPUTED_VALUE"""),"TX") -> TX | H37: =IFERROR(__xludf.DUMMYFUNCTION("""COMPUTED_VALUE"""),"77025") -> 77025 | I37: =IFERROR(__xludf.DUMMYFUNCTION("""COMPUTED_VALUE"""),"713-667-9336") -> 713-667-9336 | J37: =IFERROR(__xludf.DUMMYFUNCTION("""COMPUTED_VALUE"""),"29.68805345, -95.4440327818119") -> 29.68805345, -95.4440327818119 | K37: =IFERROR(__xludf.DUMMYFUNCTION("""COMPUTED_VALUE"""),"{""regular"":[{""days"":[""Mo"",""Tu"",""We"",""Th"",""Fr""],""open"":""08:00"",""close"":""16:00""}]}") -> {"regular":[{"days":["Mo","Tu","We","Th","Fr"],"open":"08:00","close":"16:00"}]} | M37: =IFERROR(__xludf.DUMMYFUNCTION("""COMPUTED_VALUE"""),33.0) -> 33 | N37: =IFERROR(__xludf.DUMMYFUNCTION("""COMPUTED_VALUE"""),"Medical - Behavioral Health") -> Medical - Behavioral Health | O37: =IFERROR(__xludf.DUMMYFUNCTION("""COMPUTED_VALUE"""),1.0) -> 1 | P37: =IFERROR(__xludf.DUMMYFUNCTION("""COMPUTED_VALUE"""),"ACTIVE") -> ACTIVE | Q37: =IFERROR(__xludf.DUMMYFUNCTION("""COMPUTED_VALUE"""),45674.0) -> 45674 | R37: =IFERROR(__xludf.DUMMYFUNCTION("""COMPUTED_VALUE"""),"Verified by phone") -> Verified by phone | S37: =IFERROR(__xludf.DUMMYFUNCTION("""COMPUTED_VALUE"""),"Licensed mental health professionals for adults and children.") -> Licensed mental health professionals for adults and children. | T37: =IFERROR(__xludf.DUMMYFUNCTION("""COMPUTED_VALUE"""),FALSE) -> FALSE | U37: =IFERROR(__xludf.DUMMYFUNCTION("""COMPUTED_VALUE"""),FALSE) -> FALSE | V37: =IFERROR(__xludf.DUMMYFUNCTION("""COMPUTED_VALUE"""),"https://www.alexanderjfs.org/") -> https://www.alexanderjfs.org/ | W37: =IFERROR(__xludf.DUMMYFUNCTION("""COMPUTED_VALUE"""),"https://maps.app.goo.gl/FEhdBRkjwU1f7Fgh9") -> https://maps.app.goo.gl/FEhdBRkjwU1f7Fgh9 | Y37: =IFERROR(__xludf.DUMMYFUNCTION("""COMPUTED_VALUE"""),"Houston") -> Houston | Z37: =IFERROR(__xludf.DUMMYFUNCTION("""COMPUTED_VALUE"""),"Braeswood, Braeswood Place, Knollwood Village") -> Braeswood, Braeswood Place, Knollwood Village | AA37: =IFERROR(__xludf.DUMMYFUNCTION("""COMPUTED_VALUE"""),"Alexander Jewish Family Service") -> Alexander Jewish Family Service | AB37: =IFERROR(__xludf.DUMMYFUNCTION("""COMPUTED_VALUE"""),"Braeswood") -> Braeswood
A38: 37 | B38: =IFERROR(__xludf.DUMMYFUNCTION("""COMPUTED_VALUE"""),"[""77025"", ""77030"", ""77031"", ""77035"", ""77036"", ""77045"", ""77046"", ""77054"", ""77071"", ""77072"", ""77074"", ""77081"", ""77083"", ""77085"", ""77096"", ""77099""]") -> ["77025", "77030", "77031", "77035", "77036", "77045", "77046", "77054", "77071", "77072", "77074", "77081", "77083", "77085", "77096", "77099"] | C38: =IFERROR(__xludf.DUMMYFUNCTION("""COMPUTED_VALUE"""),"Alexander Jewish Family Service") -> Alexander Jewish Family Service | D38: =IFERROR(__xludf.DUMMYFUNCTION("""COMPUTED_VALUE"""),"4131 S. Braeswood Blvd") -> 4131 S. Braeswood Blvd | F38: =IFERROR(__xludf.DUMMYFUNCTION("""COMPUTED_VALUE"""),"Houston") -> Houston | G38: =IFERROR(__xludf.DUMMYFUNCTION("""COMPUTED_VALUE"""),"TX") -> TX | H38: =IFERROR(__xludf.DUMMYFUNCTION("""COMPUTED_VALUE"""),"77025") -> 77025 | I38: =IFERROR(__xludf.DUMMYFUNCTION("""COMPUTED_VALUE"""),"713-667-9336") -> 713-667-9336 | J38: =IFERROR(__xludf.DUMMYFUNCTION("""COMPUTED_VALUE"""),"29.68805345, -95.4440327818119") -> 29.68805345, -95.4440327818119 | K38: =IFERROR(__xludf.DUMMYFUNCTION("""COMPUTED_VALUE"""),"{""regular"":[{""days"":[""Mo"",""Tu"",""We"",""Th"",""Fr""],""open"":""08:00"",""close"":""16:00""}]}") -> {"regular":[{"days":["Mo","Tu","We","Th","Fr"],"open":"08:00","close":"16:00"}]} | M38: =IFERROR(__xludf.DUMMYFUNCTION("""COMPUTED_VALUE"""),52.0) -> 52 | N38: =IFERROR(__xludf.DUMMYFUNCTION("""COMPUTED_VALUE"""),"Jobs") -> Jobs | O38: =IFERROR(__xludf.DUMMYFUNCTION("""COMPUTED_VALUE"""),1.0) -> 1 | P38: =IFERROR(__xludf.DUMMYFUNCTION("""COMPUTED_VALUE"""),"ACTIVE") -> ACTIVE | Q38: =IFERROR(__xludf.DUMMYFUNCTION("""COMPUTED_VALUE"""),45674.0) -> 45674 | R38: =IFERROR(__xludf.DUMMYFUNCTION("""COMPUTED_VALUE"""),"Verified by phone") -> Verified by phone | S38: =IFERROR(__xludf.DUMMYFUNCTION("""COMPUTED_VALUE"""),"Career coaching and employment training. Career guidance for people with disabilities.") -> Career coaching and employment training. Career guidance for people with disabilities. | T38: =IFERROR(__xludf.DUMMYFUNCTION("""COMPUTED_VALUE"""),FALSE) -> FALSE | U38: =IFERROR(__xludf.DUMMYFUNCTION("""COMPUTED_VALUE"""),FALSE) -> FALSE | V38: =IFERROR(__xludf.DUMMYFUNCTION("""COMPUTED_VALUE"""),"https://www.alexanderjfs.org/") -> https://www.alexanderjfs.org/ | W38: =IFERROR(__xludf.DUMMYFUNCTION("""COMPUTED_VALUE"""),"https://maps.app.goo.gl/FEhdBRkjwU1f7Fgh9") -> https://maps.app.goo.gl/FEhdBRkjwU1f7Fgh9 | Y38: =IFERROR(__xludf.DUMMYFUNCTION("""COMPUTED_VALUE"""),"Houston") -> Houston | Z38: =IFERROR(__xludf.DUMMYFUNCTION("""COMPUTED_VALUE"""),"Braeswood, Braeswood Place, Knollwood Village") -> Braeswood, Braeswood Place, Knollwood Village | AA38: =IFERROR(__xludf.DUMMYFUNCTION("""COMPUTED_VALUE"""),"Alexander Jewish Family Service") -> Alexander Jewish Family Service | AB38: =IFERROR(__xludf.DUMMYFUNCTION("""COMPUTED_VALUE"""),"Braeswood") -> Braeswood
A39: 38 | B39: =IFERROR(__xludf.DUMMYFUNCTION("""COMPUTED_VALUE"""),"[""77002"", ""77003"", ""77004"", ""77005"", ""77006"", ""77007"", ""77008"", ""77009"", ""77010"", ""77011"", ""77012"", ""77013"", ""77014"", ""77015"", ""77016"", ""77017"", ""77018"", ""77019"", ""77020"", ""77021"", ""77022"", ""77023"", ""77024"", "&"""77025"", ""77026"", ""77027"", ""77028"", ""77029"", ""77030"", ""77031"", ""77032"", ""77033"", ""77034"", ""77035"", ""77036"", ""77037"", ""77038"", ""77039"", ""77040"", ""77041"", ""77042"", ""77043"", ""77044"", ""77045"", ""77046"", ""77047"", """&"77048"", ""77049"", ""77050"", ""77051"", ""77053"", ""77054"", ""77055"", ""77056"", ""77057"", ""77058"", ""77059"", ""77060"", ""77061"", ""77062"", ""77063"", ""77064"", ""77065"", ""77066"", ""77067"", ""77068"", ""77069"", ""77070"", ""77071"", ""77"&"072"", ""77073"", ""77074"", ""77075"", ""77076"", ""77077"", ""77078"", ""77079"", ""77080"", ""77081"", ""77082"", ""77083"", ""77084"", ""77085"", ""77086"", ""77087"", ""77088"", ""77089"", ""77090"", ""77091"", ""77092"", ""77093"", ""77094"", ""7709"&"5"", ""77096"", ""77098"", ""77099"", ""77242"", ""77257"", ""77277"", ""77279""]") -> ["77002", "77003", "77004", "77005", "77006", "77007", "77008", "77009", "77010", "77011", "77012", "77013", "77014", "77015", "77016", "77017", "77018", "77019", "77020", "77021", "77022", "77023", "77024", "77025", "77026", "77027", "77028", "77029", "77030", "77031", "77032", "77033", "77034", "77035", "77036", "77037", "77038", "77039", "77040", "77041", "77042", "77043", "77044", "77045", "77046", "77047", "77048", "77049", "77050", "77051", "77053", "77054", "77055", "77056", "77057", "77058", "77059", "77060", "77061", "77062", "77063", "77064", "77065", "77066", "77067", "77068", "77069", "77070", "77071", "77072", "77073", "77074", "77075", "77076", "77077", "77078", "77079", "77080", "77081", "77082", "77083", "77084", "77085", "77086", "77087", "77088", "77089", "77090", "77091", "77092", "77093", "77094", "77095", "77096", "77098", "77099", "77242", "77257", "77277", "77279"] | C39: =IFERROR(__xludf.DUMMYFUNCTION("""COMPUTED_VALUE"""),"Alief Neighborhood Center") -> Alief Neighborhood Center | D39: =IFERROR(__xludf.DUMMYFUNCTION("""COMPUTED_VALUE"""),"11903 Bellaire Blvd") -> 11903 Bellaire Blvd | F39: =IFERROR(__xludf.DUMMYFUNCTION("""COMPUTED_VALUE"""),"Houston") -> Houston | G39: =IFERROR(__xludf.DUMMYFUNCTION("""COMPUTED_VALUE"""),"TX") -> TX | H39: =IFERROR(__xludf.DUMMYFUNCTION("""COMPUTED_VALUE"""),"77072") -> 77072 | I39: =IFERROR(__xludf.DUMMYFUNCTION("""COMPUTED_VALUE"""),"832-393-5427") -> 832-393-5427 | J39: =IFERROR(__xludf.DUMMYFUNCTION("""COMPUTED_VALUE"""),"29.70297345115537, -95.58882452197315") -> 29.70297345115537, -95.58882452197315 | K39: =IFERROR(__xludf.DUMMYFUNCTION("""COMPUTED_VALUE"""),"{""regular"":[{""days"":[""Mo"",""Tu"",""We"",""Th""],""open"":""08:00"",""close"":""17:00""}]}") -> {"regular":[{"days":["Mo","Tu","We","Th"],"open":"08:00","close":"17:00"}]} | M39: =IFERROR(__xludf.DUMMYFUNCTION("""COMPUTED_VALUE"""),44.0) -> 44 | N39: =IFERROR(__xludf.DUMMYFUNCTION("""COMPUTED_VALUE"""),"Mother & Child") -> Mother & Child | O39: =IFERROR(__xludf.DUMMYFUNCTION("""COMPUTED_VALUE"""),1.0) -> 1 | P39: =IFERROR(__xludf.DUMMYFUNCTION("""COMPUTED_VALUE"""),"ACTIVE") -> ACTIVE | Q39: =IFERROR(__xludf.DUMMYFUNCTION("""COMPUTED_VALUE"""),46057.0) -> 46057 | R39: =IFERROR(__xludf.DUMMYFUNCTION("""COMPUTED_VALUE"""),"Verified online") -> Verified online | S39: =IFERROR(__xludf.DUMMYFUNCTION("""COMPUTED_VALUE"""),"Women, Infants and Children (WIC) Supplemental nutrition program providing health care referrals, nutrition education and nutritious foods to pregnant, breastfeeding and postpartum women and children under five who have nutrition health-related problems.") -> Women, Infants and Children (WIC) Supplemental nutrition program providing health care referrals, nutrition education and nutritious foods to pregnant, breastfeeding and postpartum women and children under five who have nutrition health-related problems. | T39: =IFERROR(__xludf.DUMMYFUNCTION("""COMPUTED_VALUE"""),FALSE) -> FALSE | U39: =IFERROR(__xludf.DUMMYFUNCTION("""COMPUTED_VALUE"""),FALSE) -> FALSE | V39: =IFERROR(__xludf.DUMMYFUNCTION("""COMPUTED_VALUE"""),"https://www.houstonhealth.org/services/multi-service-centers/alief-multi-service-center") -> https://www.houstonhealth.org/services/multi-service-centers/alief-multi-service-center | W39: =IFERROR(__xludf.DUMMYFUNCTION("""COMPUTED_VALUE"""),"https://www.google.com/maps/place/Alief+Neighborhood+Center/@29.7027824,-95.5914638,17z/data=!3m1!4b1!4m6!3m5!1s0x8640dd1112820e8f:0x8168f3ce4f125463!8m2!3d29.7027778!4d-95.5888889!16s%2Fg%2F1vn18xzb?entry=ttu&g_ep=EgoyMDI2MDIwMS4wIKXMDSoKLDEwMDc5MjA2OUgB"&"UAM%3D") -> https://www.google.com/maps/place/Alief+Neighborhood+Center/@29.7027824,-95.5914638,17z/data=!3m1!4b1!4m6!3m5!1s0x8640dd1112820e8f:0x8168f3ce4f125463!8m2!3d29.7027778!4d-95.5888889!16s%2Fg%2F1vn18xzb?entry=ttu&g_ep=EgoyMDI2MDIwMS4wIKXMDSoKLDEwMDc5MjA2OUgBUAM%3D | Y39: =IFERROR(__xludf.DUMMYFUNCTION("""COMPUTED_VALUE"""),"Houston") -> Houston | Z39: =IFERROR(__xludf.DUMMYFUNCTION("""COMPUTED_VALUE"""),"Alief") -> Alief | AA39: =IFERROR(__xludf.DUMMYFUNCTION("""COMPUTED_VALUE"""),"City of Houston") -> City of Houston | AB39: =IFERROR(__xludf.DUMMYFUNCTION("""COMPUTED_VALUE"""),"Alief") -> Alief
A40: 39 | B40: =IFERROR(__xludf.DUMMYFUNCTION("""COMPUTED_VALUE"""),"[""77007"", ""77008"", ""77009""]") -> ["77007", "77008", "77009"] | C40: =IFERROR(__xludf.DUMMYFUNCTION("""COMPUTED_VALUE"""),"All Saints (SVdP D4)") -> All Saints (SVdP D4) | D40: =IFERROR(__xludf.DUMMYFUNCTION("""COMPUTED_VALUE"""),"1035 Cortlandt Street") -> 1035 Cortlandt Street | F40: =IFERROR(__xludf.DUMMYFUNCTION("""COMPUTED_VALUE"""),"Houston") -> Houston | G40: =IFERROR(__xludf.DUMMYFUNCTION("""COMPUTED_VALUE"""),"TX") -> TX | H40: =IFERROR(__xludf.DUMMYFUNCTION("""COMPUTED_VALUE"""),"77008") -> 77008 | I40: =IFERROR(__xludf.DUMMYFUNCTION("""COMPUTED_VALUE"""),"713-864-8937") -> 713-864-8937 | J40: =IFERROR(__xludf.DUMMYFUNCTION("""COMPUTED_VALUE"""),"29.7895703265306, -95.3953734489796") -> 29.7895703265306, -95.3953734489796 | K40: =IFERROR(__xludf.DUMMYFUNCTION("""COMPUTED_VALUE"""),"{""regular"":[{""days"":[""Mo""],""open"":""09:00"",""close"":""10:30""}]}") -> {"regular":[{"days":["Mo"],"open":"09:00","close":"10:30"}]} | M40: =IFERROR(__xludf.DUMMYFUNCTION("""COMPUTED_VALUE"""),11.0) -> 11 | N40: =IFERROR(__xludf.DUMMYFUNCTION("""COMPUTED_VALUE"""),"Rent") -> Rent | O40: =IFERROR(__xludf.DUMMYFUNCTION("""COMPUTED_VALUE"""),1.0) -> 1 | P40: =IFERROR(__xludf.DUMMYFUNCTION("""COMPUTED_VALUE"""),"ACTIVE") -> ACTIVE | Q40: =IFERROR(__xludf.DUMMYFUNCTION("""COMPUTED_VALUE"""),45758.0) -> 45758 | T40: =IFERROR(__xludf.DUMMYFUNCTION("""COMPUTED_VALUE"""),FALSE) -> FALSE | U40: =IFERROR(__xludf.DUMMYFUNCTION("""COMPUTED_VALUE"""),FALSE) -> FALSE | V40: =IFERROR(__xludf.DUMMYFUNCTION("""COMPUTED_VALUE"""),"https://allsaintsheights.com/svdp") -> https://allsaintsheights.com/svdp | W40: =IFERROR(__xludf.DUMMYFUNCTION("""COMPUTED_VALUE"""),"https://www.google.com/maps/place/All+Saints+Saint+Vincent+de+Paul+Society%E2%80%99s+Food+Pantry/@29.7901633,-95.3980995,17z/data=!3m1!4b1!4m6!3m5!1s0x8640c75f3eb178f5:0xa4944b9b05cc0648!8m2!3d29.7901587!4d-95.3955246!16s%2Fg%2F11rt_jqfzc?entry=ttu&g_ep=E"&"goyMDI1MDEyOS4xIKXMDSoASAFQAw%3D%3D") -> https://www.google.com/maps/place/All+Saints+Saint+Vincent+de+Paul+Society%E2%80%99s+Food+Pantry/@29.7901633,-95.3980995,17z/data=!3m1!4b1!4m6!3m5!1s0x8640c75f3eb178f5:0xa4944b9b05cc0648!8m2!3d29.7901587!4d-95.3955246!16s%2Fg%2F11rt_jqfzc?entry=ttu&g_ep=EgoyMDI1MDEyOS4xIKXMDSoASAFQAw%3D%3D | Y40: =IFERROR(__xludf.DUMMYFUNCTION("""COMPUTED_VALUE"""),"Houston") -> Houston | Z40: =IFERROR(__xludf.DUMMYFUNCTION("""COMPUTED_VALUE"""),"Lazybrook / Timbergrove, Northside, Shady Acres, The Heights, Timbergrove") -> Lazybrook / Timbergrove, Northside, Shady Acres, The Heights, Timbergrove | AA40: =IFERROR(__xludf.DUMMYFUNCTION("""COMPUTED_VALUE"""),"Society of St Vincent de Paul") -> Society of St Vincent de Paul | AB40: =IFERROR(__xludf.DUMMYFUNCTION("""COMPUTED_VALUE"""),"Northside") -> Northside
A41: 40 | B41: =IFERROR(__xludf.DUMMYFUNCTION("""COMPUTED_VALUE"""),"[""77007"", ""77008"", ""77009""]") -> ["77007", "77008", "77009"] | C41: =IFERROR(__xludf.DUMMYFUNCTION("""COMPUTED_VALUE"""),"All Saints (SVdP D4)") -> All Saints (SVdP D4) | D41: =IFERROR(__xludf.DUMMYFUNCTION("""COMPUTED_VALUE"""),"1035 Cortlandt Street") -> 1035 Cortlandt Street | F41: =IFERROR(__xludf.DUMMYFUNCTION("""COMPUTED_VALUE"""),"Houston") -> Houston | G41: =IFERROR(__xludf.DUMMYFUNCTION("""COMPUTED_VALUE"""),"TX") -> TX | H41: =IFERROR(__xludf.DUMMYFUNCTION("""COMPUTED_VALUE"""),"77008") -> 77008 | I41: =IFERROR(__xludf.DUMMYFUNCTION("""COMPUTED_VALUE"""),"713-864-8937") -> 713-864-8937 | J41: =IFERROR(__xludf.DUMMYFUNCTION("""COMPUTED_VALUE"""),"29.7895703265306, -95.3953734489796") -> 29.7895703265306, -95.3953734489796 | K41: =IFERROR(__xludf.DUMMYFUNCTION("""COMPUTED_VALUE"""),"{""regular"":[{""days"":[""Mo""],""open"":""09:00"",""close"":""10:30""}]}") -> {"regular":[{"days":["Mo"],"open":"09:00","close":"10:30"}]} | M41: =IFERROR(__xludf.DUMMYFUNCTION("""COMPUTED_VALUE"""),12.0) -> 12 | N41: =IFERROR(__xludf.DUMMYFUNCTION("""COMPUTED_VALUE"""),"Utilities") -> Utilities | O41: =IFERROR(__xludf.DUMMYFUNCTION("""COMPUTED_VALUE"""),1.0) -> 1 | P41: =IFERROR(__xludf.DUMMYFUNCTION("""COMPUTED_VALUE"""),"ACTIVE") -> ACTIVE | Q41: =IFERROR(__xludf.DUMMYFUNCTION("""COMPUTED_VALUE"""),45758.0) -> 45758 | T41: =IFERROR(__xludf.DUMMYFUNCTION("""COMPUTED_VALUE"""),FALSE) -> FALSE | U41: =IFERROR(__xludf.DUMMYFUNCTION("""COMPUTED_VALUE"""),FALSE) -> FALSE | V41: =IFERROR(__xludf.DUMMYFUNCTION("""COMPUTED_VALUE"""),"https://allsaintsheights.com/svdp") -> https://allsaintsheights.com/svdp | W41: =IFERROR(__xludf.DUMMYFUNCTION("""COMPUTED_VALUE"""),"https://www.google.com/maps/place/All+Saints+Saint+Vincent+de+Paul+Society%E2%80%99s+Food+Pantry/@29.7901633,-95.3980995,17z/data=!3m1!4b1!4m6!3m5!1s0x8640c75f3eb178f5:0xa4944b9b05cc0648!8m2!3d29.7901587!4d-95.3955246!16s%2Fg%2F11rt_jqfzc?entry=ttu&g_ep=E"&"goyMDI1MDEyOS4xIKXMDSoASAFQAw%3D%3D") -> https://www.google.com/maps/place/All+Saints+Saint+Vincent+de+Paul+Society%E2%80%99s+Food+Pantry/@29.7901633,-95.3980995,17z/data=!3m1!4b1!4m6!3m5!1s0x8640c75f3eb178f5:0xa4944b9b05cc0648!8m2!3d29.7901587!4d-95.3955246!16s%2Fg%2F11rt_jqfzc?entry=ttu&g_ep=EgoyMDI1MDEyOS4xIKXMDSoASAFQAw%3D%3D | Y41: =IFERROR(__xludf.DUMMYFUNCTION("""COMPUTED_VALUE"""),"Houston") -> Houston | Z41: =IFERROR(__xludf.DUMMYFUNCTION("""COMPUTED_VALUE"""),"Lazybrook / Timbergrove, Northside, Shady Acres, The Heights, Timbergrove") -> Lazybrook / Timbergrove, Northside, Shady Acres, The Heights, Timbergrove | AA41: =IFERROR(__xludf.DUMMYFUNCTION("""COMPUTED_VALUE"""),"Society of St Vincent de Paul") -> Society of St Vincent de Paul | AB41: =IFERROR(__xludf.DUMMYFUNCTION("""COMPUTED_VALUE"""),"Northside") -> Northside
A42: 41 | B42: =IFERROR(__xludf.DUMMYFUNCTION("""COMPUTED_VALUE"""),"[""77007"", ""77008"", ""77009""]") -> ["77007", "77008", "77009"] | C42: =IFERROR(__xludf.DUMMYFUNCTION("""COMPUTED_VALUE"""),"All Saints (SVdP D4)") -> All Saints (SVdP D4) | D42: =IFERROR(__xludf.DUMMYFUNCTION("""COMPUTED_VALUE"""),"1035 Cortlandt Street") -> 1035 Cortlandt Street | F42: =IFERROR(__xludf.DUMMYFUNCTION("""COMPUTED_VALUE"""),"Houston") -> Houston | G42: =IFERROR(__xludf.DUMMYFUNCTION("""COMPUTED_VALUE"""),"TX") -> TX | H42: =IFERROR(__xludf.DUMMYFUNCTION("""COMPUTED_VALUE"""),"77008") -> 77008 | I42: =IFERROR(__xludf.DUMMYFUNCTION("""COMPUTED_VALUE"""),"713-864-8937") -> 713-864-8937 | J42: =IFERROR(__xludf.DUMMYFUNCTION("""COMPUTED_VALUE"""),"29.7895703265306, -95.3953734489796") -> 29.7895703265306, -95.3953734489796 | K42: =IFERROR(__xludf.DUMMYFUNCTION("""COMPUTED_VALUE"""),"{""regular"":[{""days"":[""Mo"",""Tu"",""We"",""Th""],""open"":""09:00"",""close"":""10:30""},{""days"":[""We""],""open"":""18:00"",""close"":""19:30""}]}") -> {"regular":[{"days":["Mo","Tu","We","Th"],"open":"09:00","close":"10:30"},{"days":["We"],"open":"18:00","close":"19:30"}]} | M42: =IFERROR(__xludf.DUMMYFUNCTION("""COMPUTED_VALUE"""),13.0) -> 13 | N42: =IFERROR(__xludf.DUMMYFUNCTION("""COMPUTED_VALUE"""),"Food") -> Food | O42: =IFERROR(__xludf.DUMMYFUNCTION("""COMPUTED_VALUE"""),1.0) -> 1 | P42: =IFERROR(__xludf.DUMMYFUNCTION("""COMPUTED_VALUE"""),"ACTIVE") -> ACTIVE | Q42: =IFERROR(__xludf.DUMMYFUNCTION("""COMPUTED_VALUE"""),45758.0) -> 45758 | S42: =IFERROR(__xludf.DUMMYFUNCTION("""COMPUTED_VALUE"""),"Food delivery available for those unable to physically make it to the pantry.") -> Food delivery available for those unable to physically make it to the pantry. | T42: =IFERROR(__xludf.DUMMYFUNCTION("""COMPUTED_VALUE"""),FALSE) -> FALSE | U42: =IFERROR(__xludf.DUMMYFUNCTION("""COMPUTED_VALUE"""),FALSE) -> FALSE | V42: =IFERROR(__xludf.DUMMYFUNCTION("""COMPUTED_VALUE"""),"https://allsaintsheights.com/svdp") -> https://allsaintsheights.com/svdp | W42: =IFERROR(__xludf.DUMMYFUNCTION("""COMPUTED_VALUE"""),"https://www.google.com/maps/place/All+Saints+Saint+Vincent+de+Paul+Society%E2%80%99s+Food+Pantry/@29.7901633,-95.3980995,17z/data=!3m1!4b1!4m6!3m5!1s0x8640c75f3eb178f5:0xa4944b9b05cc0648!8m2!3d29.7901587!4d-95.3955246!16s%2Fg%2F11rt_jqfzc?entry=ttu&g_ep=E"&"goyMDI1MDEyOS4xIKXMDSoASAFQAw%3D%3D") -> https://www.google.com/maps/place/All+Saints+Saint+Vincent+de+Paul+Society%E2%80%99s+Food+Pantry/@29.7901633,-95.3980995,17z/data=!3m1!4b1!4m6!3m5!1s0x8640c75f3eb178f5:0xa4944b9b05cc0648!8m2!3d29.7901587!4d-95.3955246!16s%2Fg%2F11rt_jqfzc?entry=ttu&g_ep=EgoyMDI1MDEyOS4xIKXMDSoASAFQAw%3D%3D | Y42: =IFERROR(__xludf.DUMMYFUNCTION("""COMPUTED_VALUE"""),"Houston") -> Houston | Z42: =IFERROR(__xludf.DUMMYFUNCTION("""COMPUTED_VALUE"""),"Lazybrook / Timbergrove, Northside, Shady Acres, The Heights, Timbergrove") -> Lazybrook / Timbergrove, Northside, Shady Acres, The Heights, Timbergrove | AA42: =IFERROR(__xludf.DUMMYFUNCTION("""COMPUTED_VALUE"""),"Society of St Vincent de Paul") -> Society of St Vincent de Paul | AB42: =IFERROR(__xludf.DUMMYFUNCTION("""COMPUTED_VALUE"""),"Northside") -> Northside
A43: 42 | B43: =IFERROR(__xludf.DUMMYFUNCTION("""COMPUTED_VALUE"""),"[""99999""]") -> ["99999"] | C43: =IFERROR(__xludf.DUMMYFUNCTION("""COMPUTED_VALUE"""),"Allyson Whitney Foundation") -> Allyson Whitney Foundation | D43: =IFERROR(__xludf.DUMMYFUNCTION("""COMPUTED_VALUE"""),"12221 Towne Lake Drive") -> 12221 Towne Lake Drive | E43: =IFERROR(__xludf.DUMMYFUNCTION("""COMPUTED_VALUE"""),"Suite A158") -> Suite A158 | F43: =IFERROR(__xludf.DUMMYFUNCTION("""COMPUTED_VALUE"""),"Fort Myers") -> Fort Myers | G43: =IFERROR(__xludf.DUMMYFUNCTION("""COMPUTED_VALUE"""),"FL") -> FL | H43: =IFERROR(__xludf.DUMMYFUNCTION("""COMPUTED_VALUE"""),"33913") -> 33913 | J43: =IFERROR(__xludf.DUMMYFUNCTION("""COMPUTED_VALUE"""),"26.566374990656055, -81.74982919680966") -> 26.566374990656055, -81.74982919680966 | L43: =IFERROR(__xludf.DUMMYFUNCTION("""COMPUTED_VALUE"""),"Apply online") -> Apply online | M43: =IFERROR(__xludf.DUMMYFUNCTION("""COMPUTED_VALUE"""),36.0) -> 36 | N43: =IFERROR(__xludf.DUMMYFUNCTION("""COMPUTED_VALUE"""),"Medical - Bill Payment") -> Medical - Bill Payment | O43: =IFERROR(__xludf.DUMMYFUNCTION("""COMPUTED_VALUE"""),1.0) -> 1 | P43: =IFERROR(__xludf.DUMMYFUNCTION("""COMPUTED_VALUE"""),"ACTIVE") -> ACTIVE | Q43: =IFERROR(__xludf.DUMMYFUNCTION("""COMPUTED_VALUE"""),45816.0) -> 45816 | R43: =IFERROR(__xludf.DUMMYFUNCTION("""COMPUTED_VALUE"""),"Verified online") -> Verified online | S43: =IFERROR(__xludf.DUMMYFUNCTION("""COMPUTED_VALUE"""),"Provides grants for young adults (between 16 and 36 years old) diagnosed with rare cancer. US Citizens/Permanent Residents. Applications are accepted online only are are open four times a year. Please check website for key dates and deadlines. Applicatio"&"ns initiated by doctor's office or patient navigator.") -> Provides grants for young adults (between 16 and 36 years old) diagnosed with rare cancer. US Citizens/Permanent Residents. Applications are accepted online only are are open four times a year. Please check website for key dates and deadlines. Applications initiated by doctor's office or patient navigator. | T43: =IFERROR(__xludf.DUMMYFUNCTION("""COMPUTED_VALUE"""),FALSE) -> FALSE | U43: =IFERROR(__xludf.DUMMYFUNCTION("""COMPUTED_VALUE"""),FALSE) -> FALSE | V43: =IFERROR(__xludf.DUMMYFUNCTION("""COMPUTED_VALUE"""),"https://allysonwhitney.org/") -> https://allysonwhitney.org/ | Y43: =IFERROR(__xludf.DUMMYFUNCTION("""COMPUTED_VALUE"""),"Fort Myers") -> Fort Myers | Z43: =IFERROR(__xludf.DUMMYFUNCTION("""COMPUTED_VALUE"""),"Gateway") -> Gateway | AA43: =IFERROR(__xludf.DUMMYFUNCTION("""COMPUTED_VALUE"""),"Allyson Whitney Foundation") -> Allyson Whitney Foundation | AB43: =IFERROR(__xludf.DUMMYFUNCTION("""COMPUTED_VALUE"""),"Gateway") -> Gateway
A44: 43 | B44: =IFERROR(__xludf.DUMMYFUNCTION("""COMPUTED_VALUE"""),"[""99999""]") -> ["99999"] | C44: =IFERROR(__xludf.DUMMYFUNCTION("""COMPUTED_VALUE"""),"American Kidney Fund") -> American Kidney Fund | D44: =IFERROR(__xludf.DUMMYFUNCTION("""COMPUTED_VALUE"""),"11921 Rockville Pike") -> 11921 Rockville Pike | E44: =IFERROR(__xludf.DUMMYFUNCTION("""COMPUTED_VALUE"""),"Suite 300") -> Suite 300 | F44: =IFERROR(__xludf.DUMMYFUNCTION("""COMPUTED_VALUE"""),"Rockville") -> Rockville | G44: =IFERROR(__xludf.DUMMYFUNCTION("""COMPUTED_VALUE"""),"MD") -> MD | H44: =IFERROR(__xludf.DUMMYFUNCTION("""COMPUTED_VALUE"""),"20852") -> 20852 | I44: =IFERROR(__xludf.DUMMYFUNCTION("""COMPUTED_VALUE"""),"800-638-8299") -> 800-638-8299 | J44: =IFERROR(__xludf.DUMMYFUNCTION("""COMPUTED_VALUE"""),"39.05221372094748, -77.11477665671595") -> 39.05221372094748, -77.11477665671595 | K44: =IFERROR(__xludf.DUMMYFUNCTION("""COMPUTED_VALUE"""),"{""regular"":[{""days"":[""Mo"",""Tu"",""We"",""Th"",""Fr""],""open"":""09:00"",""close"":""17:00""}]}") -> {"regular":[{"days":["Mo","Tu","We","Th","Fr"],"open":"09:00","close":"17:00"}]} | L44: =IFERROR(__xludf.DUMMYFUNCTION("""COMPUTED_VALUE"""),"Apply online") -> Apply online | M44: =IFERROR(__xludf.DUMMYFUNCTION("""COMPUTED_VALUE"""),36.0) -> 36 | N44: =IFERROR(__xludf.DUMMYFUNCTION("""COMPUTED_VALUE"""),"Medical - Bill Payment") -> Medical - Bill Payment | O44: =IFERROR(__xludf.DUMMYFUNCTION("""COMPUTED_VALUE"""),1.0) -> 1 | P44: =IFERROR(__xludf.DUMMYFUNCTION("""COMPUTED_VALUE"""),"ACTIVE") -> ACTIVE | R44: =IFERROR(__xludf.DUMMYFUNCTION("""COMPUTED_VALUE"""),"Verified online") -> Verified online | S44: =IFERROR(__xludf.DUMMYFUNCTION("""COMPUTED_VALUE"""),"Need-based financial assistance programs help U.S. kidney patients with health insurance premiums, transportation costs and prescription medications. Check eligibility and apply online. A charitable patient assistance foundation.") -> Need-based financial assistance programs help U.S. kidney patients with health insurance premiums, transportation costs and prescription medications. Check eligibility and apply online. A charitable patient assistance foundation. | T44: =IFERROR(__xludf.DUMMYFUNCTION("""COMPUTED_VALUE"""),FALSE) -> FALSE | U44: =IFERROR(__xludf.DUMMYFUNCTION("""COMPUTED_VALUE"""),FALSE) -> FALSE | V44: =IFERROR(__xludf.DUMMYFUNCTION("""COMPUTED_VALUE"""),"https://www.kidneyfund.org/get-assistance") -> https://www.kidneyfund.org/get-assistance | W44: =IFERROR(__xludf.DUMMYFUNCTION("""COMPUTED_VALUE"""),"https://www.google.com/maps/place/American+Kidney+Fund/@39.0518139,-77.1196798,16z/data=!3m2!4b1!5s0x89b7cc31c5ed337d:0x5a6d370d8c2bc86f!4m6!3m5!1s0x89b7cd246949ae89:0x563a057bb9f021d0!8m2!3d39.051814!4d-77.1148035!16s%2Fg%2F11vszk1mcb?entry=ttu&g_ep=Egoy"&"MDI2MDEyMC4wIKXMDSoKLDEwMDc5MjA2OUgBUAM%3D") -> https://www.google.com/maps/place/American+Kidney+Fund/@39.0518139,-77.1196798,16z/data=!3m2!4b1!5s0x89b7cc31c5ed337d:0x5a6d370d8c2bc86f!4m6!3m5!1s0x89b7cd246949ae89:0x563a057bb9f021d0!8m2!3d39.051814!4d-77.1148035!16s%2Fg%2F11vszk1mcb?entry=ttu&g_ep=EgoyMDI2MDEyMC4wIKXMDSoKLDEwMDc5MjA2OUgBUAM%3D | Y44: =IFERROR(__xludf.DUMMYFUNCTION("""COMPUTED_VALUE"""),"Rockville") -> Rockville | Z44: =IFERROR(__xludf.DUMMYFUNCTION("""COMPUTED_VALUE"""),"North Bethesda") -> North Bethesda | AA44: =IFERROR(__xludf.DUMMYFUNCTION("""COMPUTED_VALUE"""),"American Kidney Fund") -> American Kidney Fund | AB44: =IFERROR(__xludf.DUMMYFUNCTION("""COMPUTED_VALUE"""),"North Bethesda") -> North Bethesda
A45: 44 | B45: =IFERROR(__xludf.DUMMYFUNCTION("""COMPUTED_VALUE"""),"[""99999""]") -> ["99999"] | C45: =IFERROR(__xludf.DUMMYFUNCTION("""COMPUTED_VALUE"""),"American Red Cross") -> American Red Cross | D45: =IFERROR(__xludf.DUMMYFUNCTION("""COMPUTED_VALUE"""),"2700 Southwest Fwy") -> 2700 Southwest Fwy | F45: =IFERROR(__xludf.DUMMYFUNCTION("""COMPUTED_VALUE"""),"Houston") -> Houston | G45: =IFERROR(__xludf.DUMMYFUNCTION("""COMPUTED_VALUE"""),"TX") -> TX | H45: =IFERROR(__xludf.DUMMYFUNCTION("""COMPUTED_VALUE"""),"77098") -> 77098 | I45: =IFERROR(__xludf.DUMMYFUNCTION("""COMPUTED_VALUE"""),"713-526-8300") -> 713-526-8300 | J45: =IFERROR(__xludf.DUMMYFUNCTION("""COMPUTED_VALUE"""),"29.7301392368421, -95.4211873421053") -> 29.7301392368421, -95.4211873421053 | M45: =IFERROR(__xludf.DUMMYFUNCTION("""COMPUTED_VALUE"""),12.0) -> 12 | N45: =IFERROR(__xludf.DUMMYFUNCTION("""COMPUTED_VALUE"""),"Utilities") -> Utilities | O45: =IFERROR(__xludf.DUMMYFUNCTION("""COMPUTED_VALUE"""),2.0) -> 2 | P45: =IFERROR(__xludf.DUMMYFUNCTION("""COMPUTED_VALUE"""),"LIMITED") -> LIMITED | R45: =IFERROR(__xludf.DUMMYFUNCTION("""COMPUTED_VALUE"""),"For disaster victims and military families only.") -> For disaster victims and military families only. | T45: =IFERROR(__xludf.DUMMYFUNCTION("""COMPUTED_VALUE"""),FALSE) -> FALSE | U45: =IFERROR(__xludf.DUMMYFUNCTION("""COMPUTED_VALUE"""),FALSE) -> FALSE | V45: =IFERROR(__xludf.DUMMYFUNCTION("""COMPUTED_VALUE"""),"https://www.redcross.org/local/texas/gulf-coast/about-us/locations/houston.html?CID=organic_gmb_listings") -> https://www.redcross.org/local/texas/gulf-coast/about-us/locations/houston.html?CID=organic_gmb_listings | W45: =IFERROR(__xludf.DUMMYFUNCTION("""COMPUTED_VALUE"""),"https://maps.google.com/?q=American%20Red%20Cross%202700%20Southwest%20Fwy%20Houston%20TX%2077098") -> https://maps.google.com/?q=American%20Red%20Cross%202700%20Southwest%20Fwy%20Houston%20TX%2077098 | Y45: =IFERROR(__xludf.DUMMYFUNCTION("""COMPUTED_VALUE"""),"Houston") -> Houston | Z45: =IFERROR(__xludf.DUMMYFUNCTION("""COMPUTED_VALUE"""),"Greenway / Upper Kirby Area, River Oaks, Upper Kirby") -> Greenway / Upper Kirby Area, River Oaks, Upper Kirby | AA45: =IFERROR(__xludf.DUMMYFUNCTION("""COMPUTED_VALUE"""),"American Red Cross") -> American Red Cross | AB45: =IFERROR(__xludf.DUMMYFUNCTION("""COMPUTED_VALUE"""),"Greenway / Upper Kirby Area") -> Greenway / Upper Kirby Area
A46: 45 | B46: =IFERROR(__xludf.DUMMYFUNCTION("""COMPUTED_VALUE"""),"[""99999""]") -> ["99999"] | C46: =IFERROR(__xludf.DUMMYFUNCTION("""COMPUTED_VALUE"""),"American Red Cross") -> American Red Cross | D46: =IFERROR(__xludf.DUMMYFUNCTION("""COMPUTED_VALUE"""),"2700 Southwest Fwy") -> 2700 Southwest Fwy | F46: =IFERROR(__xludf.DUMMYFUNCTION("""COMPUTED_VALUE"""),"Houston") -> Houston | G46: =IFERROR(__xludf.DUMMYFUNCTION("""COMPUTED_VALUE"""),"TX") -> TX | H46: =IFERROR(__xludf.DUMMYFUNCTION("""COMPUTED_VALUE"""),"77098") -> 77098 | I46: =IFERROR(__xludf.DUMMYFUNCTION("""COMPUTED_VALUE"""),"713-526-8300") -> 713-526-8300 | J46: =IFERROR(__xludf.DUMMYFUNCTION("""COMPUTED_VALUE"""),"29.7301392368421, -95.4211873421053") -> 29.7301392368421, -95.4211873421053 | M46: =IFERROR(__xludf.DUMMYFUNCTION("""COMPUTED_VALUE"""),13.0) -> 13 | N46: =IFERROR(__xludf.DUMMYFUNCTION("""COMPUTED_VALUE"""),"Food") -> Food | O46: =IFERROR(__xludf.DUMMYFUNCTION("""COMPUTED_VALUE"""),2.0) -> 2 | P46: =IFERROR(__xludf.DUMMYFUNCTION("""COMPUTED_VALUE"""),"LIMITED") -> LIMITED | R46: =IFERROR(__xludf.DUMMYFUNCTION("""COMPUTED_VALUE"""),"For disaster victims and military families only.") -> For disaster victims and military families only. | T46: =IFERROR(__xludf.DUMMYFUNCTION("""COMPUTED_VALUE"""),FALSE) -> FALSE | U46: =IFERROR(__xludf.DUMMYFUNCTION("""COMPUTED_VALUE"""),FALSE) -> FALSE | V46: =IFERROR(__xludf.DUMMYFUNCTION("""COMPUTED_VALUE"""),"https://www.redcross.org/local/texas/gulf-coast/about-us/locations/houston.html?CID=organic_gmb_listings") -> https://www.redcross.org/local/texas/gulf-coast/about-us/locations/houston.html?CID=organic_gmb_listings | W46: =IFERROR(__xludf.DUMMYFUNCTION("""COMPUTED_VALUE"""),"https://maps.google.com/?q=American%20Red%20Cross%202700%20Southwest%20Fwy%20Houston%20TX%2077098") -> https://maps.google.com/?q=American%20Red%20Cross%202700%20Southwest%20Fwy%20Houston%20TX%2077098 | Y46: =IFERROR(__xludf.DUMMYFUNCTION("""COMPUTED_VALUE"""),"Houston") -> Houston | Z46: =IFERROR(__xludf.DUMMYFUNCTION("""COMPUTED_VALUE"""),"Greenway / Upper Kirby Area, River Oaks, Upper Kirby") -> Greenway / Upper Kirby Area, River Oaks, Upper Kirby | AA46: =IFERROR(__xludf.DUMMYFUNCTION("""COMPUTED_VALUE"""),"American Red Cross") -> American Red Cross | AB46: =IFERROR(__xludf.DUMMYFUNCTION("""COMPUTED_VALUE"""),"Greenway / Upper Kirby Area") -> Greenway / Upper Kirby Area
A47: 46 | B47: =IFERROR(__xludf.DUMMYFUNCTION("""COMPUTED_VALUE"""),"[""99999""]") -> ["99999"] | C47: =IFERROR(__xludf.DUMMYFUNCTION("""COMPUTED_VALUE"""),"American Red Cross") -> American Red Cross | D47: =IFERROR(__xludf.DUMMYFUNCTION("""COMPUTED_VALUE"""),"2700 Southwest Fwy") -> 2700 Southwest Fwy | F47: =IFERROR(__xludf.DUMMYFUNCTION("""COMPUTED_VALUE"""),"Houston") -> Houston | G47: =IFERROR(__xludf.DUMMYFUNCTION("""COMPUTED_VALUE"""),"TX") -> TX | H47: =IFERROR(__xludf.DUMMYFUNCTION("""COMPUTED_VALUE"""),"77098") -> 77098 | I47: =IFERROR(__xludf.DUMMYFUNCTION("""COMPUTED_VALUE"""),"713-526-8300") -> 713-526-8300 | J47: =IFERROR(__xludf.DUMMYFUNCTION("""COMPUTED_VALUE"""),"29.7301392368421, -95.4211873421053") -> 29.7301392368421, -95.4211873421053 | M47: =IFERROR(__xludf.DUMMYFUNCTION("""COMPUTED_VALUE"""),14.0) -> 14 | N47: =IFERROR(__xludf.DUMMYFUNCTION("""COMPUTED_VALUE"""),"Clothing") -> Clothing | O47: =IFERROR(__xludf.DUMMYFUNCTION("""COMPUTED_VALUE"""),2.0) -> 2 | P47: =IFERROR(__xludf.DUMMYFUNCTION("""COMPUTED_VALUE"""),"LIMITED") -> LIMITED | R47: =IFERROR(__xludf.DUMMYFUNCTION("""COMPUTED_VALUE"""),"For disaster victims and military families only.") -> For disaster victims and military families only. | T47: =IFERROR(__xludf.DUMMYFUNCTION("""COMPUTED_VALUE"""),FALSE) -> FALSE | U47: =IFERROR(__xludf.DUMMYFUNCTION("""COMPUTED_VALUE"""),FALSE) -> FALSE | V47: =IFERROR(__xludf.DUMMYFUNCTION("""COMPUTED_VALUE"""),"https://www.redcross.org/local/texas/gulf-coast/about-us/locations/houston.html?CID=organic_gmb_listings") -> https://www.redcross.org/local/texas/gulf-coast/about-us/locations/houston.html?CID=organic_gmb_listings | W47: =IFERROR(__xludf.DUMMYFUNCTION("""COMPUTED_VALUE"""),"https://maps.google.com/?q=American%20Red%20Cross%202700%20Southwest%20Fwy%20Houston%20TX%2077098") -> https://maps.google.com/?q=American%20Red%20Cross%202700%20Southwest%20Fwy%20Houston%20TX%2077098 | Y47: =IFERROR(__xludf.DUMMYFUNCTION("""COMPUTED_VALUE"""),"Houston") -> Houston | Z47: =IFERROR(__xludf.DUMMYFUNCTION("""COMPUTED_VALUE"""),"Greenway / Upper Kirby Area, River Oaks, Upper Kirby") -> Greenway / Upper Kirby Area, River Oaks, Upper Kirby | AA47: =IFERROR(__xludf.DUMMYFUNCTION("""COMPUTED_VALUE"""),"American Red Cross") -> American Red Cross | AB47: =IFERROR(__xludf.DUMMYFUNCTION("""COMPUTED_VALUE"""),"Greenway / Upper Kirby Area") -> Greenway / Upper Kirby Area
A48: 47 | B48: =IFERROR(__xludf.DUMMYFUNCTION("""COMPUTED_VALUE"""),"[""99999""]") -> ["99999"] | C48: =IFERROR(__xludf.DUMMYFUNCTION("""COMPUTED_VALUE"""),"Anchor Point") -> Anchor Point | D48: =IFERROR(__xludf.DUMMYFUNCTION("""COMPUTED_VALUE"""),"103 Davis Road, Suite B") -> 103 Davis Road, Suite B | F48: =IFERROR(__xludf.DUMMYFUNCTION("""COMPUTED_VALUE"""),"League City") -> League City | G48: =IFERROR(__xludf.DUMMYFUNCTION("""COMPUTED_VALUE"""),"TX") -> TX | H48: =IFERROR(__xludf.DUMMYFUNCTION("""COMPUTED_VALUE"""),"77573") -> 77573 | I48: =IFERROR(__xludf.DUMMYFUNCTION("""COMPUTED_VALUE"""),"832-632-1221") -> 832-632-1221 | J48: =IFERROR(__xludf.DUMMYFUNCTION("""COMPUTED_VALUE"""),"29.5294698851117, -95.0726858411499") -> 29.5294698851117, -95.0726858411499 | K48: =IFERROR(__xludf.DUMMYFUNCTION("""COMPUTED_VALUE"""),"{""regular"":[{""days"":[""Mo"",""Tu"",""We"",""Th"",""Fr""],""open"":null,""close"":null}]}") -> {"regular":[{"days":["Mo","Tu","We","Th","Fr"],"open":null,"close":null}]} | M48: =IFERROR(__xludf.DUMMYFUNCTION("""COMPUTED_VALUE"""),65.0) -> 65 | N48: =IFERROR(__xludf.DUMMYFUNCTION("""COMPUTED_VALUE"""),"Other") -> Other | O48: =IFERROR(__xludf.DUMMYFUNCTION("""COMPUTED_VALUE"""),4.0) -> 4 | P48: =IFERROR(__xludf.DUMMYFUNCTION("""COMPUTED_VALUE"""),"CLOSED") -> CLOSED | Q48: =IFERROR(__xludf.DUMMYFUNCTION("""COMPUTED_VALUE"""),45948.0) -> 45948 | R48: =IFERROR(__xludf.DUMMYFUNCTION("""COMPUTED_VALUE"""),"Appears to be a conduit for for-profit clinic") -> Appears to be a conduit for for-profit clinic | T48: =IFERROR(__xludf.DUMMYFUNCTION("""COMPUTED_VALUE"""),FALSE) -> FALSE | U48: =IFERROR(__xludf.DUMMYFUNCTION("""COMPUTED_VALUE"""),FALSE) -> FALSE | V48: =IFERROR(__xludf.DUMMYFUNCTION("""COMPUTED_VALUE"""),"https://anchorpoint.us/") -> https://anchorpoint.us/ | W48: =IFERROR(__xludf.DUMMYFUNCTION("""COMPUTED_VALUE"""),"https://www.google.com/maps/place/Anchor+Point/@29.529608,-95.0759713,16z/data=!3m1!4b1!4m6!3m5!1s0x86409d427a7055f7:0x69975b23d0d7abe5!8m2!3d29.529608!4d-95.073391!16s%2Fg%2F1tlkcrn3?entry=ttu&g_ep=EgoyMDI1MDQwOS4wIKXMDSoASAFQAw%3D%3D") -> https://www.google.com/maps/place/Anchor+Point/@29.529608,-95.0759713,16z/data=!3m1!4b1!4m6!3m5!1s0x86409d427a7055f7:0x69975b23d0d7abe5!8m2!3d29.529608!4d-95.073391!16s%2Fg%2F1tlkcrn3?entry=ttu&g_ep=EgoyMDI1MDQwOS4wIKXMDSoASAFQAw%3D%3D | Y48: =IFERROR(__xludf.DUMMYFUNCTION("""COMPUTED_VALUE"""),"League City") -> League City | Z48: =IFERROR(__xludf.DUMMYFUNCTION("""COMPUTED_VALUE"""),"League City, South Shore Harbour, Victory Lakes") -> League City, South Shore Harbour, Victory Lakes | AA48: =IFERROR(__xludf.DUMMYFUNCTION("""COMPUTED_VALUE"""),"Anchor Point") -> Anchor Point | AB48: =IFERROR(__xludf.DUMMYFUNCTION("""COMPUTED_VALUE"""),"League City") -> League City
A49: 48 | B49: =IFERROR(__xludf.DUMMYFUNCTION("""COMPUTED_VALUE"""),"[""99999""]") -> ["99999"] | C49: =IFERROR(__xludf.DUMMYFUNCTION("""COMPUTED_VALUE"""),"Angela House") -> Angela House | D49: =IFERROR(__xludf.DUMMYFUNCTION("""COMPUTED_VALUE"""),"6725 Reed Road") -> 6725 Reed Road | F49: =IFERROR(__xludf.DUMMYFUNCTION("""COMPUTED_VALUE"""),"Houston") -> Houston | G49: =IFERROR(__xludf.DUMMYFUNCTION("""COMPUTED_VALUE"""),"TX") -> TX | H49: =IFERROR(__xludf.DUMMYFUNCTION("""COMPUTED_VALUE"""),"77087") -> 77087 | I49: =IFERROR(__xludf.DUMMYFUNCTION("""COMPUTED_VALUE"""),"281-445-9696") -> 281-445-9696 | J49: =IFERROR(__xludf.DUMMYFUNCTION("""COMPUTED_VALUE"""),"29.6610695260382, -95.3082044659209") -> 29.6610695260382, -95.3082044659209 | K49: =IFERROR(__xludf.DUMMYFUNCTION("""COMPUTED_VALUE"""),"{""regular"":[{""days"":[""Mo"",""Tu"",""We"",""Th"",""Fr""],""open"":null,""close"":null}]}") -> {"regular":[{"days":["Mo","Tu","We","Th","Fr"],"open":null,"close":null}]} | M49: =IFERROR(__xludf.DUMMYFUNCTION("""COMPUTED_VALUE"""),24.0) -> 24 | N49: =IFERROR(__xludf.DUMMYFUNCTION("""COMPUTED_VALUE"""),"Housing") -> Housing | O49: =IFERROR(__xludf.DUMMYFUNCTION("""COMPUTED_VALUE"""),1.0) -> 1 | P49: =IFERROR(__xludf.DUMMYFUNCTION("""COMPUTED_VALUE"""),"ACTIVE") -> ACTIVE | Q49: =IFERROR(__xludf.DUMMYFUNCTION("""COMPUTED_VALUE"""),45761.0) -> 45761 | R49: =IFERROR(__xludf.DUMMYFUNCTION("""COMPUTED_VALUE"""),"SVdP Church Help for Moms Ministry") -> SVdP Church Help for Moms Ministry | S49: =IFERROR(__xludf.DUMMYFUNCTION("""COMPUTED_VALUE"""),"Transitional housing for women currently incarcerated, on probation or on parole. Shelter") -> Transitional housing for women currently incarcerated, on probation or on parole. Shelter | T49: =IFERROR(__xludf.DUMMYFUNCTION("""COMPUTED_VALUE"""),FALSE) -> FALSE | U49: =IFERROR(__xludf.DUMMYFUNCTION("""COMPUTED_VALUE"""),FALSE) -> FALSE | V49: =IFERROR(__xludf.DUMMYFUNCTION("""COMPUTED_VALUE"""),"https://angelahouse.org/") -> https://angelahouse.org/ | W49: =IFERROR(__xludf.DUMMYFUNCTION("""COMPUTED_VALUE"""),"https://www.google.com/maps/place/Angela+House/@29.6622836,-95.3099262,17z/data=!3m1!4b1!4m6!3m5!1s0x8640c826aaaaaaab:0x127be3a1fd2185bb!8m2!3d29.6622836!4d-95.3073513!16s%2Fg%2F12642tldr?entry=ttu&g_ep=EgoyMDI1MDQwOS4wIKXMDSoASAFQAw%3D%3D") -> https://www.google.com/maps/place/Angela+House/@29.6622836,-95.3099262,17z/data=!3m1!4b1!4m6!3m5!1s0x8640c826aaaaaaab:0x127be3a1fd2185bb!8m2!3d29.6622836!4d-95.3073513!16s%2Fg%2F12642tldr?entry=ttu&g_ep=EgoyMDI1MDQwOS4wIKXMDSoASAFQAw%3D%3D | Y49: =IFERROR(__xludf.DUMMYFUNCTION("""COMPUTED_VALUE"""),"Houston") -> Houston | Z49: =IFERROR(__xludf.DUMMYFUNCTION("""COMPUTED_VALUE"""),"Gulfgate, Gulfgate Riverview / Pine Valley, Pine Valley, Southeast Houston") -> Gulfgate, Gulfgate Riverview / Pine Valley, Pine Valley, Southeast Houston | AA49: =IFERROR(__xludf.DUMMYFUNCTION("""COMPUTED_VALUE"""),"Angela House") -> Angela House | AB49: =IFERROR(__xludf.DUMMYFUNCTION("""COMPUTED_VALUE"""),"Southeast Houston") -> Southeast Houston
A50: 49 | B50: =IFERROR(__xludf.DUMMYFUNCTION("""COMPUTED_VALUE"""),"[""99999""]") -> ["99999"] | C50: =IFERROR(__xludf.DUMMYFUNCTION("""COMPUTED_VALUE"""),"Annunciation Maternity Home") -> Annunciation Maternity Home | D50: =IFERROR(__xludf.DUMMYFUNCTION("""COMPUTED_VALUE"""),"3610 Shell Road") -> 3610 Shell Road | F50: =IFERROR(__xludf.DUMMYFUNCTION("""COMPUTED_VALUE"""),"Georgetown") -> Georgetown | G50: =IFERROR(__xludf.DUMMYFUNCTION("""COMPUTED_VALUE"""),"TX") -> TX | H50: =IFERROR(__xludf.DUMMYFUNCTION("""COMPUTED_VALUE"""),"78628") -> 78628 | J50: =IFERROR(__xludf.DUMMYFUNCTION("""COMPUTED_VALUE"""),"30.7189464778299, -97.6780014967854") -> 30.7189464778299, -97.6780014967854 | K50: =IFERROR(__xludf.DUMMYFUNCTION("""COMPUTED_VALUE"""),"{""regular"":[{""days"":[""Mo"",""Tu"",""We"",""Th"",""Fr""],""open"":null,""close"":null}]}") -> {"regular":[{"days":["Mo","Tu","We","Th","Fr"],"open":null,"close":null}]} | M50: =IFERROR(__xludf.DUMMYFUNCTION("""COMPUTED_VALUE"""),24.0) -> 24 | N50: =IFERROR(__xludf.DUMMYFUNCTION("""COMPUTED_VALUE"""),"Housing") -> Housing | O50: =IFERROR(__xludf.DUMMYFUNCTION("""COMPUTED_VALUE"""),1.0) -> 1 | P50: =IFERROR(__xludf.DUMMYFUNCTION("""COMPUTED_VALUE"""),"ACTIVE") -> ACTIVE | Q50: =IFERROR(__xludf.DUMMYFUNCTION("""COMPUTED_VALUE"""),45761.0) -> 45761 | R50: =IFERROR(__xludf.DUMMYFUNCTION("""COMPUTED_VALUE"""),"SVdP Church Help for Moms Ministry") -> SVdP Church Help for Moms Ministry | S50: =IFERROR(__xludf.DUMMYFUNCTION("""COMPUTED_VALUE"""),"Housing and related services for women facing unplanned pregnancies. Educational opportunities Health services") -> Housing and related services for women facing unplanned pregnancies. Educational opportunities Health services | T50: =IFERROR(__xludf.DUMMYFUNCTION("""COMPUTED_VALUE"""),FALSE) -> FALSE | U50: =IFERROR(__xludf.DUMMYFUNCTION("""COMPUTED_VALUE"""),FALSE) -> FALSE | V50: =IFERROR(__xludf.DUMMYFUNCTION("""COMPUTED_VALUE"""),"https://wp.thematernityhome.org/") -> https://wp.thematernityhome.org/ | W50: =IFERROR(__xludf.DUMMYFUNCTION("""COMPUTED_VALUE"""),"https://www.google.com/maps/place/Annunciation+Maternity+Home/@30.715947,-97.6779099,16z/data=!3m1!4b1!4m6!3m5!1s0x8645290abe886bc3:0x37691a5b7468dd82!8m2!3d30.715947!4d-97.675335!16s%2Fg%2F11xln2gz0?entry=ttu&g_ep=EgoyMDI1MDQwOS4wIKXMDSoASAFQAw%3D%3D") -> https://www.google.com/maps/place/Annunciation+Maternity+Home/@30.715947,-97.6779099,16z/data=!3m1!4b1!4m6!3m5!1s0x8645290abe886bc3:0x37691a5b7468dd82!8m2!3d30.715947!4d-97.675335!16s%2Fg%2F11xln2gz0?entry=ttu&g_ep=EgoyMDI1MDQwOS4wIKXMDSoASAFQAw%3D%3D | Y50: =IFERROR(__xludf.DUMMYFUNCTION("""COMPUTED_VALUE"""),"Georgetown") -> Georgetown | Z50: =IFERROR(__xludf.DUMMYFUNCTION("""COMPUTED_VALUE"""),"Georgetown") -> Georgetown | AA50: =IFERROR(__xludf.DUMMYFUNCTION("""COMPUTED_VALUE"""),"Annunciation Maternity Home") -> Annunciation Maternity Home | AB50: =IFERROR(__xludf.DUMMYFUNCTION("""COMPUTED_VALUE"""),"Georgetown") -> Georgetown
